Workbook

Sheet Controle de NF - SETEMBRO
B1: 21.515.602/0001-51
A2: Mês | B2: CNPJ | C2: Fornecedor | D2: Gestor Adm | E2: NF | F2: Emissão da NF | G2: Valor da NF | H2: Conferência | I2: Observação | J2: SLA
A3: 45910 | B3: 01609514000101 | C3: =VLOOKUP(B3,Fornecedores!A:B,2,0) -> E-HUNTER TECNOLOGIA DA INFORMAÇÃO LTDA | D3: Sunara | E3: 00005513 | F3: 45901 | G3: 2614 | H3: =VLOOKUP(E3&B3,'Conf Oracle'!A:F,6,0) -> 45926.573 | J3: =IF(OR(ISBLANK(F3), ISBLANK(H3)), "", IFERROR(NETWORKDAYS(F3, H3), "")) -> 20
A4: 45910 | B4: 23412247000110 | C4: =VLOOKUP(B4,Fornecedores!A:B,2,0) -> AMAZON AWS SERVICOS BRASIL LTDA | D4: Ingrid | E4: 91696365 | F4: 45901 | G4: 114905.83 | H4: =VLOOKUP(E4&B4,'Conf Oracle'!A:F,6,0) -> #N/A | I4: Invoice NFs 04729432 e 04729425 | J4: =IF(OR(ISBLANK(F4), ISBLANK(H4)), "", IFERROR(NETWORKDAYS(F4, H4), ""))
A5: 45910 | B5: 09162855000517 | C5: =VLOOKUP(B5,Fornecedores!A:B,2,0) -> PTLS SERV TECNOLOGIA E ASSESS TECN LTDA | D5: Sunara | E5: 00219477 | F5: 45901 | G5: 30803.59 | H5: =VLOOKUP(E5&B5,'Conf Oracle'!A:F,6,0) -> 45915.691 | J5: =IF(OR(ISBLANK(F5), ISBLANK(H5)), "", IFERROR(NETWORKDAYS(F5, H5), "")) -> 11
A6: 45910 | B6: 02279806000196 | C6: =VLOOKUP(B6,Fornecedores!A:B,2,0) -> DAIMON ENGENHARIA E SISTEMAS S/S LTDA | D6: Sunara | E6: 00005097 | F6: 45902 | G6: 18982.5 | H6: =VLOOKUP(E6&B6,'Conf Oracle'!A:F,6,0) -> 45911.671 | J6: =IF(OR(ISBLANK(F6), ISBLANK(H6)), "", IFERROR(NETWORKDAYS(F6, H6), "")) -> 8
A7: 45910 | B7: 13617051000109 | C7: =VLOOKUP(B7,Fornecedores!A:B,2,0) -> COMPLEMENTO CONSULTORIA E TECNOLOGIA LTDA | D7: Sunara | E7: 00000500 | F7: 45903 | G7: 9600 | H7: =VLOOKUP(E7&B7,'Conf Oracle'!A:F,6,0) -> 45911.362 | J7: =IF(OR(ISBLANK(F7), ISBLANK(H7)), "", IFERROR(NETWORKDAYS(F7, H7), "")) -> 7
A8: 45910 | B8: 33541368000116 | C8: =VLOOKUP(B8,Fornecedores!A:B,2,0) -> CIA HIDRO ELETRICA SAO FRANCISCO - CHESF | D8: Sunara | E8: 00044496 | F8: 45903 | G8: 4011.82 | H8: =VLOOKUP(E8&B8,'Conf Oracle'!A:F,6,0) -> #N/A | I8: OC_0011253 - LANÇADA | J8: =IF(OR(ISBLANK(F8), ISBLANK(H8)), "", IFERROR(NETWORKDAYS(F8, H8), ""))
A9: 45910 | B9: 82703331000152 | C9: =VLOOKUP(B9,Fornecedores!A:B,2,0) -> MRTS CONSULTORIA E ENGENHARIA LTDA ME | D9: Sunara | E9: 00001310 | F9: 45909 | G9: 18982.5 | H9: =VLOOKUP(E9&B9,'Conf Oracle'!A:F,6,0) -> 45916.665 | J9: =IF(OR(ISBLANK(F9), ISBLANK(H9)), "", IFERROR(NETWORKDAYS(F9, H9), "")) -> 6
A10: 45910 | B10: 82703331000152 | C10: =VLOOKUP(B10,Fornecedores!A:B,2,0) -> MRTS CONSULTORIA E ENGENHARIA LTDA ME | D10: Sunara | E10: 00001311 | F10: 45909 | G10: 18982.5 | H10: =VLOOKUP(E10&B10,'Conf Oracle'!A:F,6,0) -> 45916.673 | J10: =IF(OR(ISBLANK(F10), ISBLANK(H10)), "", IFERROR(NETWORKDAYS(F10, H10), "")) -> 6
A11: 45910 | B11: 05217065000107 | C11: =VLOOKUP(B11,Fornecedores!A:B,2,0) -> ARVP CONSULTORIA E CAPACITACAO LTDA | D11: Pedro | E11: 00001083 | F11: 45901 | G11: 38410.07 | H11: =VLOOKUP(E11&B11,'Conf Oracle'!A:F,6,0) -> 45918.676 | J11: =IF(OR(ISBLANK(F11), ISBLANK(H11)), "", IFERROR(NETWORKDAYS(F11, H11), "")) -> 14
A12: 45910 | B12: 81785545000152 | C12: =VLOOKUP(B12,Fornecedores!A:B,2,0) -> DEL GRANDE INFO E TELEC IND E COM LTDA | D12: Pedro | E12: 00004449 | F12: 45901 | G12: 3151.24 | H12: =VLOOKUP(E12&B12,'Conf Oracle'!A:F,6,0) -> 45918.666 | J12: =IF(OR(ISBLANK(F12), ISBLANK(H12)), "", IFERROR(NETWORKDAYS(F12, H12), "")) -> 14
A13: 45910 | B13: 81785545000152 | C13: =VLOOKUP(B13,Fornecedores!A:B,2,0) -> DEL GRANDE INFO E TELEC IND E COM LTDA | D13: Pedro | E13: 00004448 | F13: 45901 | G13: 1618.7 | H13: =VLOOKUP(E13&B13,'Conf Oracle'!A:F,6,0) -> 45918.675 | J13: =IF(OR(ISBLANK(F13), ISBLANK(H13)), "", IFERROR(NETWORKDAYS(F13, H13), "")) -> 14
A14: 45910 | B14: 81785545000152 | C14: =VLOOKUP(B14,Fornecedores!A:B,2,0) -> DEL GRANDE INFO E TELEC IND E COM LTDA | D14: Pedro | E14: 00004447 | F14: 45901 | G14: 5077 | H14: =VLOOKUP(E14&B14,'Conf Oracle'!A:F,6,0) -> 45918.671 | J14: =IF(OR(ISBLANK(F14), ISBLANK(H14)), "", IFERROR(NETWORKDAYS(F14, H14), "")) -> 14
A15: 45910 | B15: 81785545000152 | C15: =VLOOKUP(B15,Fornecedores!A:B,2,0) -> DEL GRANDE INFO E TELEC IND E COM LTDA | D15: Pedro | E15: 00004450 | F15: 45901 | G15: 2825.73 | H15: =VLOOKUP(E15&B15,'Conf Oracle'!A:F,6,0) -> 45918.661 | J15: =IF(OR(ISBLANK(F15), ISBLANK(H15)), "", IFERROR(NETWORKDAYS(F15, H15), "")) -> 14
A16: 45910 | B16: 82895327000133 | C16: =VLOOKUP(B16,Fornecedores!A:B,2,0) -> FUNDACAO DE ENSINO E ENGENHARIA DE SC | D16: Pedro | E16: 00009699 | F16: 45902 | G16: 53333.33 | H16: =VLOOKUP(E16&B16,'Conf Oracle'!A:F,6,0) -> 45918.693 | J16: =IF(OR(ISBLANK(F16), ISBLANK(H16)), "", IFERROR(NETWORKDAYS(F16, H16), "")) -> 13
A17: 45910 | B17: 04732840000108 | C17: =VLOOKUP(B17,Fornecedores!A:B,2,0) -> CONCERT TECHNOLOGIES S.A. | D17: Pedro | E17: 00003247 | F17: 45903 | G17: 60000 | H17: =VLOOKUP(E17&B17,'Conf Oracle'!A:F,6,0) -> 45918.68 | J17: =IF(OR(ISBLANK(F17), ISBLANK(H17)), "", IFERROR(NETWORKDAYS(F17, H17), "")) -> 12
A18: 45910 | B18: 30608514000195 | C18: =VLOOKUP(B18,Fornecedores!A:B,2,0) -> AGENCIA FR DE COMUNICACAO LTDA | D18: Pedro | E18: 00004493 | F18: 45904 | G18: 39746.37 | H18: =VLOOKUP(E18&B18,'Conf Oracle'!A:F,6,0) -> #N/A | J18: =IF(OR(ISBLANK(F18), ISBLANK(H18)), "", IFERROR(NETWORKDAYS(F18, H18), ""))
A19: 45910 | B19: 10791466000106 | C19: =VLOOKUP(B19,Fornecedores!A:B,2,0) -> RPT.ESTRATEGIA CONSULTORIA LTDA | D19: Pedro | E19: 00001129 | F19: 45908 | G19: 11250 | H19: =VLOOKUP(E19&B19,'Conf Oracle'!A:F,6,0) -> #N/A | J19: =IF(OR(ISBLANK(F19), ISBLANK(H19)), "", IFERROR(NETWORKDAYS(F19, H19), ""))
A20: 45910 | B20: 42288886000160 | C20: =VLOOKUP(B20,Fornecedores!A:B,2,0) -> CENTRO DE PESQUISA DE ENERGIA ELET CEPEL | D20: Pedro | E20: 00017311 | F20: 45909 | G20: 117356.88 | H20: =VLOOKUP(E20&B20,'Conf Oracle'!A:F,6,0) -> #N/A | J20: =IF(OR(ISBLANK(F20), ISBLANK(H20)), "", IFERROR(NETWORKDAYS(F20, H20), ""))
... A24: 45911 | B24: 42288886000160 | C24: =VLOOKUP(B24,Fornecedores!A:B,2,0) -> CENTRO DE PESQUISA DE ENERGIA ELET CEPEL | D24: Pedro | E24: 00017314 | F24: 45909 | G24: 55700 | H24: =VLOOKUP(E24&B24,'Conf Oracle'!A:F,6,0) -> #N/A | J24: =IF(OR(ISBLANK(F24), ISBLANK(H24)), "", IFERROR(NETWORKDAYS(F24, H24), ""))
A25: 45911 | B25: 15667402000111 | C25: =VLOOKUP(B25,Fornecedores!A:B,2,0) -> SIMPLE ENERGY ASSESSORIA E GESTAO DE ENERGIA LTDA. | D25: Evandrea | E25: 00022639 | F25: 45902 | G25: 733.38 | H25: =VLOOKUP(E25&B25,'Conf Oracle'!A:F,6,0) -> 45919.386 | I25: lançada | J25: =IF(OR(ISBLANK(F25), ISBLANK(H25)), "", IFERROR(NETWORKDAYS(F25, H25), "")) -> 14
A26: 45911 | B26: 15667402000111 | C26: =VLOOKUP(B26,Fornecedores!A:B,2,0) -> SIMPLE ENERGY ASSESSORIA E GESTAO DE ENERGIA LTDA. | D26: Evandrea | E26: 00022643 | F26: 45902 | G26: 733.38 | H26: =VLOOKUP(E26&B26,'Conf Oracle'!A:F,6,0) -> 45919.407 | I26: lançada | J26: =IF(OR(ISBLANK(F26), ISBLANK(H26)), "", IFERROR(NETWORKDAYS(F26, H26), "")) -> 14
A27: 45911 | B27: 15667402000111 | C27: =VLOOKUP(B27,Fornecedores!A:B,2,0) -> SIMPLE ENERGY ASSESSORIA E GESTAO DE ENERGIA LTDA. | D27: Evandrea | E27: 00022646 | F27: 45902 | G27: 733.38 | H27: =VLOOKUP(E27&B27,'Conf Oracle'!A:F,6,0) -> 45919.402 | I27: lançada | J27: =IF(OR(ISBLANK(F27), ISBLANK(H27)), "", IFERROR(NETWORKDAYS(F27, H27), "")) -> 14
A28: 45911 | B28: 15667402000111 | C28: =VLOOKUP(B28,Fornecedores!A:B,2,0) -> SIMPLE ENERGY ASSESSORIA E GESTAO DE ENERGIA LTDA. | D28: Evandrea | E28: 00022645 | F28: 45902 | G28: 733.38 | H28: =VLOOKUP(E28&B28,'Conf Oracle'!A:F,6,0) -> 45919.633 | I28: lançada | J28: =IF(OR(ISBLANK(F28), ISBLANK(H28)), "", IFERROR(NETWORKDAYS(F28, H28), "")) -> 14
A29: 45911 | B29: 00001180000126 | C29: =VLOOKUP(B29,Fornecedores!A:B,2,0) -> Centrais Elétricas Brasileiras S/A - Eletrobras | D29: Evandrea | E29: 00059757 | F29: 45903 | G29: 18749.39 | H29: =VLOOKUP(E29&B29,'Conf Oracle'!A:F,6,0) -> 45908.579 | J29: =IF(OR(ISBLANK(F29), ISBLANK(H29)), "", IFERROR(NETWORKDAYS(F29, H29), "")) -> 4
A30: 45911 | B30: 00001180000126 | C30: =VLOOKUP(B30,Fornecedores!A:B,2,0) -> Centrais Elétricas Brasileiras S/A - Eletrobras | D30: Evandrea | E30: 00059755 | F30: 45903 | G30: 85391.74 | H30: =VLOOKUP(E30&B30,'Conf Oracle'!A:F,6,0) -> 45908.561 | J30: =IF(OR(ISBLANK(F30), ISBLANK(H30)), "", IFERROR(NETWORKDAYS(F30, H30), "")) -> 4
A31: 45911 | B31: 00001180000126 | C31: =VLOOKUP(B31,Fornecedores!A:B,2,0) -> Centrais Elétricas Brasileiras S/A - Eletrobras | D31: Evandrea | E31: 00059754 | F31: 45903 | G31: 59329.76 | H31: =VLOOKUP(E31&B31,'Conf Oracle'!A:F,6,0) -> 45908.552 | J31: =IF(OR(ISBLANK(F31), ISBLANK(H31)), "", IFERROR(NETWORKDAYS(F31, H31), "")) -> 4
A32: 45911 | B32: 00001180000126 | C32: =VLOOKUP(B32,Fornecedores!A:B,2,0) -> Centrais Elétricas Brasileiras S/A - Eletrobras | D32: Evandrea | E32: 00059756 | F32: 45903 | G32: 36415.67 | H32: =VLOOKUP(E32&B32,'Conf Oracle'!A:F,6,0) -> 45908.566 | J32: =IF(OR(ISBLANK(F32), ISBLANK(H32)), "", IFERROR(NETWORKDAYS(F32, H32), "")) -> 4
A33: 45911 | B33: 60444437000146 | C33: =VLOOKUP(B33,Fornecedores!A:B,2,0) -> LIGHT SERV. DE ELETRICIDADE SA | D33: Evandrea | E33: 00292749 | F33: 45901 | G33: 140022.94 | H33: =VLOOKUP(E33&B33,'Conf Oracle'!A:F,6,0) -> #N/A | I33: Lançada | J33: =IF(OR(ISBLANK(F33), ISBLANK(H33)), "", IFERROR(NETWORKDAYS(F33, H33), ""))
A34: 45911 | B34: 57623555000107 | C34: =VLOOKUP(B34,Fornecedores!A:B,2,0) -> MAGICCOMP ENG E SERV DE INFORMATICA LTDA | D34: Jessy | E34: 00055887 | F34: 45901 | G34: 49705.57 | H34: =VLOOKUP(E34&B34,'Conf Oracle'!A:F,6,0) -> #N/A | I34: OC_0011447- NF 00055887 substituida para 55955 | J34: =IF(OR(ISBLANK(F34), ISBLANK(H34)), "", IFERROR(NETWORKDAYS(F34, H34), ""))
A35: 45911 | B35: 57623555000107 | C35: =VLOOKUP(B35,Fornecedores!A:B,2,0) -> MAGICCOMP ENG E SERV DE INFORMATICA LTDA | D35: Jessy | E35: 00055888 | F35: 45901 | G35: 49705.57 | H35: =VLOOKUP(E35&B35,'Conf Oracle'!A:F,6,0) -> 45918.449 | I35: OC_0011332 | J35: =IF(OR(ISBLANK(F35), ISBLANK(H35)), "", IFERROR(NETWORKDAYS(F35, H35), "")) -> 14
A36: 45911 | B36: 57623555000107 | C36: =VLOOKUP(B36,Fornecedores!A:B,2,0) -> MAGICCOMP ENG E SERV DE INFORMATICA LTDA | D36: Jessy | E36: 00055889 | F36: 45901 | G36: 72500 | H36: =VLOOKUP(E36&B36,'Conf Oracle'!A:F,6,0) -> 45925.352 | I36: OC_0011452 | J36: =IF(OR(ISBLANK(F36), ISBLANK(H36)), "", IFERROR(NETWORKDAYS(F36, H36), "")) -> 19
A37: 45911 | B37: 57623555000107 | C37: =VLOOKUP(B37,Fornecedores!A:B,2,0) -> MAGICCOMP ENG E SERV DE INFORMATICA LTDA | D37: Jessy | E37: 00055882 | F37: 45901 | G37: 27750 | H37: =VLOOKUP(E37&B37,'Conf Oracle'!A:F,6,0) -> 45916.623 | I37: ok | J37: =IF(OR(ISBLANK(F37), ISBLANK(H37)), "", IFERROR(NETWORKDAYS(F37, H37), "")) -> 12
A38: 45911 | B38: 57623555000107 | C38: =VLOOKUP(B38,Fornecedores!A:B,2,0) -> MAGICCOMP ENG E SERV DE INFORMATICA LTDA | D38: Jessy | E38: 00055883 | F38: 45901 | G38: 27750 | H38: =VLOOKUP(E38&B38,'Conf Oracle'!A:F,6,0) -> 45916.647 | I38: ok | J38: =IF(OR(ISBLANK(F38), ISBLANK(H38)), "", IFERROR(NETWORKDAYS(F38, H38), "")) -> 12
A39: 45911 | B39: 57623555000107 | C39: =VLOOKUP(B39,Fornecedores!A:B,2,0) -> MAGICCOMP ENG E SERV DE INFORMATICA LTDA | D39: Jessy | E39: 00055884 | F39: 45901 | G39: 27750 | H39: =VLOOKUP(E39&B39,'Conf Oracle'!A:F,6,0) -> 45916.649 | I39: ok | J39: =IF(OR(ISBLANK(F39), ISBLANK(H39)), "", IFERROR(NETWORKDAYS(F39, H39), "")) -> 12
A40: 45911 | B40: 57623555000107 | C40: =VLOOKUP(B40,Fornecedores!A:B,2,0) -> MAGICCOMP ENG E SERV DE INFORMATICA LTDA | D40: Jessy | E40: 00055885 | F40: 45901 | G40: 27750 | H40: =VLOOKUP(E40&B40,'Conf Oracle'!A:F,6,0) -> 45916.644 | I40: ok | J40: =IF(OR(ISBLANK(F40), ISBLANK(H40)), "", IFERROR(NETWORKDAYS(F40, H40), "")) -> 12
A41: 45911 | B41: 21356354000143 | C41: =VLOOKUP(B41,Fornecedores!A:B,2,0) -> POPULOS TECNOLOGIA LTDA | D41: Jessy | E41: 00003062 | F41: 45901 | G41: 3118.52 | H41: =VLOOKUP(E41&B41,'Conf Oracle'!A:F,6,0) -> 45915.657 | I41: ok | J41: =IF(OR(ISBLANK(F41), ISBLANK(H41)), "", IFERROR(NETWORKDAYS(F41, H41), "")) -> 11
A42: 45911 | B42: 51886784000138 | C42: =VLOOKUP(B42,Fornecedores!A:B,2,0) -> EASY 5 SOLUCOES LTDA | D42: Jessy | E42: 00000638 | F42: 45901 | G42: 20800 | H42: =VLOOKUP(E42&B42,'Conf Oracle'!A:F,6,0) -> 45916.422 | I42: ok | J42: =IF(OR(ISBLANK(F42), ISBLANK(H42)), "", IFERROR(NETWORKDAYS(F42, H42), "")) -> 12
A43: 45911 | B43: 51886784000138 | C43: =VLOOKUP(B43,Fornecedores!A:B,2,0) -> EASY 5 SOLUCOES LTDA | D43: Jessy | E43: 00000637 | F43: 45901 | G43: 20800 | H43: =VLOOKUP(E43&B43,'Conf Oracle'!A:F,6,0) -> 45916.43 | I43: ok | J43: =IF(OR(ISBLANK(F43), ISBLANK(H43)), "", IFERROR(NETWORKDAYS(F43, H43), "")) -> 12
A44: 45911 | B44: 51886784000138 | C44: =VLOOKUP(B44,Fornecedores!A:B,2,0) -> EASY 5 SOLUCOES LTDA | D44: Jessy | E44: 00000636 | F44: 45901 | G44: 20800 | H44: =VLOOKUP(E44&B44,'Conf Oracle'!A:F,6,0) -> 45916.433 | I44: ok | J44: =IF(OR(ISBLANK(F44), ISBLANK(H44)), "", IFERROR(NETWORKDAYS(F44, H44), "")) -> 12
... A52: 45911 | B52: 72381189000110 | C52: =VLOOKUP(B52,Fornecedores!A:B,2,0) -> DELL COMPUTADORES DO BRASIL LTDA | D52: Jessy | E52: 02831939 | F52: 45905 | G52: 22560.71 | H52: =VLOOKUP(E52&B52,'Conf Oracle'!A:F,6,0) -> 45911.366 | I52: ok | J52: =IF(OR(ISBLANK(F52), ISBLANK(H52)), "", IFERROR(NETWORKDAYS(F52, H52), "")) -> 5
A53: 45911 | B53: 09554428000150 | C53: =VLOOKUP(B53,Fornecedores!A:B,2,0) -> STAEFA SERVICOS DE MANUTENCAO PREDIAL LTDA | D53: Guilherme | E53: 00000570 | F53: 45908 | G53: 20363.63 | H53: =VLOOKUP(E53&B53,'Conf Oracle'!A:F,6,0) -> 45926.417 | J53: =IF(OR(ISBLANK(F53), ISBLANK(H53)), "", IFERROR(NETWORKDAYS(F53, H53), "")) -> 15
A54: 45911 | B54: 08689542000125 | C54: =VLOOKUP(B54,Fornecedores!A:B,2,0) -> VOCS MULTIMIDIA PROD AUDIO VID LTDA EPP | D54: Jessy | E54: 00003453 | F54: 45911 | G54: 3978 | H54: =VLOOKUP(E54&B54,'Conf Oracle'!A:F,6,0) -> 45929.645 | I54: Compra delegada | J54: =IF(OR(ISBLANK(F54), ISBLANK(H54)), "", IFERROR(NETWORKDAYS(F54, H54), "")) -> 13
A55: 45911 | B55: 05217065000107 | C55: =VLOOKUP(B55,Fornecedores!A:B,2,0) -> ARVP CONSULTORIA E CAPACITACAO LTDA | D55: Pedro | E55: 00001087 | F55: 45910 | G55: 38410.07 | H55: =VLOOKUP(E55&B55,'Conf Oracle'!A:F,6,0) -> 45918.673 | J55: =IF(OR(ISBLANK(F55), ISBLANK(H55)), "", IFERROR(NETWORKDAYS(F55, H55), "")) -> 7
A56: 45911 | B56: 14793051000122 | C56: =VLOOKUP(B56,Fornecedores!A:B,2,0) -> TORTORO MADUREIRA E RAGAZZI SOCADVOGAD | D56: Isabela | E56: 00010191 | F56: 45901 | G56: 1500 | H56: =VLOOKUP(E56&B56,'Conf Oracle'!A:F,6,0) -> 45922.679 | I56: Lançada | J56: =IF(OR(ISBLANK(F56), ISBLANK(H56)), "", IFERROR(NETWORKDAYS(F56, H56), "")) -> 16
A57: 45911 | B57: 26409092000151 | C57: =VLOOKUP(B57,Fornecedores!A:B,2,0) -> SSAMRO SOLUCOES PARA MANUTENCAO INDUSTR | D57: Isabela | E57: 00026093 | F57: 45902 | G57: 648.76 | H57: =VLOOKUP(E57&B57,'Conf Oracle'!A:F,6,0) -> 45911.675 | J57: =IF(OR(ISBLANK(F57), ISBLANK(H57)), "", IFERROR(NETWORKDAYS(F57, H57), "")) -> 8
A58: 45911 | B58: 26409092000151 | C58: =VLOOKUP(B58,Fornecedores!A:B,2,0) -> SSAMRO SOLUCOES PARA MANUTENCAO INDUSTR | D58: Isabela | E58: 00026094 | F58: 45902 | G58: 648.76 | H58: =VLOOKUP(E58&B58,'Conf Oracle'!A:F,6,0) -> 45904.583 | J58: =IF(OR(ISBLANK(F58), ISBLANK(H58)), "", IFERROR(NETWORKDAYS(F58, H58), "")) -> 3
A59: 45911 | B59: 26409092000151 | C59: =VLOOKUP(B59,Fornecedores!A:B,2,0) -> SSAMRO SOLUCOES PARA MANUTENCAO INDUSTR | D59: Isabela | E59: 00026097 | F59: 45902 | G59: 648.76 | H59: =VLOOKUP(E59&B59,'Conf Oracle'!A:F,6,0) -> 45904.595 | J59: =IF(OR(ISBLANK(F59), ISBLANK(H59)), "", IFERROR(NETWORKDAYS(F59, H59), "")) -> 3
A60: 45911 | B60: 26409092000151 | C60: =VLOOKUP(B60,Fornecedores!A:B,2,0) -> SSAMRO SOLUCOES PARA MANUTENCAO INDUSTR | D60: Isabela | E60: 00026096 | F60: 45902 | G60: 648.76 | H60: =VLOOKUP(E60&B60,'Conf Oracle'!A:F,6,0) -> 45904.585 | J60: =IF(OR(ISBLANK(F60), ISBLANK(H60)), "", IFERROR(NETWORKDAYS(F60, H60), "")) -> 3
A61: 45911 | B61: 15491115000101 | C61: =VLOOKUP(B61,Fornecedores!A:B,2,0) -> CS INTEGRA SOLUCOES EM TECNOLOG LTDA ME | D61: Isabela | E61: 00006498 | F61: 45902 | G61: 3093 | H61: =VLOOKUP(E61&B61,'Conf Oracle'!A:F,6,0) -> 45904.628 | J61: =IF(OR(ISBLANK(F61), ISBLANK(H61)), "", IFERROR(NETWORKDAYS(F61, H61), "")) -> 3
A62: 45911 | B62: 72157654000215 | C62: =VLOOKUP(B62,Fornecedores!A:B,2,0) -> VELA SOFTWARE E SERVICOS LTDA | D62: Isabela | E62: 00016043 | F62: 45903 | G62: 677.6 | H62: =VLOOKUP(E62&B62,'Conf Oracle'!A:F,6,0) -> #N/A | I62: Lançada | J62: =IF(OR(ISBLANK(F62), ISBLANK(H62)), "", IFERROR(NETWORKDAYS(F62, H62), ""))
A63: 45911 | B63: 72157654000215 | C63: =VLOOKUP(B63,Fornecedores!A:B,2,0) -> VELA SOFTWARE E SERVICOS LTDA | D63: Isabela | E63: 00016044 | F63: 45903 | G63: 677.6 | H63: =VLOOKUP(E63&B63,'Conf Oracle'!A:F,6,0) -> #N/A | I63: Lançada | J63: =IF(OR(ISBLANK(F63), ISBLANK(H63)), "", IFERROR(NETWORKDAYS(F63, H63), ""))
A64: 45911 | B64: 72157654000215 | C64: =VLOOKUP(B64,Fornecedores!A:B,2,0) -> VELA SOFTWARE E SERVICOS LTDA | D64: Isabela | E64: 00016045 | F64: 45903 | G64: 677.6 | H64: =VLOOKUP(E64&B64,'Conf Oracle'!A:F,6,0) -> #N/A | I64: Lançada | J64: =IF(OR(ISBLANK(F64), ISBLANK(H64)), "", IFERROR(NETWORKDAYS(F64, H64), ""))
A65: 45911 | B65: 72157654000215 | C65: =VLOOKUP(B65,Fornecedores!A:B,2,0) -> VELA SOFTWARE E SERVICOS LTDA | D65: Isabela | E65: 00016046 | F65: 45903 | G65: 677.6 | H65: =VLOOKUP(E65&B65,'Conf Oracle'!A:F,6,0) -> #N/A | I65: Lançada | J65: =IF(OR(ISBLANK(F65), ISBLANK(H65)), "", IFERROR(NETWORKDAYS(F65, H65), ""))
A66: 45911 | B66: 22772012000177 | C66: =VLOOKUP(B66,Fornecedores!A:B,2,0) -> SPECIALISTERNE BRASIL CAPACITACAO EM SERVICOS RELACIONADOS A TECNOLOGIA, INFORMATICA E CONSULTORIA EMPRESARIAL LTDA. | D66: Isabela | E66: 00005005 | F66: 45903 | G66: 4000 | H66: =VLOOKUP(E66&B66,'Conf Oracle'!A:F,6,0) -> 45904.623 | J66: =IF(OR(ISBLANK(F66), ISBLANK(H66)), "", IFERROR(NETWORKDAYS(F66, H66), "")) -> 2
A67: 45911 | B67: 69034668000156 | C67: =VLOOKUP(B67,Fornecedores!A:B,2,0) -> PLUXEE BENEFICIOS BRASIL SA | D67: Isabela | E67: 05954374 | F67: 45903 | G67: 1066.91 | H67: =VLOOKUP(E67&B67,'Conf Oracle'!A:F,6,0) -> 45905.459 | J67: =IF(OR(ISBLANK(F67), ISBLANK(H67)), "", IFERROR(NETWORKDAYS(F67, H67), "")) -> 3
A68: 45911 | B68: 69034668000156 | C68: =VLOOKUP(B68,Fornecedores!A:B,2,0) -> PLUXEE BENEFICIOS BRASIL SA | D68: Isabela | E68: 05954372 | F68: 45903 | G68: 1981.41 | H68: =VLOOKUP(E68&B68,'Conf Oracle'!A:F,6,0) -> 45905.469 | J68: =IF(OR(ISBLANK(F68), ISBLANK(H68)), "", IFERROR(NETWORKDAYS(F68, H68), "")) -> 3
A69: 45911 | B69: 07751071000175 | C69: =VLOOKUP(B69,Fornecedores!A:B,2,0) -> TELEGESTAO SISTEMAS DE ATEND LTDA | D69: Isabela | E69: 00001353 | F69: 45904 | G69: 700 | H69: =VLOOKUP(E69&B69,'Conf Oracle'!A:F,6,0) -> 45905.5 | J69: =IF(OR(ISBLANK(F69), ISBLANK(H69)), "", IFERROR(NETWORKDAYS(F69, H69), "")) -> 2
A70: 45911 | B70: 463754 | C70: =VLOOKUP(B70,Fornecedores!A:B,2,0) -> LINKEDIN IRLAND UNLIMITED COMPANY | D70: Isabela | E70: 12639205 | F70: 45910 | G70: 12600 | H70: =VLOOKUP(E70&B70,'Conf Oracle'!A:F,6,0) -> #N/A | I70: Lançada | J70: =IF(OR(ISBLANK(F70), ISBLANK(H70)), "", IFERROR(NETWORKDAYS(F70, H70), ""))
A71: 45911 | B71: 64601925000502 | C71: =VLOOKUP(B71,Fornecedores!A:B,2,0) -> Tour House Viagens e Turismo LTDA-THV - Bragança | D71: Isabela | E71: 00655485 | F71: 45905 | G71: 2739.8 | H71: =VLOOKUP(E71&B71,'Conf Oracle'!A:F,6,0) -> #N/A | J71: =IF(OR(ISBLANK(F71), ISBLANK(H71)), "", IFERROR(NETWORKDAYS(F71, H71), ""))
A72: 45911 | B72: 47827415000105 | C72: =VLOOKUP(B72,Fornecedores!A:B,2,0) -> SAD CONSULTORIA LTDA | D72: Isabela | E72: 00126054 | F72: 45910 | G72: 18502.04 | H72: =VLOOKUP(E72&B72,'Conf Oracle'!A:F,6,0) -> 45912.608 | J72: =IF(OR(ISBLANK(F72), ISBLANK(H72)), "", IFERROR(NETWORKDAYS(F72, H72), "")) -> 3
A73: 45911 | B73: 47827415000105 | C73: =VLOOKUP(B73,Fornecedores!A:B,2,0) -> SAD CONSULTORIA LTDA | D73: Isabela | E73: 00126055 | F73: 45910 | G73: 122997.96 | H73: =VLOOKUP(E73&B73,'Conf Oracle'!A:F,6,0) -> 45915.494 | J73: =IF(OR(ISBLANK(F73), ISBLANK(H73)), "", IFERROR(NETWORKDAYS(F73, H73), "")) -> 4
A74: 45911 | B74: 33402892000106 | C74: =VLOOKUP(B74,Fornecedores!A:B,2,0) -> ASSOCIACAO BRASILEIRA DE NORMAS TECNICAS ABNT | D74: Isabela | E74: 00195656 | F74: 45911 | G74: 86950 | H74: =VLOOKUP(E74&B74,'Conf Oracle'!A:F,6,0) -> 45916.628 | J74: =IF(OR(ISBLANK(F74), ISBLANK(H74)), "", IFERROR(NETWORKDAYS(F74, H74), "")) -> 4
A75: 45911 | B75: 58652678000139 | C75: =VLOOKUP(B75,Fornecedores!A:B,2,0) -> COLUMBIA STORAGE INTEGR DE SITEMAS LTDA | D75: Ingrid | E75: 00011259 | F75: 45901 | G75: 17116.41 | H75: =VLOOKUP(E75&B75,'Conf Oracle'!A:F,6,0) -> 45924.612 | J75: =IF(OR(ISBLANK(F75), ISBLANK(H75)), "", IFERROR(NETWORKDAYS(F75, H75), "")) -> 18
A76: 45911 | B76: 07850212000107 | C76: =VLOOKUP(B76,Fornecedores!A:B,2,0) -> REAL SEGURANCA INTEGRADA EIRELI | D76: Ingrid | E76: 00001451 | F76: 45901 | G76: 217.9 | H76: =VLOOKUP(E76&B76,'Conf Oracle'!A:F,6,0) -> 45925.441 | J76: =IF(OR(ISBLANK(F76), ISBLANK(H76)), "", IFERROR(NETWORKDAYS(F76, H76), "")) -> 19
A77: 45911 | B77: 00005468 | C77: =VLOOKUP(B77,Fornecedores!A:B,2,0) -> AMAZON WEB SERVICES LLC | D77: Sunara | E77: 91767933 | F77: 45901 | G77: 0.06 | H77: =VLOOKUP(E77&B77,'Conf Oracle'!A:F,6,0) -> #N/A | I77: não será emitida ordem de compras | J77: =IF(OR(ISBLANK(F77), ISBLANK(H77)), "", IFERROR(NETWORKDAYS(F77, H77), ""))
A78: 45912 | B78: 23412247000110 | C78: =VLOOKUP(B78,Fornecedores!A:B,2,0) -> AMAZON AWS SERVICOS BRASIL LTDA | D78: Ingrid | E78: 91777545 | F78: 45901 | G78: 614930.62 | H78: =VLOOKUP(E78&B78,'Conf Oracle'!A:F,6,0) -> #N/A | I78: Invoice NF 04729714 | J78: =IF(OR(ISBLANK(F78), ISBLANK(H78)), "", IFERROR(NETWORKDAYS(F78, H78), ""))
A79: 45912 | B79: 23412247000110 | C79: =VLOOKUP(B79,Fornecedores!A:B,2,0) -> AMAZON AWS SERVICOS BRASIL LTDA | D79: Ingrid | E79: 04729432 | F79: 45901 | G79: 43090.96 | H79: =VLOOKUP(E79&B79,'Conf Oracle'!A:F,6,0) -> 45911.655 | J79: =IF(OR(ISBLANK(F79), ISBLANK(H79)), "", IFERROR(NETWORKDAYS(F79, H79), "")) -> 9
A80: 45912 | B80: 23412247000110 | C80: =VLOOKUP(B80,Fornecedores!A:B,2,0) -> AMAZON AWS SERVICOS BRASIL LTDA | D80: Ingrid | E80: 04729425 | F80: 45901 | G80: 71814.74 | H80: =VLOOKUP(E80&B80,'Conf Oracle'!A:F,6,0) -> 45911.65 | J80: =IF(OR(ISBLANK(F80), ISBLANK(H80)), "", IFERROR(NETWORKDAYS(F80, H80), "")) -> 9
A81: 45912 | B81: 23412247000110 | C81: =VLOOKUP(B81,Fornecedores!A:B,2,0) -> AMAZON AWS SERVICOS BRASIL LTDA | D81: Ingrid | E81: 04729714 | F81: 45901 | G81: 614933.24 | H81: =VLOOKUP(E81&B81,'Conf Oracle'!A:F,6,0) -> 45912.58 | J81: =IF(OR(ISBLANK(F81), ISBLANK(H81)), "", IFERROR(NETWORKDAYS(F81, H81), "")) -> 10
A82: 45912 | B82: 96534094000158 | C82: =VLOOKUP(B82,Fornecedores!A:B,2,0) -> ACCENTURE DO BRASIL LTDA | D82: Ingrid | E82: 00106079 | F82: 45903 | G82: 183243.6 | H82: =VLOOKUP(E82&B82,'Conf Oracle'!A:F,6,0) -> 45925.375 | J82: =IF(OR(ISBLANK(F82), ISBLANK(H82)), "", IFERROR(NETWORKDAYS(F82, H82), "")) -> 17
A83: 45912 | B83: 96534094000158 | C83: =VLOOKUP(B83,Fornecedores!A:B,2,0) -> ACCENTURE DO BRASIL LTDA | D83: Ingrid | E83: 00106081 | F83: 45903 | G83: 196295.88 | H83: =VLOOKUP(E83&B83,'Conf Oracle'!A:F,6,0) -> 45925.367 | J83: =IF(OR(ISBLANK(F83), ISBLANK(H83)), "", IFERROR(NETWORKDAYS(F83, H83), "")) -> 17
A84: 45912 | B84: 15423421000100 | C84: =VLOOKUP(B84,Fornecedores!A:B,2,0) -> ROSEANE SANTOS INFORMACOES CADASTRAIS LTDA | D84: Ingrid | E84: 00000103 | F84: 45902 | G84: 37000 | H84: =VLOOKUP(E84&B84,'Conf Oracle'!A:F,6,0) -> 45923.672 | J84: =IF(OR(ISBLANK(F84), ISBLANK(H84)), "", IFERROR(NETWORKDAYS(F84, H84), "")) -> 16
A85: 45912 | B85: 02558157013574 | C85: =VLOOKUP(B85,Fornecedores!A:B,2,0) -> TELEFONICA BRASIL SA | D85: Ingrid | E85: 00605139 | F85: 45909 | G85: 2522.64 | H85: =VLOOKUP(E85&B85,'Conf Oracle'!A:F,6,0) -> #N/A | I85: Em contestação | J85: =IF(OR(ISBLANK(F85), ISBLANK(H85)), "", IFERROR(NETWORKDAYS(F85, H85), ""))
A86: 45912 | B86: 02558157013574 | C86: =VLOOKUP(B86,Fornecedores!A:B,2,0) -> TELEFONICA BRASIL SA | D86: Ingrid | E86: 00608359 | F86: 45909 | G86: 1581.56 | H86: =VLOOKUP(E86&B86,'Conf Oracle'!A:F,6,0) -> #N/A | I86: Em contestação | J86: =IF(OR(ISBLANK(F86), ISBLANK(H86)), "", IFERROR(NETWORKDAYS(F86, H86), ""))
A87: 45912 | B87: 02558157013574 | C87: =VLOOKUP(B87,Fornecedores!A:B,2,0) -> TELEFONICA BRASIL SA | D87: Ingrid | E87: 00608357 | F87: 45909 | G87: 191.27 | H87: =VLOOKUP(E87&B87,'Conf Oracle'!A:F,6,0) -> #N/A | I87: Em contestação | J87: =IF(OR(ISBLANK(F87), ISBLANK(H87)), "", IFERROR(NETWORKDAYS(F87, H87), ""))
A88: 45912 | B88: 02558157013574 | C88: =VLOOKUP(B88,Fornecedores!A:B,2,0) -> TELEFONICA BRASIL SA | D88: Ingrid | E88: 00605140 | F88: 45909 | G88: 3167.16 | H88: =VLOOKUP(E88&B88,'Conf Oracle'!A:F,6,0) -> #N/A | I88: Em contestação | J88: =IF(OR(ISBLANK(F88), ISBLANK(H88)), "", IFERROR(NETWORKDAYS(F88, H88), ""))
A89: 45912 | B89: 02558157013574 | C89: =VLOOKUP(B89,Fornecedores!A:B,2,0) -> TELEFONICA BRASIL SA | D89: Ingrid | E89: 00605141 | F89: 45909 | G89: 1657.98 | H89: =VLOOKUP(E89&B89,'Conf Oracle'!A:F,6,0) -> #N/A | I89: Em contestação | J89: =IF(OR(ISBLANK(F89), ISBLANK(H89)), "", IFERROR(NETWORKDAYS(F89, H89), ""))
A90: 45912 | B90: 02558157013574 | C90: =VLOOKUP(B90,Fornecedores!A:B,2,0) -> TELEFONICA BRASIL SA | D90: Ingrid | E90: 00608446 | F90: 45909 | G90: 360 | H90: =VLOOKUP(E90&B90,'Conf Oracle'!A:F,6,0) -> #N/A | I90: Em contestação | J90: =IF(OR(ISBLANK(F90), ISBLANK(H90)), "", IFERROR(NETWORKDAYS(F90, H90), ""))
A91: 45912 | B91: 02558157013574 | C91: =VLOOKUP(B91,Fornecedores!A:B,2,0) -> TELEFONICA BRASIL SA | D91: Ingrid | E91: 00608447 | F91: 45909 | G91: 1169.59 | H91: =VLOOKUP(E91&B91,'Conf Oracle'!A:F,6,0) -> #N/A | I91: Em contestação | J91: =IF(OR(ISBLANK(F91), ISBLANK(H91)), "", IFERROR(NETWORKDAYS(F91, H91), ""))
A92: 45912 | B92: 02558157013574 | C92: =VLOOKUP(B92,Fornecedores!A:B,2,0) -> TELEFONICA BRASIL SA | D92: Ingrid | E92: 00608448 | F92: 45909 | G92: 929.67 | H92: =VLOOKUP(E92&B92,'Conf Oracle'!A:F,6,0) -> #N/A | I92: Em contestação | J92: =IF(OR(ISBLANK(F92), ISBLANK(H92)), "", IFERROR(NETWORKDAYS(F92, H92), ""))
A93: 45912 | B93: 02558157013574 | C93: =VLOOKUP(B93,Fornecedores!A:B,2,0) -> TELEFONICA BRASIL SA | D93: Ingrid | E93: 00608445 | F93: 45909 | G93: 1080 | H93: =VLOOKUP(E93&B93,'Conf Oracle'!A:F,6,0) -> #N/A | I93: Em contestação | J93: =IF(OR(ISBLANK(F93), ISBLANK(H93)), "", IFERROR(NETWORKDAYS(F93, H93), ""))
A94: 45912 | B94: 02558157013574 | C94: =VLOOKUP(B94,Fornecedores!A:B,2,0) -> TELEFONICA BRASIL SA | D94: Ingrid | E94: 00608358 | F94: 45909 | G94: 180 | H94: =VLOOKUP(E94&B94,'Conf Oracle'!A:F,6,0) -> #N/A | I94: Em contestação | J94: =IF(OR(ISBLANK(F94), ISBLANK(H94)), "", IFERROR(NETWORKDAYS(F94, H94), ""))
A95: 45912 | B95: 02558157013574 | C95: =VLOOKUP(B95,Fornecedores!A:B,2,0) -> TELEFONICA BRASIL SA | D95: Ingrid | E95: 00609572 | F95: 45909 | G95: 915.86 | H95: =VLOOKUP(E95&B95,'Conf Oracle'!A:F,6,0) -> #N/A | I95: Em contestação | J95: =IF(OR(ISBLANK(F95), ISBLANK(H95)), "", IFERROR(NETWORKDAYS(F95, H95), ""))
A96: 45912 | B96: 20099142000165 | C96: =VLOOKUP(B96,Fornecedores!A:B,2,0) -> RECOLD SERVICOS DE REFRIGERACAO INDUSTRIAL E HVAC EIRELI | D96: Guilherme | E96: 00002770 | F96: 45901 | G96: 96477 | H96: =VLOOKUP(E96&B96,'Conf Oracle'!A:F,6,0) -> 45905.675 | J96: =IF(OR(ISBLANK(F96), ISBLANK(H96)), "", IFERROR(NETWORKDAYS(F96, H96), "")) -> 5
A97: 45912 | B97: 34151100000300 | C97: =VLOOKUP(B97,Fornecedores!A:B,2,0) -> SOTREQ SA | D97: Guilherme | E97: 00475741 | F97: 45904 | G97: 2132.92 | H97: =VLOOKUP(E97&B97,'Conf Oracle'!A:F,6,0) -> #N/A | J97: =IF(OR(ISBLANK(F97), ISBLANK(H97)), "", IFERROR(NETWORKDAYS(F97, H97), ""))
A98: 45912 | B98: 09554428000150 | C98: =VLOOKUP(B98,Fornecedores!A:B,2,0) -> STAEFA SERVICOS DE MANUTENCAO PREDIAL LTDA | D98: Guilherme | E98: 00000566 | F98: 45905 | G98: 9631.44 | H98: =VLOOKUP(E98&B98,'Conf Oracle'!A:F,6,0) -> 45926.445 | J98: =IF(OR(ISBLANK(F98), ISBLANK(H98)), "", IFERROR(NETWORKDAYS(F98, H98), "")) -> 16
A99: 45912 | B99: 09554428000150 | C99: =VLOOKUP(B99,Fornecedores!A:B,2,0) -> STAEFA SERVICOS DE MANUTENCAO PREDIAL LTDA | D99: Guilherme | E99: 00000568 | F99: 45905 | G99: 39078 | H99: =VLOOKUP(E99&B99,'Conf Oracle'!A:F,6,0) -> 45926.388 | J99: =IF(OR(ISBLANK(F99), ISBLANK(H99)), "", IFERROR(NETWORKDAYS(F99, H99), "")) -> 16
A100: 45912 | B100: 09554428000150 | C100: =VLOOKUP(B100,Fornecedores!A:B,2,0) -> STAEFA SERVICOS DE MANUTENCAO PREDIAL LTDA | D100: Guilherme | E100: 00000567 | F100: 45905 | G100: 9631.44 | H100: =VLOOKUP(E100&B100,'Conf Oracle'!A:F,6,0) -> #N/A | J100: =IF(OR(ISBLANK(F100), ISBLANK(H100)), "", IFERROR(NETWORKDAYS(F100, H100), ""))
A101: 45912 | B101: 09554428000150 | C101: =VLOOKUP(B101,Fornecedores!A:B,2,0) -> STAEFA SERVICOS DE MANUTENCAO PREDIAL LTDA | D101: Guilherme | E101: 00000565 | F101: 45905 | G101: 19734.63 | H101: =VLOOKUP(E101&B101,'Conf Oracle'!A:F,6,0) -> 45926.451 | J101: =IF(OR(ISBLANK(F101), ISBLANK(H101)), "", IFERROR(NETWORKDAYS(F101, H101), "")) -> 16
A102: 45912 | B102: 45184161000110 | C102: =VLOOKUP(B102,Fornecedores!A:B,2,0) -> Fernando Goncalves Costa | D102: Guilherme | E102: 00000005 | F102: 45905 | G102: 15000 | H102: =VLOOKUP(E102&B102,'Conf Oracle'!A:F,6,0) -> 45911.37 | J102: =IF(OR(ISBLANK(F102), ISBLANK(H102)), "", IFERROR(NETWORKDAYS(F102, H102), "")) -> 5
A103: 45912 | B103: 08998197000101 | C103: =VLOOKUP(B103,Fornecedores!A:B,2,0) -> PANIFICADORA CONFEITARIA ESPINHEIRO LTDA | D103: Guilherme | E103: 00003435 | F103: 45908 | G103: 1595.04 | H103: =VLOOKUP(E103&B103,'Conf Oracle'!A:F,6,0) -> 45930.388 | J103: =IF(OR(ISBLANK(F103), ISBLANK(H103)), "", IFERROR(NETWORKDAYS(F103, H103), "")) -> 17
A104: 45912 | B104: 08998197000101 | C104: =VLOOKUP(B104,Fornecedores!A:B,2,0) -> PANIFICADORA CONFEITARIA ESPINHEIRO LTDA | D104: Guilherme | E104: 00003436 | F104: 45908 | G104: 1324.35 | H104: =VLOOKUP(E104&B104,'Conf Oracle'!A:F,6,0) -> 45912.598 | J104: =IF(OR(ISBLANK(F104), ISBLANK(H104)), "", IFERROR(NETWORKDAYS(F104, H104), "")) -> 5
A105: 45912 | B105: 01092686002366 | C105: =VLOOKUP(B105,Fornecedores!A:B,2,0) -> JOHNSON CONTROLS BE DO BRASIL LTDA | D105: Guilherme | E105: 00131372 | F105: 45911 | G105: 18579.49 | H105: =VLOOKUP(E105&B105,'Conf Oracle'!A:F,6,0) -> 45916.648 | J105: =IF(OR(ISBLANK(F105), ISBLANK(H105)), "", IFERROR(NETWORKDAYS(F105, H105), "")) -> 4
A106: 45912 | B106: 61595364000156 | C106: =VLOOKUP(B106,Fornecedores!A:B,2,0) -> RAFA TUR TRANSPORTES LTDA | D106: Guilherme | E106: 00000014 | F106: 45911 | G106: 3200 | H106: =VLOOKUP(E106&B106,'Conf Oracle'!A:F,6,0) -> #N/A | J106: =IF(OR(ISBLANK(F106), ISBLANK(H106)), "", IFERROR(NETWORKDAYS(F106, H106), ""))
A107: 45912 | B107: 19427033000140 | C107: =VLOOKUP(B107,Fornecedores!A:B,2,0) -> ARQUIVEI SERVICOS ON LINE LTDA | D107: Evandrea | E107: 00517624 | F107: 45901 | G107: 2600 | H107: =VLOOKUP(E107&B107,'Conf Oracle'!A:F,6,0) -> 45918.433 | I107: falta lançamento | J107: =IF(OR(ISBLANK(F107), ISBLANK(H107)), "", IFERROR(NETWORKDAYS(F107, H107), "")) -> 14
A108: 45912 | B108: 02911903000150 | C108: =VLOOKUP(B108,Fornecedores!A:B,2,0) -> FUNDACAO COMITE DE GESTAO EMPRESARIAL- FUNDACAO COGE | D108: Evandrea | E108: 00005210 | F108: 45901 | G108: 10995.4 | H108: =VLOOKUP(E108&B108,'Conf Oracle'!A:F,6,0) -> 45915.456 | J108: =IF(OR(ISBLANK(F108), ISBLANK(H108)), "", IFERROR(NETWORKDAYS(F108, H108), "")) -> 11
A109: 45912 | B109: 64030638000158 | C109: =VLOOKUP(B109,Fornecedores!A:B,2,0) -> CTE - CENTRO DE TECNOLOGIA DE EDIFICACOES LTDA | D109: Evandrea | E109: 00034501 | F109: 45901 | G109: 4500 | H109: =VLOOKUP(E109&B109,'Conf Oracle'!A:F,6,0) -> 45918.569 | I109: falta lançamento | J109: =IF(OR(ISBLANK(F109), ISBLANK(H109)), "", IFERROR(NETWORKDAYS(F109, H109), "")) -> 14
A110: 45912 | B110: 16554325000156 | C110: =VLOOKUP(B110,Fornecedores!A:B,2,0) -> AMBIENTE VERDE RESIDUOS LTDA | D110: Evandrea | E110: 00001247 | F110: 45902 | G110: 2690 | H110: =VLOOKUP(E110&B110,'Conf Oracle'!A:F,6,0) -> 45919.706 | I110: Lançada | J110: =IF(OR(ISBLANK(F110), ISBLANK(H110)), "", IFERROR(NETWORKDAYS(F110, H110), "")) -> 14
...

Sheet Controle de NF - Março
A2: Mês | B2: CNPJ | C2: Fornecedor | D2: Gestor Adm | E2: NF | F2: Emissão da NF | G2: Valor da NF | H2: Conferência | I2: Observação | J2: SLA
A3: 45730 | B3: 15667402000111 | C3: =VLOOKUP(B3,Fornecedores!A:B,2,0) -> SIMPLE ENERGY ASSESSORIA E GESTAO DE ENERGIA LTDA. | D3: EVANDREA | E3: 00020196 | F3: 45719 | G3: 733.38 | H3: =VLOOKUP(E3&B3,'Conf Oracle'!A:F,6,0) -> 45742.481 | I3: Lançada | J3: =IF(OR(ISBLANK(F3), ISBLANK(H3)), "", IFERROR(NETWORKDAYS(F3, H3), "")) -> 18
A4: 45730 | B4: 15667402000111 | C4: =VLOOKUP(B4,Fornecedores!A:B,2,0) -> SIMPLE ENERGY ASSESSORIA E GESTAO DE ENERGIA LTDA. | D4: EVANDREA | E4: 00020214 | F4: 45719 | G4: 733.38 | H4: =VLOOKUP(E4&B4,'Conf Oracle'!A:F,6,0) -> 45742.392 | I4: FALTA LANÇAR | J4: =IF(OR(ISBLANK(F4), ISBLANK(H4)), "", IFERROR(NETWORKDAYS(F4, H4), "")) -> 18
A5: 45730 | B5: 15667402000111 | C5: =VLOOKUP(B5,Fornecedores!A:B,2,0) -> SIMPLE ENERGY ASSESSORIA E GESTAO DE ENERGIA LTDA. | D5: EVANDREA | E5: 00020200 | F5: 45719 | G5: 733.38 | H5: =VLOOKUP(E5&B5,'Conf Oracle'!A:F,6,0) -> 45742.486 | I5: Lançada | J5: =IF(OR(ISBLANK(F5), ISBLANK(H5)), "", IFERROR(NETWORKDAYS(F5, H5), "")) -> 18
A6: 45730 | B6: 16554325000156 | C6: =VLOOKUP(B6,Fornecedores!A:B,2,0) -> AMBIENTE VERDE RESIDUOS LTDA | D6: EVANDREA | E6: 00000807 | F6: 45719 | G6: 2690 | H6: =VLOOKUP(E6&B6,'Conf Oracle'!A:F,6,0) -> 45743.656 | I6: Lançada | J6: =IF(OR(ISBLANK(F6), ISBLANK(H6)), "", IFERROR(NETWORKDAYS(F6, H6), "")) -> 19
A7: 45734 | B7: 15667402000111 | C7: =VLOOKUP(B7,Fornecedores!A:B,2,0) -> SIMPLE ENERGY ASSESSORIA E GESTAO DE ENERGIA LTDA. | D7: EVANDREA | E7: 00020205 | F7: 45719 | G7: 733.38 | H7: =VLOOKUP(E7&B7,'Conf Oracle'!A:F,6,0) -> 45742.423 | I7: FALTA LANÇAR | J7: =IF(OR(ISBLANK(F7), ISBLANK(H7)), "", IFERROR(NETWORKDAYS(F7, H7), "")) -> 18
A8: 45734 | B8: 16554325000156 | C8: =VLOOKUP(B8,Fornecedores!A:B,2,0) -> AMBIENTE VERDE RESIDUOS LTDA | D8: EVANDREA | E8: 00000808 | F8: 45719 | G8: 2690 | H8: =VLOOKUP(E8&B8,'Conf Oracle'!A:F,6,0) -> 45743.667 | I8: Lançada | J8: =IF(OR(ISBLANK(F8), ISBLANK(H8)), "", IFERROR(NETWORKDAYS(F8, H8), "")) -> 19
A9: 45734 | B9: 16554325000156 | C9: =VLOOKUP(B9,Fornecedores!A:B,2,0) -> AMBIENTE VERDE RESIDUOS LTDA | D9: EVANDREA | E9: 00000813 | F9: 45719 | G9: 2490 | H9: =VLOOKUP(E9&B9,'Conf Oracle'!A:F,6,0) -> 45743.681 | I9: Lançada | J9: =IF(OR(ISBLANK(F9), ISBLANK(H9)), "", IFERROR(NETWORKDAYS(F9, H9), "")) -> 19
A10: 45734 | B10: 33597659001602 | C10: =VLOOKUP(B10,Fornecedores!A:B,2,0) -> RICOH BRASIL S A | D10: EVANDREA | E10: 00049486 | F10: 45722 | G10: 1287.36 | H10: =VLOOKUP(E10&B10,'Conf Oracle'!A:F,6,0) -> 45744.725 | I10: Lançada | J10: =IF(OR(ISBLANK(F10), ISBLANK(H10)), "", IFERROR(NETWORKDAYS(F10, H10), "")) -> 17
A11: 45734 | B11: 33597659000126 | C11: =VLOOKUP(B11,Fornecedores!A:B,2,0) -> RICOH BRASIL S A | D11: EVANDREA | E11: 00049487 | F11: 45722 | G11: 80.32 | H11: =VLOOKUP(E11&B11,'Conf Oracle'!A:F,6,0) -> 45744.47 | I11: Lançada | J11: =IF(OR(ISBLANK(F11), ISBLANK(H11)), "", IFERROR(NETWORKDAYS(F11, H11), "")) -> 17
A12: 45734 | B12: 33597659000126 | C12: =VLOOKUP(B12,Fornecedores!A:B,2,0) -> RICOH BRASIL S A | D12: EVANDREA | E12: 00049488 | F12: 45722 | G12: 254.17 | H12: =VLOOKUP(E12&B12,'Conf Oracle'!A:F,6,0) -> 45747.368 | I12: Lançada | J12: =IF(OR(ISBLANK(F12), ISBLANK(H12)), "", IFERROR(NETWORKDAYS(F12, H12), "")) -> 18
A13: 45734 | B13: 33597659000126 | C13: =VLOOKUP(B13,Fornecedores!A:B,2,0) -> RICOH BRASIL S A | D13: EVANDREA | E13: 00049489 | F13: 45722 | G13: 86.56 | H13: =VLOOKUP(E13&B13,'Conf Oracle'!A:F,6,0) -> 45744.731 | I13: Lançada | J13: =IF(OR(ISBLANK(F13), ISBLANK(H13)), "", IFERROR(NETWORKDAYS(F13, H13), "")) -> 17
A14: 45734 | B14: 33597659001602 | C14: =VLOOKUP(B14,Fornecedores!A:B,2,0) -> RICOH BRASIL S A | D14: EVANDREA | E14: 00049491 | F14: 45722 | G14: 253.64 | H14: =VLOOKUP(E14&B14,'Conf Oracle'!A:F,6,0) -> 45744.718 | I14: Lançada | J14: =IF(OR(ISBLANK(F14), ISBLANK(H14)), "", IFERROR(NETWORKDAYS(F14, H14), "")) -> 17
... A16: 45734 | B16: 00028986001694 | C16: =VLOOKUP(B16,Fornecedores!A:B,2,0) -> ELEVADORES ATLAS SCHINDLER SA | D16: EVANDREA | E16: 00465236 | F16: 45721 | G16: 1960.94 | H16: =VLOOKUP(E16&B16,'Conf Oracle'!A:F,6,0) -> 45736.701 | I16: Lançada | J16: =IF(OR(ISBLANK(F16), ISBLANK(H16)), "", IFERROR(NETWORKDAYS(F16, H16), "")) -> 12
A17: 45734 | B17: 08270682000164 | C17: =VLOOKUP(B17,Fornecedores!A:B,2,0) -> CONFIDERE IMOBILIARIA LTDA | D17: EVANDREA | E17: 00202503 | F17: 45722 | G17: 2737093.3 | H17: =VLOOKUP(E17&B17,'Conf Oracle'!A:F,6,0) -> 45727.389 | J17: =IF(OR(ISBLANK(F17), ISBLANK(H17)), "", IFERROR(NETWORKDAYS(F17, H17), "")) -> 4
A18: 45734 | B18: 05208211001614 | C18: =VLOOKUP(B18,Fornecedores!A:B,2,0) -> IN-HAUS INDUSTRIAL E SERVICOS DE LOGISTICA LTDA | D18: EVANDREA | E18: 00000365 | F18: 45723 | G18: 94387.81 | H18: =VLOOKUP(E18&B18,'Conf Oracle'!A:F,6,0) -> 45744.702 | I18: FALTA LANÇAR | J18: =IF(OR(ISBLANK(F18), ISBLANK(H18)), "", IFERROR(NETWORKDAYS(F18, H18), "")) -> 16
A19: 45734 | B19: 00973749000115 | C19: =VLOOKUP(B19,Fornecedores!A:B,2,0) -> TOP SERVICE SERVICOS E SISTEMAS S/A | D19: EVANDREA | E19: 00212863 | F19: 45723 | G19: 10427.67 | H19: =VLOOKUP(E19&B19,'Conf Oracle'!A:F,6,0) -> 45744.406 | I19: FALTA LANÇAR | J19: =IF(OR(ISBLANK(F19), ISBLANK(H19)), "", IFERROR(NETWORKDAYS(F19, H19), "")) -> 16
A20: 45734 | B20: 00973749000115 | C20: =VLOOKUP(B20,Fornecedores!A:B,2,0) -> TOP SERVICE SERVICOS E SISTEMAS S/A | D20: EVANDREA | E20: 00212844 | F20: 45723 | G20: 49388.6 | H20: =VLOOKUP(E20&B20,'Conf Oracle'!A:F,6,0) -> 45744.429 | I20: FALTA LANÇAR | J20: =IF(OR(ISBLANK(F20), ISBLANK(H20)), "", IFERROR(NETWORKDAYS(F20, H20), "")) -> 16
A21: 45734 | B21: 90347840005691 | C21: =VLOOKUP(B21,Fornecedores!A:B,2,0) -> TK ELEVADORES BRASIL LTDA. | D21: EVANDREA | E21: 00111731 | F21: 45717 | G21: 13781.17 | H21: =VLOOKUP(E21&B21,'Conf Oracle'!A:F,6,0) -> 45736.383 | I21: FALTA LANÇAR | J21: =IF(OR(ISBLANK(F21), ISBLANK(H21)), "", IFERROR(NETWORKDAYS(F21, H21), "")) -> 14
A22: 45734 | B22: 40432544000147 | C22: =VLOOKUP(B22,Fornecedores!A:B,2,0) -> CLARO SA | D22: EVANDREA | E22: 83906243 | F22: 45726 | G22: 18299.85 | H22: =VLOOKUP(E22&B22,'Conf Oracle'!A:F,6,0) -> 45735.614 | I22: Lançada | J22: =IF(OR(ISBLANK(F22), ISBLANK(H22)), "", IFERROR(NETWORKDAYS(F22, H22), "")) -> 8
A23: 45734 | B23: 40432544000147 | C23: =VLOOKUP(B23,Fornecedores!A:B,2,0) -> CLARO SA | D23: EVANDREA | E23: 05393221 | F23: 45726 | G23: 2419.83 | H23: =VLOOKUP(E23&B23,'Conf Oracle'!A:F,6,0) -> 45735.611 | I23: Lançada | J23: =IF(OR(ISBLANK(F23), ISBLANK(H23)), "", IFERROR(NETWORKDAYS(F23, H23), "")) -> 8
A24: 45734 | B24: 40432544000147 | C24: =VLOOKUP(B24,Fornecedores!A:B,2,0) -> CLARO SA | D24: EVANDREA | E24: 91614197 | F24: 45726 | G24: 1843.58 | H24: =VLOOKUP(E24&B24,'Conf Oracle'!A:F,6,0) -> 45735.607 | I24: Lançada | J24: =IF(OR(ISBLANK(F24), ISBLANK(H24)), "", IFERROR(NETWORKDAYS(F24, H24), "")) -> 8
A25: 45734 | B25: 40432544000147 | C25: =VLOOKUP(B25,Fornecedores!A:B,2,0) -> CLARO SA | D25: EVANDREA | E25: 31199179 | F25: 45726 | G25: 3543.94 | H25: =VLOOKUP(E25&B25,'Conf Oracle'!A:F,6,0) -> 45735.603 | I25: Lançada | J25: =IF(OR(ISBLANK(F25), ISBLANK(H25)), "", IFERROR(NETWORKDAYS(F25, H25), "")) -> 8
A26: 45734 | B26: 40432544000147 | C26: =VLOOKUP(B26,Fornecedores!A:B,2,0) -> CLARO SA | D26: EVANDREA | E26: 00737742 | F26: 45726 | G26: 1949.23 | H26: =VLOOKUP(E26&B26,'Conf Oracle'!A:F,6,0) -> 45735.598 | I26: Lançada | J26: =IF(OR(ISBLANK(F26), ISBLANK(H26)), "", IFERROR(NETWORKDAYS(F26, H26), "")) -> 8
A27: 45734 | B27: 13498242000107 | C27: =VLOOKUP(B27,Fornecedores!A:B,2,0) -> GCCENTRO ESPECIALI EM SERV DE LIMP LTDA | D27: EVANDREA | E27: 00005900 | F27: 45727 | G27: 8306.01 | H27: =VLOOKUP(E27&B27,'Conf Oracle'!A:F,6,0) -> 45747.767 | I27: FALTA LANÇAR | J27: =IF(OR(ISBLANK(F27), ISBLANK(H27)), "", IFERROR(NETWORKDAYS(F27, H27), "")) -> 15
A28: 45734 | B28: 16554325000156 | C28: =VLOOKUP(B28,Fornecedores!A:B,2,0) -> AMBIENTE VERDE RESIDUOS LTDA | D28: EVANDREA | E28: 00000837 | F28: 45728 | G28: 6624.55 | H28: =VLOOKUP(E28&B28,'Conf Oracle'!A:F,6,0) -> 45747.608 | I28: FALTA LANÇAR | J28: =IF(OR(ISBLANK(F28), ISBLANK(H28)), "", IFERROR(NETWORKDAYS(F28, H28), "")) -> 14
A29: 45734 | B29: 29650979000125 | C29: =VLOOKUP(B29,Fornecedores!A:B,2,0) -> CAPACITARE RECURSOS HUMANOS EIRELI | D29: EVANDREA | E29: 00002205 | F29: 45726 | G29: 14880 | H29: =VLOOKUP(E29&B29,'Conf Oracle'!A:F,6,0) -> 45748.614 | I29: Lançada | J29: =IF(OR(ISBLANK(F29), ISBLANK(H29)), "", IFERROR(NETWORKDAYS(F29, H29), "")) -> 17
A30: 45734 | B30: 23412247000110 | C30: =VLOOKUP(B30,Fornecedores!A:B,2,0) -> AMAZON AWS SERVICOS BRASIL LTDA | D30: INGRID | E30: 04093699 | F30: 45718 | G30: 510096.46 | H30: =VLOOKUP(E30&B30,'Conf Oracle'!A:F,6,0) -> 45747.502 | J30: =IF(OR(ISBLANK(F30), ISBLANK(H30)), "", IFERROR(NETWORKDAYS(F30, H30), "")) -> 21
A31: 45734 | B31: 23412247000110 | C31: =VLOOKUP(B31,Fornecedores!A:B,2,0) -> AMAZON AWS SERVICOS BRASIL LTDA | D31: INGRID | E31: 04095146 | F31: 45718 | G31: 71814.74 | H31: =VLOOKUP(E31&B31,'Conf Oracle'!A:F,6,0) -> 45747.604 | J31: =IF(OR(ISBLANK(F31), ISBLANK(H31)), "", IFERROR(NETWORKDAYS(F31, H31), "")) -> 21
A32: 45734 | B32: 23412247000110 | C32: =VLOOKUP(B32,Fornecedores!A:B,2,0) -> AMAZON AWS SERVICOS BRASIL LTDA | D32: INGRID | E32: 04095151 | F32: 45718 | G32: 50287.76 | H32: =VLOOKUP(E32&B32,'Conf Oracle'!A:F,6,0) -> 45747.622 | J32: =IF(OR(ISBLANK(F32), ISBLANK(H32)), "", IFERROR(NETWORKDAYS(F32, H32), "")) -> 21
A33: 45734 | B33: 58652678000139 | C33: =VLOOKUP(B33,Fornecedores!A:B,2,0) -> COLUMBIA STORAGE INTEGR DE SITEMAS LTDA | D33: INGRID | E33: 00011049 | F33: 45722 | G33: 17116.41 | H33: =VLOOKUP(E33&B33,'Conf Oracle'!A:F,6,0) -> 45736.396 | J33: =IF(OR(ISBLANK(F33), ISBLANK(H33)), "", IFERROR(NETWORKDAYS(F33, H33), "")) -> 11
A34: 45734 | B34: 07850212000107 | C34: =VLOOKUP(B34,Fornecedores!A:B,2,0) -> REAL SEGURANCA INTEGRADA EIRELI | D34: INGRID | E34: 00001089 | F34: 45722 | G34: 217.9 | H34: =VLOOKUP(E34&B34,'Conf Oracle'!A:F,6,0) -> 45747.459 | J34: =IF(OR(ISBLANK(F34), ISBLANK(H34)), "", IFERROR(NETWORKDAYS(F34, H34), "")) -> 18
A35: 45734 | B35: 02558157000162 | C35: =VLOOKUP(B35,Fornecedores!A:B,2,0) -> TELEFONICA BRASIL SA | D35: INGRID | E35: 19504125 | F35: 45710 | G35: 29.19 | H35: =VLOOKUP(E35&B35,'Conf Oracle'!A:F,6,0) -> #N/A | I35: Em contestação | J35: =IF(OR(ISBLANK(F35), ISBLANK(H35)), "", IFERROR(NETWORKDAYS(F35, H35), ""))
A36: 45734 | B36: 02558157000162 | C36: =VLOOKUP(B36,Fornecedores!A:B,2,0) -> TELEFONICA BRASIL SA | D36: INGRID | E36: 13969264 | F36: 45710 | G36: 425.93 | H36: =VLOOKUP(E36&B36,'Conf Oracle'!A:F,6,0) -> #N/A | I36: Em contestação | J36: =IF(OR(ISBLANK(F36), ISBLANK(H36)), "", IFERROR(NETWORKDAYS(F36, H36), ""))
A37: 45734 | B37: 01768873000101 | C37: =VLOOKUP(B37,Fornecedores!A:B,2,0) -> AMCOM SISTEMAS DE INFORMACAO SA | D37: INGRID | E37: 00019090 | F37: 45723 | G37: 47600 | H37: =VLOOKUP(E37&B37,'Conf Oracle'!A:F,6,0) -> 45727.404 | J37: =IF(OR(ISBLANK(F37), ISBLANK(H37)), "", IFERROR(NETWORKDAYS(F37, H37), "")) -> 3
A38: 45734 | B38: 01768873000101 | C38: =VLOOKUP(B38,Fornecedores!A:B,2,0) -> AMCOM SISTEMAS DE INFORMACAO SA | D38: INGRID | E38: 00019091 | F38: 45723 | G38: 200600 | H38: =VLOOKUP(E38&B38,'Conf Oracle'!A:F,6,0) -> 45727.416 | J38: =IF(OR(ISBLANK(F38), ISBLANK(H38)), "", IFERROR(NETWORKDAYS(F38, H38), "")) -> 3
A39: 45734 | B39: 01768873000101 | C39: =VLOOKUP(B39,Fornecedores!A:B,2,0) -> AMCOM SISTEMAS DE INFORMACAO SA | D39: INGRID | E39: 00019092 | F39: 45723 | G39: 167790 | H39: =VLOOKUP(E39&B39,'Conf Oracle'!A:F,6,0) -> 45727.438 | J39: =IF(OR(ISBLANK(F39), ISBLANK(H39)), "", IFERROR(NETWORKDAYS(F39, H39), "")) -> 3
A40: 45734 | B40: 01768873000101 | C40: =VLOOKUP(B40,Fornecedores!A:B,2,0) -> AMCOM SISTEMAS DE INFORMACAO SA | D40: INGRID | E40: 00019093 | F40: 45723 | G40: 125120 | H40: =VLOOKUP(E40&B40,'Conf Oracle'!A:F,6,0) -> 45741.68 | J40: =IF(OR(ISBLANK(F40), ISBLANK(H40)), "", IFERROR(NETWORKDAYS(F40, H40), "")) -> 13
A41: 45734 | B41: 01768873000101 | C41: =VLOOKUP(B41,Fornecedores!A:B,2,0) -> AMCOM SISTEMAS DE INFORMACAO SA | D41: INGRID | E41: 00019094 | F41: 45723 | G41: 86700 | H41: =VLOOKUP(E41&B41,'Conf Oracle'!A:F,6,0) -> 45727.617 | J41: =IF(OR(ISBLANK(F41), ISBLANK(H41)), "", IFERROR(NETWORKDAYS(F41, H41), "")) -> 3
A42: 45734 | B42: 01768873000101 | C42: =VLOOKUP(B42,Fornecedores!A:B,2,0) -> AMCOM SISTEMAS DE INFORMACAO SA | D42: INGRID | E42: 00019095 | F42: 45723 | G42: 205360 | H42: =VLOOKUP(E42&B42,'Conf Oracle'!A:F,6,0) -> 45727.465 | J42: =IF(OR(ISBLANK(F42), ISBLANK(H42)), "", IFERROR(NETWORKDAYS(F42, H42), "")) -> 3
A43: 45734 | B43: 01768873000101 | C43: =VLOOKUP(B43,Fornecedores!A:B,2,0) -> AMCOM SISTEMAS DE INFORMACAO SA | D43: INGRID | E43: 00019096 | F43: 45723 | G43: 288660 | H43: =VLOOKUP(E43&B43,'Conf Oracle'!A:F,6,0) -> 45727.451 | J43: =IF(OR(ISBLANK(F43), ISBLANK(H43)), "", IFERROR(NETWORKDAYS(F43, H43), "")) -> 3
A44: 45734 | B44: 01768873000101 | C44: =VLOOKUP(B44,Fornecedores!A:B,2,0) -> AMCOM SISTEMAS DE INFORMACAO SA | D44: INGRID | E44: 00019097 | F44: 45723 | G44: 46648 | H44: =VLOOKUP(E44&B44,'Conf Oracle'!A:F,6,0) -> 45749.578 | I44: Lançada | J44: =IF(OR(ISBLANK(F44), ISBLANK(H44)), "", IFERROR(NETWORKDAYS(F44, H44), "")) -> 19
A45: 45734 | B45: 01768873000101 | C45: =VLOOKUP(B45,Fornecedores!A:B,2,0) -> AMCOM SISTEMAS DE INFORMACAO SA | D45: INGRID | E45: 00019098 | F45: 45723 | G45: 48790 | H45: =VLOOKUP(E45&B45,'Conf Oracle'!A:F,6,0) -> 45727.446 | J45: =IF(OR(ISBLANK(F45), ISBLANK(H45)), "", IFERROR(NETWORKDAYS(F45, H45), "")) -> 3
A46: 45734 | B46: 15491115000101 | C46: =VLOOKUP(B46,Fornecedores!A:B,2,0) -> CS INTEGRA SOLUCOES EM TECNOLOG LTDA ME | D46: ISABELA | E46: 00006206 | F46: 45719 | G46: 3093 | H46: =VLOOKUP(E46&B46,'Conf Oracle'!A:F,6,0) -> 45730.576 | J46: =IF(OR(ISBLANK(F46), ISBLANK(H46)), "", IFERROR(NETWORKDAYS(F46, H46), "")) -> 10
A47: 45734 | B47: 07751071000175 | C47: =VLOOKUP(B47,Fornecedores!A:B,2,0) -> TELEGESTAO SISTEMAS DE ATEND LTDA | D47: ISABELA | E47: 00000939 | F47: 45721 | G47: 700 | H47: =VLOOKUP(E47&B47,'Conf Oracle'!A:F,6,0) -> 45729.634 | I47: NF COM MESMO NÚMERO DE FORNECEDORES DIFERENTES | J47: =IF(OR(ISBLANK(F47), ISBLANK(H47)), "", IFERROR(NETWORKDAYS(F47, H47), "")) -> 7
A48: 45734 | B48: 72157654000215 | C48: =VLOOKUP(B48,Fornecedores!A:B,2,0) -> VELA SOFTWARE E SERVICOS LTDA | D48: ISABELA | E48: 00003791 | F48: 45721 | G48: 677.6 | H48: =VLOOKUP(E48&B48,'Conf Oracle'!A:F,6,0) -> #N/A | I48: Lançada | J48: =IF(OR(ISBLANK(F48), ISBLANK(H48)), "", IFERROR(NETWORKDAYS(F48, H48), ""))
A49: 45734 | B49: 72157654000215 | C49: =VLOOKUP(B49,Fornecedores!A:B,2,0) -> VELA SOFTWARE E SERVICOS LTDA | D49: ISABELA | E49: 00003795 | F49: 45721 | G49: 677.6 | H49: =VLOOKUP(E49&B49,'Conf Oracle'!A:F,6,0) -> #N/A | I49: Lançada | J49: =IF(OR(ISBLANK(F49), ISBLANK(H49)), "", IFERROR(NETWORKDAYS(F49, H49), ""))
A50: 45734 | B50: 72157654000215 | C50: =VLOOKUP(B50,Fornecedores!A:B,2,0) -> VELA SOFTWARE E SERVICOS LTDA | D50: ISABELA | E50: 00003797 | F50: 45721 | G50: 677.6 | H50: =VLOOKUP(E50&B50,'Conf Oracle'!A:F,6,0) -> #N/A | I50: Lançada | J50: =IF(OR(ISBLANK(F50), ISBLANK(H50)), "", IFERROR(NETWORKDAYS(F50, H50), ""))
A51: 45734 | B51: 72157654000215 | C51: =VLOOKUP(B51,Fornecedores!A:B,2,0) -> VELA SOFTWARE E SERVICOS LTDA | D51: ISABELA | E51: 00003799 | F51: 45721 | G51: 677.6 | H51: =VLOOKUP(E51&B51,'Conf Oracle'!A:F,6,0) -> #N/A | I51: Lançada | J51: =IF(OR(ISBLANK(F51), ISBLANK(H51)), "", IFERROR(NETWORKDAYS(F51, H51), ""))
A52: 45734 | B52: 72157654000215 | C52: =VLOOKUP(B52,Fornecedores!A:B,2,0) -> VELA SOFTWARE E SERVICOS LTDA | D52: ISABELA | E52: 00024297 | F52: 45721 | G52: 648.76 | H52: =VLOOKUP(E52&B52,'Conf Oracle'!A:F,6,0) -> #N/A | I52: fevereiro | J52: =IF(OR(ISBLANK(F52), ISBLANK(H52)), "", IFERROR(NETWORKDAYS(F52, H52), ""))
A53: 45734 | B53: 72157654000215 | C53: =VLOOKUP(B53,Fornecedores!A:B,2,0) -> VELA SOFTWARE E SERVICOS LTDA | D53: ISABELA | E53: 00024289 | F53: 45721 | G53: 648.76 | H53: =VLOOKUP(E53&B53,'Conf Oracle'!A:F,6,0) -> #N/A | I53: fevereiro | J53: =IF(OR(ISBLANK(F53), ISBLANK(H53)), "", IFERROR(NETWORKDAYS(F53, H53), ""))
A54: 45734 | B54: 26409092000151 | C54: =VLOOKUP(B54,Fornecedores!A:B,2,0) -> SSAMRO SOLUCOES PARA MANUTENCAO INDUSTR | D54: ISABELA | E54: 00024307 | F54: 45721 | G54: 648.76 | H54: =VLOOKUP(E54&B54,'Conf Oracle'!A:F,6,0) -> 45729.404 | J54: =IF(OR(ISBLANK(F54), ISBLANK(H54)), "", IFERROR(NETWORKDAYS(F54, H54), "")) -> 7
A55: 45734 | B55: 26409092000151 | C55: =VLOOKUP(B55,Fornecedores!A:B,2,0) -> SSAMRO SOLUCOES PARA MANUTENCAO INDUSTR | D55: ISABELA | E55: 00024311 | F55: 45721 | G55: 648.76 | H55: =VLOOKUP(E55&B55,'Conf Oracle'!A:F,6,0) -> 45729.392 | J55: =IF(OR(ISBLANK(F55), ISBLANK(H55)), "", IFERROR(NETWORKDAYS(F55, H55), "")) -> 7
A56: 45734 | B56: 04359325000116 | C56: =VLOOKUP(B56,Fornecedores!A:B,2,0) -> MORAES PITOMBO ADVOGADOS | D56: ISABELA | E56: 00019978 | F56: 45723 | G56: 7500 | H56: =VLOOKUP(E56&B56,'Conf Oracle'!A:F,6,0) -> 45730.544 | J56: =IF(OR(ISBLANK(F56), ISBLANK(H56)), "", IFERROR(NETWORKDAYS(F56, H56), "")) -> 6
A57: 45734 | B57: 96534094000158 | C57: =VLOOKUP(B57,Fornecedores!A:B,2,0) -> ACCENTURE DO BRASIL LTDA | D57: ISABELA | E57: 00101607 | F57: 45726 | G57: 41904 | H57: =VLOOKUP(E57&B57,'Conf Oracle'!A:F,6,0) -> 45728.467 | J57: =IF(OR(ISBLANK(F57), ISBLANK(H57)), "", IFERROR(NETWORKDAYS(F57, H57), "")) -> 3
A58: 45734 | B58: 96534094000158 | C58: =VLOOKUP(B58,Fornecedores!A:B,2,0) -> ACCENTURE DO BRASIL LTDA | D58: ISABELA | E58: 00101608 | F58: 45726 | G58: 183243.6 | H58: =VLOOKUP(E58&B58,'Conf Oracle'!A:F,6,0) -> 45728.387 | J58: =IF(OR(ISBLANK(F58), ISBLANK(H58)), "", IFERROR(NETWORKDAYS(F58, H58), "")) -> 3
A59: 45734 | B59: 02558157013574 | C59: =VLOOKUP(B59,Fornecedores!A:B,2,0) -> TELEFONICA BRASIL SA | D59: INGRID | E59: 00335952 | F59: 45724 | G59: 915.86 | H59: =VLOOKUP(E59&B59,'Conf Oracle'!A:F,6,0) -> #N/A | I59: Em contestação | J59: =IF(OR(ISBLANK(F59), ISBLANK(H59)), "", IFERROR(NETWORKDAYS(F59, H59), ""))
A60: 45734 | B60: 02558157013574 | C60: =VLOOKUP(B60,Fornecedores!A:B,2,0) -> TELEFONICA BRASIL SA | D60: INGRID | E60: 00333434 | F60: 45724 | G60: 1657.98 | H60: =VLOOKUP(E60&B60,'Conf Oracle'!A:F,6,0) -> #N/A | I60: Em contestação | J60: =IF(OR(ISBLANK(F60), ISBLANK(H60)), "", IFERROR(NETWORKDAYS(F60, H60), ""))
A61: 45734 | B61: 02558157013574 | C61: =VLOOKUP(B61,Fornecedores!A:B,2,0) -> TELEFONICA BRASIL SA | D61: INGRID | E61: 00339365 | F61: 45724 | G61: 180 | H61: =VLOOKUP(E61&B61,'Conf Oracle'!A:F,6,0) -> #N/A | I61: Em contestação | J61: =IF(OR(ISBLANK(F61), ISBLANK(H61)), "", IFERROR(NETWORKDAYS(F61, H61), ""))
A62: 45734 | B62: 02558157013574 | C62: =VLOOKUP(B62,Fornecedores!A:B,2,0) -> TELEFONICA BRASIL SA | D62: INGRID | E62: 00333098 | F62: 45724 | G62: 3167.16 | H62: =VLOOKUP(E62&B62,'Conf Oracle'!A:F,6,0) -> #N/A | I62: Em contestação | J62: =IF(OR(ISBLANK(F62), ISBLANK(H62)), "", IFERROR(NETWORKDAYS(F62, H62), ""))
A63: 45734 | B63: 02558157013574 | C63: =VLOOKUP(B63,Fornecedores!A:B,2,0) -> TELEFONICA BRASIL SA | D63: INGRID | E63: 00337151 | F63: 45724 | G63: 2522.64 | H63: =VLOOKUP(E63&B63,'Conf Oracle'!A:F,6,0) -> #N/A | I63: Em contestação | J63: =IF(OR(ISBLANK(F63), ISBLANK(H63)), "", IFERROR(NETWORKDAYS(F63, H63), ""))
A64: 45734 | B64: 02558157013574 | C64: =VLOOKUP(B64,Fornecedores!A:B,2,0) -> TELEFONICA BRASIL SA | D64: INGRID | E64: 00336932 | F64: 45724 | G64: 180 | H64: =VLOOKUP(E64&B64,'Conf Oracle'!A:F,6,0) -> #N/A | I64: Em contestação | J64: =IF(OR(ISBLANK(F64), ISBLANK(H64)), "", IFERROR(NETWORKDAYS(F64, H64), ""))
A65: 45734 | B65: 02558157013574 | C65: =VLOOKUP(B65,Fornecedores!A:B,2,0) -> TELEFONICA BRASIL SA | D65: INGRID | E65: 00338305 | F65: 45724 | G65: 1581.56 | H65: =VLOOKUP(E65&B65,'Conf Oracle'!A:F,6,0) -> #N/A | I65: Em contestação | J65: =IF(OR(ISBLANK(F65), ISBLANK(H65)), "", IFERROR(NETWORKDAYS(F65, H65), ""))
A66: 45734 | B66: 02558157013574 | C66: =VLOOKUP(B66,Fornecedores!A:B,2,0) -> TELEFONICA BRASIL SA | D66: INGRID | E66: 00339513 | F66: 45724 | G66: 1080 | H66: =VLOOKUP(E66&B66,'Conf Oracle'!A:F,6,0) -> #N/A | I66: Em contestação | J66: =IF(OR(ISBLANK(F66), ISBLANK(H66)), "", IFERROR(NETWORKDAYS(F66, H66), ""))
A67: 45734 | B67: 02558157013574 | C67: =VLOOKUP(B67,Fornecedores!A:B,2,0) -> TELEFONICA BRASIL SA | D67: INGRID | E67: 00340630 | F67: 45724 | G67: 360 | H67: =VLOOKUP(E67&B67,'Conf Oracle'!A:F,6,0) -> #N/A | I67: Em contestação | J67: =IF(OR(ISBLANK(F67), ISBLANK(H67)), "", IFERROR(NETWORKDAYS(F67, H67), ""))
A68: 45734 | B68: 02558157013574 | C68: =VLOOKUP(B68,Fornecedores!A:B,2,0) -> TELEFONICA BRASIL SA | D68: INGRID | E68: 00337048 | F68: 45724 | G68: 1110.62 | H68: =VLOOKUP(E68&B68,'Conf Oracle'!A:F,6,0) -> #N/A | I68: Em contestação | J68: =IF(OR(ISBLANK(F68), ISBLANK(H68)), "", IFERROR(NETWORKDAYS(F68, H68), ""))
A69: 45734 | B69: 02558157013574 | C69: =VLOOKUP(B69,Fornecedores!A:B,2,0) -> TELEFONICA BRASIL SA | D69: INGRID | E69: 00335288 | F69: 45724 | G69: 882.79 | H69: =VLOOKUP(E69&B69,'Conf Oracle'!A:F,6,0) -> #N/A | I69: Em contestação | J69: =IF(OR(ISBLANK(F69), ISBLANK(H69)), "", IFERROR(NETWORKDAYS(F69, H69), ""))
A70: 45734 | B70: 02408485000182 | C70: =VLOOKUP(B70,Fornecedores!A:B,2,0) -> MULTIVIS BRASIL LTDA | D70: INGRID | E70: 00002483 | F70: 45727 | G70: 76829.38 | H70: =VLOOKUP(E70&B70,'Conf Oracle'!A:F,6,0) -> 45747.43 | J70: =IF(OR(ISBLANK(F70), ISBLANK(H70)), "", IFERROR(NETWORKDAYS(F70, H70), "")) -> 15
A71: 45734 | B71: 22772012000177 | C71: =VLOOKUP(B71,Fornecedores!A:B,2,0) -> SPECIALISTERNE BRASIL CAPACITACAO EM SERVICOS RELACIONADOS A TECNOLOGIA, INFORMATICA E CONSULTORIA EMPRESARIAL LTDA. | D71: ISABELA | E71: 00004747 | F71: 45727 | G71: 3000 | H71: =VLOOKUP(E71&B71,'Conf Oracle'!A:F,6,0) -> 45728.639 | J71: =IF(OR(ISBLANK(F71), ISBLANK(H71)), "", IFERROR(NETWORKDAYS(F71, H71), "")) -> 2
A72: 45734 | B72: 26409092000151 | C72: =VLOOKUP(B72,Fornecedores!A:B,2,0) -> SSAMRO SOLUCOES PARA MANUTENCAO INDUSTR | D72: ISABELA | E72: 00024395 | F72: 45728 | G72: 2170 | H72: =VLOOKUP(E72&B72,'Conf Oracle'!A:F,6,0) -> 45740.597 | I72: Vai entrar pela SA (sem contrato) | J72: =IF(OR(ISBLANK(F72), ISBLANK(H72)), "", IFERROR(NETWORKDAYS(F72, H72), "")) -> 9
A73: 45734 | B73: 33789321000176 | C73: =VLOOKUP(B73,Fornecedores!A:B,2,0) -> SALOMAO, ABRAHAO, RAPOSO E COTTA SOCIEDADE DE ADVOGADOS | D73: ISABELA | E73: 00001872 | F73: 45728 | G73: 740.33 | H73: =VLOOKUP(E73&B73,'Conf Oracle'!A:F,6,0) -> 45730.451 | J73: =IF(OR(ISBLANK(F73), ISBLANK(H73)), "", IFERROR(NETWORKDAYS(F73, H73), "")) -> 3
A74: 45734 | B74: 47827415000105 | C74: =VLOOKUP(B74,Fornecedores!A:B,2,0) -> SAD CONSULTORIA LTDA | D74: ISABELA | E74: 00113384 | F74: 45729 | G74: 29850 | H74: =VLOOKUP(E74&B74,'Conf Oracle'!A:F,6,0) -> 45734.451 | J74: =IF(OR(ISBLANK(F74), ISBLANK(H74)), "", IFERROR(NETWORKDAYS(F74, H74), "")) -> 4
A75: 45734 | B75: 47827415000105 | C75: =VLOOKUP(B75,Fornecedores!A:B,2,0) -> SAD CONSULTORIA LTDA | D75: ISABELA | E75: 00113385 | F75: 45729 | G75: 24000 | H75: =VLOOKUP(E75&B75,'Conf Oracle'!A:F,6,0) -> 45734.656 | I75: Lançada | J75: =IF(OR(ISBLANK(F75), ISBLANK(H75)), "", IFERROR(NETWORKDAYS(F75, H75), "")) -> 4
A76: 45734 | B76: 25012398000107 | C76: =VLOOKUP(B76,Fornecedores!A:B,2,0) -> GOOGLE CLOUD BRASIL COMPUTAÇÃO E SERVICOS DE DADOS LTDA | D76: JESSY | E76: 12459888 | F76: 45719 | G76: 1010.38 | H76: =VLOOKUP(E76&B76,'Conf Oracle'!A:F,6,0) -> 45730.565 | I76: Ok | J76: =IF(OR(ISBLANK(F76), ISBLANK(H76)), "", IFERROR(NETWORKDAYS(F76, H76), "")) -> 10
A77: 45734 | B77: 57623555000107 | C77: =VLOOKUP(B77,Fornecedores!A:B,2,0) -> MAGICCOMP ENG E SERV DE INFORMATICA LTDA | D77: JESSY | E77: 00055498 | F77: 45721 | G77: 23587.74 | H77: =VLOOKUP(E77&B77,'Conf Oracle'!A:F,6,0) -> 45729.662 | I77: Ok | J77: =IF(OR(ISBLANK(F77), ISBLANK(H77)), "", IFERROR(NETWORKDAYS(F77, H77), "")) -> 7
A78: 45734 | B78: 57623555000107 | C78: =VLOOKUP(B78,Fornecedores!A:B,2,0) -> MAGICCOMP ENG E SERV DE INFORMATICA LTDA | D78: JESSY | E78: 00055495 | F78: 45721 | G78: 26357.42 | H78: =VLOOKUP(E78&B78,'Conf Oracle'!A:F,6,0) -> 45733.568 | I78: Ok | J78: =IF(OR(ISBLANK(F78), ISBLANK(H78)), "", IFERROR(NETWORKDAYS(F78, H78), "")) -> 9
A79: 45734 | B79: 57623555000107 | C79: =VLOOKUP(B79,Fornecedores!A:B,2,0) -> MAGICCOMP ENG E SERV DE INFORMATICA LTDA | D79: JESSY | E79: 00055496 | F79: 45721 | G79: 26357.42 | H79: =VLOOKUP(E79&B79,'Conf Oracle'!A:F,6,0) -> 45733.485 | I79: Ok | J79: =IF(OR(ISBLANK(F79), ISBLANK(H79)), "", IFERROR(NETWORKDAYS(F79, H79), "")) -> 9
A80: 45734 | B80: 57623555000107 | C80: =VLOOKUP(B80,Fornecedores!A:B,2,0) -> MAGICCOMP ENG E SERV DE INFORMATICA LTDA | D80: JESSY | E80: 00055497 | F80: 45721 | G80: 23587.74 | H80: =VLOOKUP(E80&B80,'Conf Oracle'!A:F,6,0) -> 45733.4 | I80: Ok | J80: =IF(OR(ISBLANK(F80), ISBLANK(H80)), "", IFERROR(NETWORKDAYS(F80, H80), "")) -> 9
A81: 45734 | B81: 21356354000143 | C81: =VLOOKUP(B81,Fornecedores!A:B,2,0) -> POPULOS TECNOLOGIA LTDA | D81: JESSY | E81: 00002614 | F81: 45726 | G81: 3118.52 | H81: =VLOOKUP(E81&B81,'Conf Oracle'!A:F,6,0) -> 45728.377 | I81: Ok | J81: =IF(OR(ISBLANK(F81), ISBLANK(H81)), "", IFERROR(NETWORKDAYS(F81, H81), "")) -> 3
A82: 45734 | B82: 51886784000138 | C82: =VLOOKUP(B82,Fornecedores!A:B,2,0) -> EASY 5 SOLUCOES LTDA | D82: JESSY | E82: 00000422 | F82: 45726 | G82: 21588 | H82: =VLOOKUP(E82&B82,'Conf Oracle'!A:F,6,0) -> 45729.647 | I82: Ok | J82: =IF(OR(ISBLANK(F82), ISBLANK(H82)), "", IFERROR(NETWORKDAYS(F82, H82), "")) -> 4
A83: 45734 | B83: 51886784000138 | C83: =VLOOKUP(B83,Fornecedores!A:B,2,0) -> EASY 5 SOLUCOES LTDA | D83: JESSY | E83: 00000423 | F83: 45726 | G83: 21588 | H83: =VLOOKUP(E83&B83,'Conf Oracle'!A:F,6,0) -> 45729.65 | I83: Ok | J83: =IF(OR(ISBLANK(F83), ISBLANK(H83)), "", IFERROR(NETWORKDAYS(F83, H83), "")) -> 4
A84: 45734 | B84: 51886784000138 | C84: =VLOOKUP(B84,Fornecedores!A:B,2,0) -> EASY 5 SOLUCOES LTDA | D84: JESSY | E84: 00000424 | F84: 45726 | G84: 21588 | H84: =VLOOKUP(E84&B84,'Conf Oracle'!A:F,6,0) -> 45729.652 | I84: Ok | J84: =IF(OR(ISBLANK(F84), ISBLANK(H84)), "", IFERROR(NETWORKDAYS(F84, H84), "")) -> 4
A85: 45734 | B85: 51886784000138 | C85: =VLOOKUP(B85,Fornecedores!A:B,2,0) -> EASY 5 SOLUCOES LTDA | D85: JESSY | E85: 00000421 | F85: 45726 | G85: 25200 | H85: =VLOOKUP(E85&B85,'Conf Oracle'!A:F,6,0) -> 45730.545 | I85: Ok | J85: =IF(OR(ISBLANK(F85), ISBLANK(H85)), "", IFERROR(NETWORKDAYS(F85, H85), "")) -> 5
A86: 45734 | B86: 57623555000107 | C86: =VLOOKUP(B86,Fornecedores!A:B,2,0) -> MAGICCOMP ENG E SERV DE INFORMATICA LTDA | D86: JESSY | E86: 00052900 | F86: 45727 | G86: 30690 | H86: =VLOOKUP(E86&B86,'Conf Oracle'!A:F,6,0) -> 45743.446 | I86: OC_0007415 Aguardando aprovação da OC | J86: =IF(OR(ISBLANK(F86), ISBLANK(H86)), "", IFERROR(NETWORKDAYS(F86, H86), "")) -> 13
... A92: 45734 | B92: 10835932000108 | C92: =VLOOKUP(B92,Fornecedores!A:B,2,0) -> COMPANHIA ENERGETICA DE PERNANBUCO | D92: EVANDREA | E92: 49784665 | F92: 45727 | G92: 32865.3 | H92: =VLOOKUP(E92&B92,'Conf Oracle'!A:F,6,0) -> 45733.503 | I92: Lançada | J92: =IF(OR(ISBLANK(F92), ISBLANK(H92)), "", IFERROR(NETWORKDAYS(F92, H92), "")) -> 5
A93: 45734 | B93: 33806738000108 | C93: =VLOOKUP(B93,Fornecedores!A:B,2,0) -> PWC STRATEGY& DO BRASIL CONSULTORIA EMPRESARIAL LTDA | D93: GUILHERME | E93: 00004204 | F93: 45719 | G93: 36000 | H93: =VLOOKUP(E93&B93,'Conf Oracle'!A:F,6,0) -> 45728.461 | J93: =IF(OR(ISBLANK(F93), ISBLANK(H93)), "", IFERROR(NETWORKDAYS(F93, H93), "")) -> 8
A94: 45734 | B94: 81785545000152 | C94: =VLOOKUP(B94,Fornecedores!A:B,2,0) -> DEL GRANDE INFO E TELEC IND E COM LTDA | D94: PEDRO | E94: 00003821 | F94: 45719 | G94: 5077 | H94: =VLOOKUP(E94&B94,'Conf Oracle'!A:F,6,0) -> 45735.407 | I94: Lançada | J94: =IF(OR(ISBLANK(F94), ISBLANK(H94)), "", IFERROR(NETWORKDAYS(F94, H94), "")) -> 13
A95: 45734 | B95: 81785545000152 | C95: =VLOOKUP(B95,Fornecedores!A:B,2,0) -> DEL GRANDE INFO E TELEC IND E COM LTDA | D95: PEDRO | E95: 00003823 | F95: 45719 | G95: 3151.24 | H95: =VLOOKUP(E95&B95,'Conf Oracle'!A:F,6,0) -> 45735.398 | I95: Lançada | J95: =IF(OR(ISBLANK(F95), ISBLANK(H95)), "", IFERROR(NETWORKDAYS(F95, H95), "")) -> 13
A96: 45734 | B96: 81785545000152 | C96: =VLOOKUP(B96,Fornecedores!A:B,2,0) -> DEL GRANDE INFO E TELEC IND E COM LTDA | D96: PEDRO | E96: 00003822 | F96: 45719 | G96: 1618.7 | H96: =VLOOKUP(E96&B96,'Conf Oracle'!A:F,6,0) -> 45735.381 | I96: Lançada | J96: =IF(OR(ISBLANK(F96), ISBLANK(H96)), "", IFERROR(NETWORKDAYS(F96, H96), "")) -> 13
A97: 45734 | B97: 81785545000152 | C97: =VLOOKUP(B97,Fornecedores!A:B,2,0) -> DEL GRANDE INFO E TELEC IND E COM LTDA | D97: PEDRO | E97: 00003824 | F97: 45719 | G97: 2825.73 | H97: =VLOOKUP(E97&B97,'Conf Oracle'!A:F,6,0) -> 45735.404 | I97: Lançada | J97: =IF(OR(ISBLANK(F97), ISBLANK(H97)), "", IFERROR(NETWORKDAYS(F97, H97), "")) -> 13
A98: 45734 | B98: 08312587000186 | C98: =VLOOKUP(B98,Fornecedores!A:B,2,0) -> CURADO COMUNICACAO LTDA | D98: PEDRO | E98: 00001365 | F98: 45721 | G98: 23400 | H98: =VLOOKUP(E98&B98,'Conf Oracle'!A:F,6,0) -> 45734.65 | I98: Lançada | J98: =IF(OR(ISBLANK(F98), ISBLANK(H98)), "", IFERROR(NETWORKDAYS(F98, H98), "")) -> 10
A99: 45734 | B99: 30608514000195 | C99: =VLOOKUP(B99,Fornecedores!A:B,2,0) -> AGENCIA FR DE COMUNICACAO LTDA | D99: PEDRO | E99: 00003879 | F99: 45722 | G99: 38034.8 | H99: =VLOOKUP(E99&B99,'Conf Oracle'!A:F,6,0) -> 45735.467 | I99: Lançada | J99: =IF(OR(ISBLANK(F99), ISBLANK(H99)), "", IFERROR(NETWORKDAYS(F99, H99), "")) -> 10
A100: 45734 | B100: 08399167000189 | C100: =VLOOKUP(B100,Fornecedores!A:B,2,0) -> ICTS GLOBAL DO BRASIL LTDA | D100: PEDRO | E100: 00067978 | F100: 45728 | G100: 799 | H100: =VLOOKUP(E100&B100,'Conf Oracle'!A:F,6,0) -> 45749.59 | I100: Lançada | J100: =IF(OR(ISBLANK(F100), ISBLANK(H100)), "", IFERROR(NETWORKDAYS(F100, H100), "")) -> 16
A101: 45734 | B101: 23007579000110 | C101: =VLOOKUP(B101,Fornecedores!A:B,2,0) -> PERINITY - SOLUCOES E SERVICOS EM GOVERNANCA LTDA | D101: PEDRO | E101: 00010102 | F101: 45729 | G101: 7230.05 | H101: =VLOOKUP(E101&B101,'Conf Oracle'!A:F,6,0) -> 45735.482 | I101: Lançada | J101: =IF(OR(ISBLANK(F101), ISBLANK(H101)), "", IFERROR(NETWORKDAYS(F101, H101), "")) -> 5
A102: 45734 | B102: 00005468 | C102: =VLOOKUP(B102,Fornecedores!A:B,2,0) -> AMAZON WEB SERVICES LLC | D102: SUNARA | E102: 109734752665 | F102: 45717 | G102: 5.53 | H102: =VLOOKUP(E102&B102,'Conf Oracle'!A:F,6,0) -> 45741.653 | J102: =IF(OR(ISBLANK(F102), ISBLANK(H102)), "", IFERROR(NETWORKDAYS(F102, H102), "")) -> 17
A103: 45734 | B103: 09162855000517 | C103: =VLOOKUP(B103,Fornecedores!A:B,2,0) -> PTLS SERV TECNOLOGIA E ASSESS TECN LTDA | D103: SUNARA | E103: 00215220 | F103: 45721 | G103: 6363.07 | H103: =VLOOKUP(E103&B103,'Conf Oracle'!A:F,6,0) -> 45727.378 | J103: =IF(OR(ISBLANK(F103), ISBLANK(H103)), "", IFERROR(NETWORKDAYS(F103, H103), "")) -> 5
A104: 45734 | B104: 09162855000517 | C104: =VLOOKUP(B104,Fornecedores!A:B,2,0) -> PTLS SERV TECNOLOGIA E ASSESS TECN LTDA | D104: SUNARA | E104: 00215221 | F104: 45721 | G104: 30803.59 | H104: =VLOOKUP(E104&B104,'Conf Oracle'!A:F,6,0) -> 45727.373 | J104: =IF(OR(ISBLANK(F104), ISBLANK(H104)), "", IFERROR(NETWORKDAYS(F104, H104), "")) -> 5
A105: 45734 | B105: 01609514000101 | C105: =VLOOKUP(B105,Fornecedores!A:B,2,0) -> E-HUNTER TECNOLOGIA DA INFORMAÇÃO LTDA | D105: SUNARA | E105: 00005434 | F105: 45721 | G105: 2614 | H105: =VLOOKUP(E105&B105,'Conf Oracle'!A:F,6,0) -> 45749.47 | I105: OC_0008305 | J105: =IF(OR(ISBLANK(F105), ISBLANK(H105)), "", IFERROR(NETWORKDAYS(F105, H105), "")) -> 21
A106: 45734 | B106: 58652678000139 | C106: =VLOOKUP(B106,Fornecedores!A:B,2,0) -> COLUMBIA STORAGE INTEGR DE SITEMAS LTDA | D106: SUNARA | E106: 00000520 | F106: 45722 | G106: 5838.94 | H106: =VLOOKUP(E106&B106,'Conf Oracle'!A:F,6,0) -> 45740.614 | J106: =IF(OR(ISBLANK(F106), ISBLANK(H106)), "", IFERROR(NETWORKDAYS(F106, H106), "")) -> 13
A107: 45734 | B107: 58652678000139 | C107: =VLOOKUP(B107,Fornecedores!A:B,2,0) -> COLUMBIA STORAGE INTEGR DE SITEMAS LTDA | D107: SUNARA | E107: 00000519 | F107: 45722 | G107: 5838.94 | H107: =VLOOKUP(E107&B107,'Conf Oracle'!A:F,6,0) -> 45740.605 | J107: =IF(OR(ISBLANK(F107), ISBLANK(H107)), "", IFERROR(NETWORKDAYS(F107, H107), "")) -> 13
...

Sheet Controle de NF - Fevereiro
A2: Mês | B2: CNPJ | C2: Fornecedor | D2: Gestor Adm | E2: NF | F2: Emissão da NF | G2: Valor da NF | H2: Conferência | I2: Observação | J2: SLA
A3: 45705 | B3: 16554325000156 | C3: =VLOOKUP(B3,Fornecedores!A:B,2,0) -> AMBIENTE VERDE RESIDUOS LTDA | D3: EVANDREA | E3: 00000735 | F3: 45691 | G3: 2690 | H3: =VLOOKUP(E3&B3,'Conf Oracle'!A:F,6,0) -> 45708.666 | I3: não lançada | J3: =IF(OR(ISBLANK(F3), ISBLANK(H3)), "", IFERROR(NETWORKDAYS(F3, H3), "")) -> 14
A4: 45705 | B4: 16554325000156 | C4: =VLOOKUP(B4,Fornecedores!A:B,2,0) -> AMBIENTE VERDE RESIDUOS LTDA | D4: EVANDREA | E4: 00000741 | F4: 45692 | G4: 2490 | H4: =VLOOKUP(E4&B4,'Conf Oracle'!A:F,6,0) -> #N/A | I4: não lançada verificar se há duplicidade | J4: =IF(OR(ISBLANK(F4), ISBLANK(H4)), "", IFERROR(NETWORKDAYS(F4, H4), ""))
A5: 45705 | B5: 16554325000156 | C5: =VLOOKUP(B5,Fornecedores!A:B,2,0) -> AMBIENTE VERDE RESIDUOS LTDA | D5: EVANDREA | E5: 00000742 | F5: 45692 | G5: 2690 | H5: =VLOOKUP(E5&B5,'Conf Oracle'!A:F,6,0) -> 45708.657 | I5: não lançada | J5: =IF(OR(ISBLANK(F5), ISBLANK(H5)), "", IFERROR(NETWORKDAYS(F5, H5), "")) -> 13
A6: 45705 | B6: 08270682000164 | C6: =VLOOKUP(B6,Fornecedores!A:B,2,0) -> CONFIDERE IMOBILIARIA LTDA | D6: EVANDREA | E6: 00202502 | F6: 45689 | G6: 2737093.3 | H6: =VLOOKUP(E6&B6,'Conf Oracle'!A:F,6,0) -> 45701.496 | J6: =IF(OR(ISBLANK(F6), ISBLANK(H6)), "", IFERROR(NETWORKDAYS(F6, H6), "")) -> 9
A7: 45705 | B7: 16554325000156 | C7: =VLOOKUP(B7,Fornecedores!A:B,2,0) -> AMBIENTE VERDE RESIDUOS LTDA | D7: EVANDREA | E7: 00000750 | F7: 45692 | G7: 2490 | H7: =VLOOKUP(E7&B7,'Conf Oracle'!A:F,6,0) -> 45708.42 | I7: não lançada verificar se há duplicidade | J7: =IF(OR(ISBLANK(F7), ISBLANK(H7)), "", IFERROR(NETWORKDAYS(F7, H7), "")) -> 13
A8: 45705 | B8: 29650979000125 | C8: =VLOOKUP(B8,Fornecedores!A:B,2,0) -> CAPACITARE RECURSOS HUMANOS EIRELI | D8: EVANDREA | E8: 00002158 | F8: 45692 | G8: 16560 | H8: =VLOOKUP(E8&B8,'Conf Oracle'!A:F,6,0) -> 45708.682 | I8: não lançada | J8: =IF(OR(ISBLANK(F8), ISBLANK(H8)), "", IFERROR(NETWORKDAYS(F8, H8), "")) -> 13
A9: 45705 | B9: 00028986001694 | C9: =VLOOKUP(B9,Fornecedores!A:B,2,0) -> ELEVADORES ATLAS SCHINDLER SA | D9: EVANDREA | E9: 00463366 | F9: 45693 | G9: 1960.94 | H9: =VLOOKUP(E9&B9,'Conf Oracle'!A:F,6,0) -> 45705.373 | J9: =IF(OR(ISBLANK(F9), ISBLANK(H9)), "", IFERROR(NETWORKDAYS(F9, H9), "")) -> 9
A10: 45705 | B10: 16554325000156 | C10: =VLOOKUP(B10,Fornecedores!A:B,2,0) -> AMBIENTE VERDE RESIDUOS LTDA | D10: EVANDREA | E10: 00000760 | F10: 45693 | G10: 8839.27 | H10: =VLOOKUP(E10&B10,'Conf Oracle'!A:F,6,0) -> 45713.33 | I10: não lançada | J10: =IF(OR(ISBLANK(F10), ISBLANK(H10)), "", IFERROR(NETWORKDAYS(F10, H10), "")) -> 15
A11: 45705 | B11: 90347840005691 | C11: =VLOOKUP(B11,Fornecedores!A:B,2,0) -> TK ELEVADORES BRASIL LTDA. | D11: EVANDREA | E11: 00111690 | F11: 45691 | G11: 13781.17 | H11: =VLOOKUP(E11&B11,'Conf Oracle'!A:F,6,0) -> 45712.443 | I11: não lançada | J11: =IF(OR(ISBLANK(F11), ISBLANK(H11)), "", IFERROR(NETWORKDAYS(F11, H11), "")) -> 16
A12: 45705 | B12: 00973749000115 | C12: =VLOOKUP(B12,Fornecedores!A:B,2,0) -> TOP SERVICE SERVICOS E SISTEMAS S/A | D12: EVANDREA | E12: 00209441 | F12: 45700 | G12: 128116.16 | H12: =VLOOKUP(E12&B12,'Conf Oracle'!A:F,6,0) -> 45715.577 | I12: não lançada | J12: =IF(OR(ISBLANK(F12), ISBLANK(H12)), "", IFERROR(NETWORKDAYS(F12, H12), "")) -> 12
A13: 45705 | B13: 05208211000138 | C13: =VLOOKUP(B13,Fornecedores!A:B,2,0) -> IN-HAUS INDUSTRIAL E SERVICOS DE LOGISTICA LTDA | D13: EVANDREA | E13: 00116491 | F13: 45700 | G13: 102014.63 | H13: =VLOOKUP(E13&B13,'Conf Oracle'!A:F,6,0) -> 45715.442 | I13: não lançada | J13: =IF(OR(ISBLANK(F13), ISBLANK(H13)), "", IFERROR(NETWORKDAYS(F13, H13), "")) -> 12
A14: 45705 | B14: 00082024000137 | C14: =VLOOKUP(B14,Fornecedores!A:B,2,0) -> COMPANHIA DE SANEAMENTO AMBIENTAL DO DISTRITO FEDERAL | D14: EVANDREA | E14: 00022025 | F14: 45701 | G14: 20344.29 | H14: =VLOOKUP(E14&B14,'Conf Oracle'!A:F,6,0) -> #N/A | I14: não lançada | J14: =IF(OR(ISBLANK(F14), ISBLANK(H14)), "", IFERROR(NETWORKDAYS(F14, H14), ""))
A15: 45705 | B15: 23412247000110 | C15: =VLOOKUP(B15,Fornecedores!A:B,2,0) -> AMAZON AWS SERVICOS BRASIL LTDA | D15: INGRID | E15: 03992954 | F15: 45690 | G15: 584634.01 | H15: =VLOOKUP(E15&B15,'Conf Oracle'!A:F,6,0) -> 45722.639 | J15: =IF(OR(ISBLANK(F15), ISBLANK(H15)), "", IFERROR(NETWORKDAYS(F15, H15), "")) -> 24
A16: 45705 | B16: 23412247000110 | C16: =VLOOKUP(B16,Fornecedores!A:B,2,0) -> AMAZON AWS SERVICOS BRASIL LTDA | D16: INGRID | E16: 28672561 | F16: 45689 | G16: 584631.74 | H16: =VLOOKUP(E16&B16,'Conf Oracle'!A:F,6,0) -> #N/A | J16: =IF(OR(ISBLANK(F16), ISBLANK(H16)), "", IFERROR(NETWORKDAYS(F16, H16), ""))
A17: 45705 | B17: 23412247000110 | C17: =VLOOKUP(B17,Fornecedores!A:B,2,0) -> AMAZON AWS SERVICOS BRASIL LTDA | D17: INGRID | E17: 03993947 | F17: 45690 | G17: 71814.74 | H17: =VLOOKUP(E17&B17,'Conf Oracle'!A:F,6,0) -> 45722.671 | J17: =IF(OR(ISBLANK(F17), ISBLANK(H17)), "", IFERROR(NETWORKDAYS(F17, H17), "")) -> 24
A18: 45705 | B18: 23412247000110 | C18: =VLOOKUP(B18,Fornecedores!A:B,2,0) -> AMAZON AWS SERVICOS BRASIL LTDA | D18: INGRID | E18: 03993950 | F18: 45690 | G18: 42206.14 | H18: =VLOOKUP(E18&B18,'Conf Oracle'!A:F,6,0) -> 45722.66 | J18: =IF(OR(ISBLANK(F18), ISBLANK(H18)), "", IFERROR(NETWORKDAYS(F18, H18), "")) -> 24
A19: 45705 | B19: 23412247000110 | C19: =VLOOKUP(B19,Fornecedores!A:B,2,0) -> AMAZON AWS SERVICOS BRASIL LTDA | D19: INGRID | E19: 28766029 | F19: 45689 | G19: 114021.02 | H19: =VLOOKUP(E19&B19,'Conf Oracle'!A:F,6,0) -> #N/A | J19: =IF(OR(ISBLANK(F19), ISBLANK(H19)), "", IFERROR(NETWORKDAYS(F19, H19), ""))
A20: 45705 | B20: 07850212000107 | C20: =VLOOKUP(B20,Fornecedores!A:B,2,0) -> REAL SEGURANCA INTEGRADA EIRELI | D20: INGRID | E20: 00001052 | F20: 45692 | G20: 222.35 | H20: =VLOOKUP(E20&B20,'Conf Oracle'!A:F,6,0) -> #N/A | J20: =IF(OR(ISBLANK(F20), ISBLANK(H20)), "", IFERROR(NETWORKDAYS(F20, H20), ""))
A21: 45705 | B21: 96534094000158 | C21: =VLOOKUP(B21,Fornecedores!A:B,2,0) -> ACCENTURE DO BRASIL LTDA | D21: INGRID | E21: 00101006 | F21: 45698 | G21: 183243.6 | H21: =VLOOKUP(E21&B21,'Conf Oracle'!A:F,6,0) -> 45722.653 | J21: =IF(OR(ISBLANK(F21), ISBLANK(H21)), "", IFERROR(NETWORKDAYS(F21, H21), "")) -> 19
A22: 45705 | B22: 96534094000158 | C22: =VLOOKUP(B22,Fornecedores!A:B,2,0) -> ACCENTURE DO BRASIL LTDA | D22: INGRID | E22: 00101007 | F22: 45698 | G22: 43999.2 | H22: =VLOOKUP(E22&B22,'Conf Oracle'!A:F,6,0) -> 45722.621 | J22: =IF(OR(ISBLANK(F22), ISBLANK(H22)), "", IFERROR(NETWORKDAYS(F22, H22), "")) -> 19
A23: 45705 | B23: 02558157013574 | C23: =VLOOKUP(B23,Fornecedores!A:B,2,0) -> TELEFONICA BRASIL SA | D23: INGRID | E23: 00295537 | F23: 45696 | G23: 1110.62 | H23: =VLOOKUP(E23&B23,'Conf Oracle'!A:F,6,0) -> #N/A | J23: =IF(OR(ISBLANK(F23), ISBLANK(H23)), "", IFERROR(NETWORKDAYS(F23, H23), ""))
A24: 45705 | B24: 02558157013574 | C24: =VLOOKUP(B24,Fornecedores!A:B,2,0) -> TELEFONICA BRASIL SA | D24: INGRID | E24: 00297385 | F24: 45696 | G24: 360 | H24: =VLOOKUP(E24&B24,'Conf Oracle'!A:F,6,0) -> #N/A | J24: =IF(OR(ISBLANK(F24), ISBLANK(H24)), "", IFERROR(NETWORKDAYS(F24, H24), ""))
A25: 45705 | B25: 02558157013574 | C25: =VLOOKUP(B25,Fornecedores!A:B,2,0) -> TELEFONICA BRASIL SA | D25: INGRID | E25: 00292887 | F25: 45696 | G25: 882.79 | H25: =VLOOKUP(E25&B25,'Conf Oracle'!A:F,6,0) -> #N/A | J25: =IF(OR(ISBLANK(F25), ISBLANK(H25)), "", IFERROR(NETWORKDAYS(F25, H25), ""))
A26: 45705 | B26: 02558157013574 | C26: =VLOOKUP(B26,Fornecedores!A:B,2,0) -> TELEFONICA BRASIL SA | D26: INGRID | E26: 00293088 | F26: 45696 | G26: 1080 | H26: =VLOOKUP(E26&B26,'Conf Oracle'!A:F,6,0) -> #N/A | J26: =IF(OR(ISBLANK(F26), ISBLANK(H26)), "", IFERROR(NETWORKDAYS(F26, H26), ""))
... A35: 45705 | B35: 00593850000221 | C35: =VLOOKUP(B35,Fornecedores!A:B,2,0) -> RERUM ENGENHARIA DE SISTEMAS LTDA | D35: INGRID | E35: 00000645 | F35: 45699 | G35: 41287.84 | H35: =VLOOKUP(E35&B35,'Conf Oracle'!A:F,6,0) -> #N/A | J35: =IF(OR(ISBLANK(F35), ISBLANK(H35)), "", IFERROR(NETWORKDAYS(F35, H35), ""))
A36: 45705 | B36: 07850212000107 | C36: =VLOOKUP(B36,Fornecedores!A:B,2,0) -> REAL SEGURANCA INTEGRADA EIRELI | D36: INGRID | E36: 00001080 | F36: 45700 | G36: 217.9 | H36: =VLOOKUP(E36&B36,'Conf Oracle'!A:F,6,0) -> 45700.671 | I36: NF COM MESMO NÚMERO DE FORNECEDORES DIFERENTES | J36: =IF(OR(ISBLANK(F36), ISBLANK(H36)), "", IFERROR(NETWORKDAYS(F36, H36), "")) -> 1
A37: 45705 | B37: 02408485000182 | C37: =VLOOKUP(B37,Fornecedores!A:B,2,0) -> MULTIVIS BRASIL LTDA | D37: INGRID | E37: 00002480 | F37: 45700 | G37: 76829.38 | H37: =VLOOKUP(E37&B37,'Conf Oracle'!A:F,6,0) -> 45722.586 | J37: =IF(OR(ISBLANK(F37), ISBLANK(H37)), "", IFERROR(NETWORKDAYS(F37, H37), "")) -> 17
A38: 45705 | B38: 26409092000151 | C38: =VLOOKUP(B38,Fornecedores!A:B,2,0) -> SSAMRO SOLUCOES PARA MANUTENCAO INDUSTR | D38: ISABELA | E38: 00024003 | F38: 45691 | G38: 648.76 | H38: =VLOOKUP(E38&B38,'Conf Oracle'!A:F,6,0) -> 45699.377 | J38: =IF(OR(ISBLANK(F38), ISBLANK(H38)), "", IFERROR(NETWORKDAYS(F38, H38), "")) -> 7
A39: 45705 | B39: 26409092000151 | C39: =VLOOKUP(B39,Fornecedores!A:B,2,0) -> SSAMRO SOLUCOES PARA MANUTENCAO INDUSTR | D39: ISABELA | E39: 00024008 | F39: 45691 | G39: 648.76 | H39: =VLOOKUP(E39&B39,'Conf Oracle'!A:F,6,0) -> 45699.375 | J39: =IF(OR(ISBLANK(F39), ISBLANK(H39)), "", IFERROR(NETWORKDAYS(F39, H39), "")) -> 7
A40: 45705 | B40: 26409092000151 | C40: =VLOOKUP(B40,Fornecedores!A:B,2,0) -> SSAMRO SOLUCOES PARA MANUTENCAO INDUSTR | D40: ISABELA | E40: 00024016 | F40: 45691 | G40: 648.76 | H40: =VLOOKUP(E40&B40,'Conf Oracle'!A:F,6,0) -> 45699.374 | J40: =IF(OR(ISBLANK(F40), ISBLANK(H40)), "", IFERROR(NETWORKDAYS(F40, H40), "")) -> 7
A41: 45705 | B41: 26409092000151 | C41: =VLOOKUP(B41,Fornecedores!A:B,2,0) -> SSAMRO SOLUCOES PARA MANUTENCAO INDUSTR | D41: ISABELA | E41: 00024024 | F41: 45691 | G41: 648.76 | H41: =VLOOKUP(E41&B41,'Conf Oracle'!A:F,6,0) -> 45699.372 | J41: =IF(OR(ISBLANK(F41), ISBLANK(H41)), "", IFERROR(NETWORKDAYS(F41, H41), "")) -> 7
A42: 45705 | B42: 07751071000175 | C42: =VLOOKUP(B42,Fornecedores!A:B,2,0) -> TELEGESTAO SISTEMAS DE ATEND LTDA | D42: ISABELA | E42: 00000876 | F42: 45691 | G42: 700 | H42: =VLOOKUP(E42&B42,'Conf Oracle'!A:F,6,0) -> 45698.483 | J42: =IF(OR(ISBLANK(F42), ISBLANK(H42)), "", IFERROR(NETWORKDAYS(F42, H42), "")) -> 6
A43: 45705 | B43: 69034668000156 | C43: =VLOOKUP(B43,Fornecedores!A:B,2,0) -> PLUXEE BENEFICIOS BRASIL SA | D43: ISABELA | E43: 04356679 | F43: 45692 | G43: 1981.41 | H43: =VLOOKUP(E43&B43,'Conf Oracle'!A:F,6,0) -> 45693.652 | J43: =IF(OR(ISBLANK(F43), ISBLANK(H43)), "", IFERROR(NETWORKDAYS(F43, H43), "")) -> 2
A44: 45705 | B44: 69034668000156 | C44: =VLOOKUP(B44,Fornecedores!A:B,2,0) -> PLUXEE BENEFICIOS BRASIL SA | D44: ISABELA | E44: 04356677 | F44: 45692 | G44: 4946.59 | H44: =VLOOKUP(E44&B44,'Conf Oracle'!A:F,6,0) -> 45693.698 | J44: =IF(OR(ISBLANK(F44), ISBLANK(H44)), "", IFERROR(NETWORKDAYS(F44, H44), "")) -> 2
A45: 45705 | B45: 15491115000101 | C45: =VLOOKUP(B45,Fornecedores!A:B,2,0) -> CS INTEGRA SOLUCOES EM TECNOLOG LTDA ME | D45: ISABELA | E45: 00006163 | F45: 45692 | G45: 3093 | H45: =VLOOKUP(E45&B45,'Conf Oracle'!A:F,6,0) -> 45698.402 | J45: =IF(OR(ISBLANK(F45), ISBLANK(H45)), "", IFERROR(NETWORKDAYS(F45, H45), "")) -> 5
A46: 45705 | B46: 72157654000215 | C46: =VLOOKUP(B46,Fornecedores!A:B,2,0) -> VELA SOFTWARE E SERVICOS LTDA | D46: ISABELA | E46: 00003085 | F46: 45693 | G46: 677.6 | H46: =VLOOKUP(E46&B46,'Conf Oracle'!A:F,6,0) -> #N/A | J46: =IF(OR(ISBLANK(F46), ISBLANK(H46)), "", IFERROR(NETWORKDAYS(F46, H46), ""))
A47: 45705 | B47: 72157654000215 | C47: =VLOOKUP(B47,Fornecedores!A:B,2,0) -> VELA SOFTWARE E SERVICOS LTDA | D47: ISABELA | E47: 00003086 | F47: 45693 | G47: 677.6 | H47: =VLOOKUP(E47&B47,'Conf Oracle'!A:F,6,0) -> #N/A | J47: =IF(OR(ISBLANK(F47), ISBLANK(H47)), "", IFERROR(NETWORKDAYS(F47, H47), ""))
A48: 45705 | B48: 72157654000215 | C48: =VLOOKUP(B48,Fornecedores!A:B,2,0) -> VELA SOFTWARE E SERVICOS LTDA | D48: ISABELA | E48: 00003089 | F48: 45693 | G48: 677.6 | H48: =VLOOKUP(E48&B48,'Conf Oracle'!A:F,6,0) -> #N/A | J48: =IF(OR(ISBLANK(F48), ISBLANK(H48)), "", IFERROR(NETWORKDAYS(F48, H48), ""))
... A78: 45705 | B78: 09305983000149 | C78: =VLOOKUP(B78,Fornecedores!A:B,2,0) -> PSR SOLUCOES CONSULTORIA EM ENERGIA LTDA | D78: PEDRO | E78: 00013307 | F78: 45693 | G78: 120000 | H78: =VLOOKUP(E78&B78,'Conf Oracle'!A:F,6,0) -> 45698.382 | J78: =IF(OR(ISBLANK(F78), ISBLANK(H78)), "", IFERROR(NETWORKDAYS(F78, H78), "")) -> 4
A79: 45705 | B79: 45660322000103 | C79: =VLOOKUP(B79,Fornecedores!A:B,2,0) -> SOLAR SOLUTIONS SOLUCOES SOLARES LTDA | D79: PEDRO | E79: 00000133 | F79: 45695 | G79: 10000 | H79: =VLOOKUP(E79&B79,'Conf Oracle'!A:F,6,0) -> #N/A | I79: LANÇADA | J79: =IF(OR(ISBLANK(F79), ISBLANK(H79)), "", IFERROR(NETWORKDAYS(F79, H79), ""))
A80: 45705 | B80: 10334263000190 | C80: =VLOOKUP(B80,Fornecedores!A:B,2,0) -> HYDROBYTE SOFTWARE EIRELI | D80: PEDRO | E80: 00000452 | F80: 45700 | G80: 34547.12 | H80: =VLOOKUP(E80&B80,'Conf Oracle'!A:F,6,0) -> 45712.652 | J80: =IF(OR(ISBLANK(F80), ISBLANK(H80)), "", IFERROR(NETWORKDAYS(F80, H80), "")) -> 9
A81: 45705 | B81: 36397714000122 | C81: =VLOOKUP(B81,Fornecedores!A:B,2,0) -> MONTFRAN CONSULTORIA EM ENERGIA LIMITADA | D81: PEDRO | E81: 00000086 | F81: 45701 | G81: 36000 | H81: =VLOOKUP(E81&B81,'Conf Oracle'!A:F,6,0) -> 45715.625 | J81: =IF(OR(ISBLANK(F81), ISBLANK(H81)), "", IFERROR(NETWORKDAYS(F81, H81), "")) -> 11
A82: 45705 | B82: 30608514000195 | C82: =VLOOKUP(B82,Fornecedores!A:B,2,0) -> AGENCIA FR DE COMUNICACAO LTDA | D82: PEDRO | E82: 00003813 | F82: 45701 | G82: 38034.8 | H82: =VLOOKUP(E82&B82,'Conf Oracle'!A:F,6,0) -> 45712.492 | J82: =IF(OR(ISBLANK(F82), ISBLANK(H82)), "", IFERROR(NETWORKDAYS(F82, H82), "")) -> 8
A83: 45705 | B83: 58652678000139 | C83: =VLOOKUP(B83,Fornecedores!A:B,2,0) -> COLUMBIA STORAGE INTEGR DE SITEMAS LTDA | D83: SUNARA | E83: 00000516 | F83: 45691 | G83: 5838.94 | H83: =VLOOKUP(E83&B83,'Conf Oracle'!A:F,6,0) -> 45698.666 | J83: =IF(OR(ISBLANK(F83), ISBLANK(H83)), "", IFERROR(NETWORKDAYS(F83, H83), "")) -> 6
A84: 45705 | B84: 58652678000139 | C84: =VLOOKUP(B84,Fornecedores!A:B,2,0) -> COLUMBIA STORAGE INTEGR DE SITEMAS LTDA | D84: SUNARA | E84: 00000517 | F84: 45691 | G84: 5838.94 | H84: =VLOOKUP(E84&B84,'Conf Oracle'!A:F,6,0) -> 45698.681 | J84: =IF(OR(ISBLANK(F84), ISBLANK(H84)), "", IFERROR(NETWORKDAYS(F84, H84), "")) -> 6
A85: 45705 | B85: 09162855000517 | C85: =VLOOKUP(B85,Fornecedores!A:B,2,0) -> PTLS SERV TECNOLOGIA E ASSESS TECN LTDA | D85: SUNARA | E85: 00214567 | F85: 45691 | G85: 6363.07 | H85: =VLOOKUP(E85&B85,'Conf Oracle'!A:F,6,0) -> 45699.32 | J85: =IF(OR(ISBLANK(F85), ISBLANK(H85)), "", IFERROR(NETWORKDAYS(F85, H85), "")) -> 7
A86: 45705 | B86: 09162855000517 | C86: =VLOOKUP(B86,Fornecedores!A:B,2,0) -> PTLS SERV TECNOLOGIA E ASSESS TECN LTDA | D86: SUNARA | E86: 00214568 | F86: 45691 | G86: 30803.59 | H86: =VLOOKUP(E86&B86,'Conf Oracle'!A:F,6,0) -> 45698.723 | J86: =IF(OR(ISBLANK(F86), ISBLANK(H86)), "", IFERROR(NETWORKDAYS(F86, H86), "")) -> 6
A87: 45705 | B87: 00191027000109 | C87: =VLOOKUP(B87,Fornecedores!A:B,2,0) -> FACILIT TECNOLOGIA LTDA EPP | D87: SUNARA | E87: 00003626 | F87: 45692 | G87: 13496 | H87: =VLOOKUP(E87&B87,'Conf Oracle'!A:F,6,0) -> 45699.485 | J87: =IF(OR(ISBLANK(F87), ISBLANK(H87)), "", IFERROR(NETWORKDAYS(F87, H87), "")) -> 6
A88: 45705 | B88: 22772012000177 | C88: =VLOOKUP(B88,Fornecedores!A:B,2,0) -> SPECIALISTERNE BRASIL CAPACITACAO EM SERVICOS RELACIONADOS A TECNOLOGIA, INFORMATICA E CONSULTORIA EMPRESARIAL LTDA. | D88: SUNARA | E88: 00004681 | F88: 45693 | G88: 11095.04 | H88: =VLOOKUP(E88&B88,'Conf Oracle'!A:F,6,0) -> 45698.714 | J88: =IF(OR(ISBLANK(F88), ISBLANK(H88)), "", IFERROR(NETWORKDAYS(F88, H88), "")) -> 4
A89: 45705 | B89: 26990812000115 | C89: =VLOOKUP(B89,Fornecedores!A:B,2,0) -> TECNISYS INFORMATICA E ASSESSORIAL EMPRE | D89: SUNARA | E89: 00001388 | F89: 45698 | G89: 327429.35 | H89: =VLOOKUP(E89&B89,'Conf Oracle'!A:F,6,0) -> 45708.514 | J89: =IF(OR(ISBLANK(F89), ISBLANK(H89)), "", IFERROR(NETWORKDAYS(F89, H89), "")) -> 9
A90: 45705 | B90: 01468594000122 | C90: =VLOOKUP(B90,Fornecedores!A:B,2,0) -> LG INFORMATICA SA | D90: SUNARA | E90: 00173730 | F90: 45691 | G90: 33761.46 | H90: =VLOOKUP(E90&B90,'Conf Oracle'!A:F,6,0) -> 45712.499 | J90: =IF(OR(ISBLANK(F90), ISBLANK(H90)), "", IFERROR(NETWORKDAYS(F90, H90), "")) -> 16
A91: 45705 | B91: 01468594000122 | C91: =VLOOKUP(B91,Fornecedores!A:B,2,0) -> LG INFORMATICA SA | D91: SUNARA | E91: 00174415 | F91: 45700 | G91: 33761.46 | H91: =VLOOKUP(E91&B91,'Conf Oracle'!A:F,6,0) -> 45712.511 | J91: =IF(OR(ISBLANK(F91), ISBLANK(H91)), "", IFERROR(NETWORKDAYS(F91, H91), "")) -> 9
A92: 45705 | B92: 72381189000110 | C92: =VLOOKUP(B92,Fornecedores!A:B,2,0) -> DELL COMPUTADORES DO BRASIL LTDA | D92: SUNARA | E92: 02657998 | F92: 45702 | G92: 939.97 | H92: =VLOOKUP(E92&B92,'Conf Oracle'!A:F,6,0) -> #N/A | I92: SIMPLES REMESSA - BONIFICAÇÃO | J92: =IF(OR(ISBLANK(F92), ISBLANK(H92)), "", IFERROR(NETWORKDAYS(F92, H92), ""))
A93: 45715 | B93: 01731177000120 | C93: =VLOOKUP(B93,Fornecedores!A:B,2,0) -> RUSSEL REYNOLDS ASSOCIATES LTDA | D93: EVANDREA | E93: 00007356 | F93: 45705 | G93: 67930.03 | H93: =VLOOKUP(E93&B93,'Conf Oracle'!A:F,6,0) -> 45722.438 | J93: =IF(OR(ISBLANK(F93), ISBLANK(H93)), "", IFERROR(NETWORKDAYS(F93, H93), "")) -> 14
A94: 45715 | B94: 40432544000147 | C94: =VLOOKUP(B94,Fornecedores!A:B,2,0) -> CLARO SA | D94: EVANDREA | E94: 74580142 | F94: 45705 | G94: 117028.41 | H94: =VLOOKUP(E94&B94,'Conf Oracle'!A:F,6,0) -> #N/A | J94: =IF(OR(ISBLANK(F94), ISBLANK(H94)), "", IFERROR(NETWORKDAYS(F94, H94), ""))
A95: 45715 | B95: 40432544000147 | C95: =VLOOKUP(B95,Fornecedores!A:B,2,0) -> CLARO SA | D95: EVANDREA | E95: 745801422 | F95: 45705 | G95: 80564.7 | H95: =VLOOKUP(E95&B95,'Conf Oracle'!A:F,6,0) -> #N/A | J95: =IF(OR(ISBLANK(F95), ISBLANK(H95)), "", IFERROR(NETWORKDAYS(F95, H95), ""))
A96: 45715 | B96: 00028986003476 | C96: =VLOOKUP(B96,Fornecedores!A:B,2,0) -> ELEVADORES ATLAS SCHINDLER SA | D96: EVANDREA | E96: 00256938 | F96: 45694 | G96: 2069.88 | H96: =VLOOKUP(E96&B96,'Conf Oracle'!A:F,6,0) -> 45706.571 | J96: =IF(OR(ISBLANK(F96), ISBLANK(H96)), "", IFERROR(NETWORKDAYS(F96, H96), "")) -> 9
A97: 45715 | B97: 00028986000612 | C97: =VLOOKUP(B97,Fornecedores!A:B,2,0) -> ELEVADORES ATLAS SCHINDLER SA | D97: EVANDREA | E97: 00034706 | F97: 45694 | G97: 871.68 | H97: =VLOOKUP(E97&B97,'Conf Oracle'!A:F,6,0) -> 45706.557 | J97: =IF(OR(ISBLANK(F97), ISBLANK(H97)), "", IFERROR(NETWORKDAYS(F97, H97), "")) -> 9
A98: 45715 | B98: 35795954000201 | C98: =VLOOKUP(B98,Fornecedores!A:B,2,0) -> MED RIO CHECK UP MEDICINA PREVENTIVA LTDA | D98: EVANDREA | E98: 00023498 | F98: 45706 | G98: 21179.3 | H98: =VLOOKUP(E98&B98,'Conf Oracle'!A:F,6,0) -> 45722.503 | J98: =IF(OR(ISBLANK(F98), ISBLANK(H98)), "", IFERROR(NETWORKDAYS(F98, H98), "")) -> 13
A99: 45715 | B99: 07384360000183 | C99: =VLOOKUP(B99,Fornecedores!A:B,2,0) -> MAXXIMA AURORA NEGOCIOS IMOB. LTDA | D99: EVANDREA | E99: 00000043 | F99: 45705 | G99: 773126.72 | H99: =VLOOKUP(E99&B99,'Conf Oracle'!A:F,6,0) -> 45715.626 | J99: =IF(OR(ISBLANK(F99), ISBLANK(H99)), "", IFERROR(NETWORKDAYS(F99, H99), "")) -> 9
A100: 45715 | B100: 94001641000104 | C100: =VLOOKUP(B100,Fornecedores!A:B,2,0) -> BRINGER DO BRASIL AG CARGAS NAC INT LTDA | D100: EVANDREA | E100: 00544718 | F100: 45706 | G100: 3180.83 | H100: =VLOOKUP(E100&B100,'Conf Oracle'!A:F,6,0) -> 45722.382 | J100: =IF(OR(ISBLANK(F100), ISBLANK(H100)), "", IFERROR(NETWORKDAYS(F100, H100), "")) -> 13
A101: 45715 | B101: 42644220000106 | C101: =VLOOKUP(B101,Fornecedores!A:B,2,0) -> AGUAS DO RIO 4 SPE S.A | D101: EVANDREA | E101: 00764177 | F101: 45696 | G101: 54045.11 | H101: =VLOOKUP(E101&B101,'Conf Oracle'!A:F,6,0) -> 45708.647 | J101: =IF(OR(ISBLANK(F101), ISBLANK(H101)), "", IFERROR(NETWORKDAYS(F101, H101), "")) -> 9
A102: 45715 | B102: 43965130000171 | C102: =VLOOKUP(B102,Fornecedores!A:B,2,0) -> AGUAS CLARAS GASTRONOMIA E EVENTOS LTDA | D102: EVANDREA | E102: 00001066 | F102: 45707 | G102: 2400 | H102: =VLOOKUP(E102&B102,'Conf Oracle'!A:F,6,0) -> 45722.452 | J102: =IF(OR(ISBLANK(F102), ISBLANK(H102)), "", IFERROR(NETWORKDAYS(F102, H102), "")) -> 12
A103: 45715 | B103: 40015579000180 | C103: =VLOOKUP(B103,Fornecedores!A:B,2,0) -> AVENTIS RENTAL S.A | D103: EVANDREA | E103: REN06 | F103: 45708 | G103: 15116.88 | H103: =VLOOKUP(E103&B103,'Conf Oracle'!A:F,6,0) -> #N/A | J103: =IF(OR(ISBLANK(F103), ISBLANK(H103)), "", IFERROR(NETWORKDAYS(F103, H103), ""))
A104: 45715 | B104: 29650979000125 | C104: =VLOOKUP(B104,Fornecedores!A:B,2,0) -> CAPACITARE RECURSOS HUMANOS EIRELI | D104: EVANDREA | E104: 00002192 | F104: 45708 | G104: 16080 | H104: =VLOOKUP(E104&B104,'Conf Oracle'!A:F,6,0) -> 45722.385 | J104: =IF(OR(ISBLANK(F104), ISBLANK(H104)), "", IFERROR(NETWORKDAYS(F104, H104), "")) -> 11
... A144: 45715 | B144: 44591001000123 | C144: =VLOOKUP(B144,Fornecedores!A:B,2,0) -> EMERSON TANIGAWA TUBONI | D144: ISABELA | E144: 02025794 | F144: 45712 | G144: 19648.09 | H144: =VLOOKUP(E144&B144,'Conf Oracle'!A:F,6,0) -> 45713.602 | J144: =IF(OR(ISBLANK(F144), ISBLANK(H144)), "", IFERROR(NETWORKDAYS(F144, H144), "")) -> 2
A145: 45715 | B145: 08529788000130 | C145: =VLOOKUP(B145,Fornecedores!A:B,2,0) -> GRUPO KLINGNER DE APOIO A EMPRESAS LTDA | D145: ISABELA | H145: =VLOOKUP(E145&B145,'Conf Oracle'!A:F,6,0) -> #N/A | I145: ARQUIVO NF NÃO ABRE | J145: =IF(OR(ISBLANK(F145), ISBLANK(H145)), "", IFERROR(NETWORKDAYS(F145, H145), ""))
A146: 45715 | B146: 87169900001389 | C146: =VLOOKUP(B146,Fornecedores!A:B,2,0) -> GRABER SISTEMAS DE SEGURANCA LTDA | D146: ISABELA | E146: 00001354 | F146: 45712 | G146: 111691.36 | H146: =VLOOKUP(E146&B146,'Conf Oracle'!A:F,6,0) -> 45712.678 | J146: =IF(OR(ISBLANK(F146), ISBLANK(H146)), "", IFERROR(NETWORKDAYS(F146, H146), "")) -> 1
A147: 45715 | B147: 23211179000121 | C147: =VLOOKUP(B147,Fornecedores!A:B,2,0) -> LIDER SERVICOS GERAIS LTDA | D147: ISABELA | E147: 00011980 | F147: 45712 | G147: 94482.75 | H147: =VLOOKUP(E147&B147,'Conf Oracle'!A:F,6,0) -> 45713.498 | J147: =IF(OR(ISBLANK(F147), ISBLANK(H147)), "", IFERROR(NETWORKDAYS(F147, H147), "")) -> 2
A148: 45715 | B148: 23211179000121 | C148: =VLOOKUP(B148,Fornecedores!A:B,2,0) -> LIDER SERVICOS GERAIS LTDA | D148: ISABELA | E148: 00011981 | F148: 45712 | G148: 92188.47 | H148: =VLOOKUP(E148&B148,'Conf Oracle'!A:F,6,0) -> 45713.494 | J148: =IF(OR(ISBLANK(F148), ISBLANK(H148)), "", IFERROR(NETWORKDAYS(F148, H148), "")) -> 2
A149: 45715 | B149: 35272126000108 | C149: =VLOOKUP(B149,Fornecedores!A:B,2,0) -> RECOLD REFRIGERACAO S/C EIRELI | D149: ISABELA | E149: 00001483 | F149: 45712 | G149: 25270 | H149: =VLOOKUP(E149&B149,'Conf Oracle'!A:F,6,0) -> 45713.438 | J149: =IF(OR(ISBLANK(F149), ISBLANK(H149)), "", IFERROR(NETWORKDAYS(F149, H149), "")) -> 2
A150: 45715 | B150: 08736011000499 | C150: =VLOOKUP(B150,Fornecedores!A:B,2,0) -> GRAN COFFEE COMERCIO LOCACAO SERVICOS SA | D150: ISABELA | E150: 00274445 | F150: 45713 | G150: 17542.33 | H150: =VLOOKUP(E150&B150,'Conf Oracle'!A:F,6,0) -> #N/A | J150: =IF(OR(ISBLANK(F150), ISBLANK(H150)), "", IFERROR(NETWORKDAYS(F150, H150), ""))
A151: 45715 | B151: 08736011000499 | C151: =VLOOKUP(B151,Fornecedores!A:B,2,0) -> GRAN COFFEE COMERCIO LOCACAO SERVICOS SA | D151: ISABELA | E151: 00114153 | F151: 45713 | G151: 2825 | H151: =VLOOKUP(E151&B151,'Conf Oracle'!A:F,6,0) -> #N/A | J151: =IF(OR(ISBLANK(F151), ISBLANK(H151)), "", IFERROR(NETWORKDAYS(F151, H151), ""))
A152: 45715 | B152: 08736011000499 | C152: =VLOOKUP(B152,Fornecedores!A:B,2,0) -> GRAN COFFEE COMERCIO LOCACAO SERVICOS SA | D152: ISABELA | E152: 00274467 | F152: 45713 | G152: 17542.33 | H152: =VLOOKUP(E152&B152,'Conf Oracle'!A:F,6,0) -> 45722.655 | J152: =IF(OR(ISBLANK(F152), ISBLANK(H152)), "", IFERROR(NETWORKDAYS(F152, H152), "")) -> 8
A153: 45715 | B153: 08736011000499 | C153: =VLOOKUP(B153,Fornecedores!A:B,2,0) -> GRAN COFFEE COMERCIO LOCACAO SERVICOS SA | D153: ISABELA | E153: 00114154 | F153: 45713 | G153: 2825 | H153: =VLOOKUP(E153&B153,'Conf Oracle'!A:F,6,0) -> #N/A | J153: =IF(OR(ISBLANK(F153), ISBLANK(H153)), "", IFERROR(NETWORKDAYS(F153, H153), ""))
A154: 45715 | B154: 08736011000499 | C154: =VLOOKUP(B154,Fornecedores!A:B,2,0) -> GRAN COFFEE COMERCIO LOCACAO SERVICOS SA | D154: ISABELA | E154: 00037160 | F154: 45713 | G154: 1922.84 | H154: =VLOOKUP(E154&B154,'Conf Oracle'!A:F,6,0) -> #N/A | J154: =IF(OR(ISBLANK(F154), ISBLANK(H154)), "", IFERROR(NETWORKDAYS(F154, H154), ""))
A155: 45715 | B155: 05666393000190 | C155: =VLOOKUP(B155,Fornecedores!A:B,2,0) -> SUPREMA LOCADORA E TURISMO LTDA EPP | D155: ISABELA | E155: 00000608 | F155: 45713 | G155: 2796.16 | H155: =VLOOKUP(E155&B155,'Conf Oracle'!A:F,6,0) -> 45713.679 | J155: =IF(OR(ISBLANK(F155), ISBLANK(H155)), "", IFERROR(NETWORKDAYS(F155, H155), "")) -> 1
A156: 45715 | B156: 24427002000120 | C156: =VLOOKUP(B156,Fornecedores!A:B,2,0) -> SHALOM TAXI SER AG INT PG CO TAX LTDA ME | D156: ISABELA | E156: 00000904 | F156: 45712 | G156: 10195.93 | H156: =VLOOKUP(E156&B156,'Conf Oracle'!A:F,6,0) -> 45715.469 | J156: =IF(OR(ISBLANK(F156), ISBLANK(H156)), "", IFERROR(NETWORKDAYS(F156, H156), "")) -> 4
A157: 45715 | B157: 19540230000171 | C157: =VLOOKUP(B157,Fornecedores!A:B,2,0) -> AFEL ENGENHARIA E SERVICOS LTDA | D157: ISABELA | E157: 00001001 | F157: 45713 | G157: 29990 | H157: =VLOOKUP(E157&B157,'Conf Oracle'!A:F,6,0) -> 45714.341 | J157: =IF(OR(ISBLANK(F157), ISBLANK(H157)), "", IFERROR(NETWORKDAYS(F157, H157), "")) -> 2
... A159: 45715 | B159: 39872381000134 | C159: =VLOOKUP(B159,Fornecedores!A:B,2,0) -> E-XYON LEGAL SOFTWARE LTDA | D159: ISABELA | E159: 00000887 | F159: 45714 | G159: 3761.24 | H159: =VLOOKUP(E159&B159,'Conf Oracle'!A:F,6,0) -> 45714.434 | J159: =IF(OR(ISBLANK(F159), ISBLANK(H159)), "", IFERROR(NETWORKDAYS(F159, H159), "")) -> 1
A160: 45715 | B160: 05437734000407 | C160: =VLOOKUP(B160,Fornecedores!A:B,2,0) -> NTT BRASIL COMERCIO E SERVICOS DE TECNOLOGIA LTDA | D160: JESSY | E160: 00050263 | F160: 45702 | G160: 193476.64 | H160: =VLOOKUP(E160&B160,'Conf Oracle'!A:F,6,0) -> #N/A | I160: Bloqueio | J160: =IF(OR(ISBLANK(F160), ISBLANK(H160)), "", IFERROR(NETWORKDAYS(F160, H160), ""))
A161: 45715 | B161: 35791391000194 | C161: =VLOOKUP(B161,Fornecedores!A:B,2,0) -> QUALITY SOFTWARE SA | D161: JESSY | E161: 00025338 | F161: 45706 | G161: 69771.72 | H161: =VLOOKUP(E161&B161,'Conf Oracle'!A:F,6,0) -> #N/A | I161: OC_0007911 | J161: =IF(OR(ISBLANK(F161), ISBLANK(H161)), "", IFERROR(NETWORKDAYS(F161, H161), ""))
A162: 45715 | B162: 35791391000194 | C162: =VLOOKUP(B162,Fornecedores!A:B,2,0) -> QUALITY SOFTWARE SA | D162: JESSY | E162: 00025337 | F162: 45706 | G162: 907599.6 | H162: =VLOOKUP(E162&B162,'Conf Oracle'!A:F,6,0) -> #N/A | I162: OC_0007907 | J162: =IF(OR(ISBLANK(F162), ISBLANK(H162)), "", IFERROR(NETWORKDAYS(F162, H162), ""))
A163: 45715 | B163: 35791391000194 | C163: =VLOOKUP(B163,Fornecedores!A:B,2,0) -> QUALITY SOFTWARE SA | D163: JESSY | E163: 00025339 | F163: 45706 | G163: 87356.46 | H163: =VLOOKUP(E163&B163,'Conf Oracle'!A:F,6,0) -> #N/A | I163: OC_0007908 | J163: =IF(OR(ISBLANK(F163), ISBLANK(H163)), "", IFERROR(NETWORKDAYS(F163, H163), ""))
A164: 45715 | B164: 35791391000194 | C164: =VLOOKUP(B164,Fornecedores!A:B,2,0) -> QUALITY SOFTWARE SA | D164: JESSY | E164: 00025340 | F164: 45706 | G164: 69771.72 | H164: =VLOOKUP(E164&B164,'Conf Oracle'!A:F,6,0) -> #N/A | I164: OC_0007909 | J164: =IF(OR(ISBLANK(F164), ISBLANK(H164)), "", IFERROR(NETWORKDAYS(F164, H164), ""))
A165: 45715 | B165: 35791391000194 | C165: =VLOOKUP(B165,Fornecedores!A:B,2,0) -> QUALITY SOFTWARE SA | D165: JESSY | E165: 00025390 | F165: 45709 | G165: 15334.3 | H165: =VLOOKUP(E165&B165,'Conf Oracle'!A:F,6,0) -> #N/A | I165: OC_0007948 | J165: =IF(OR(ISBLANK(F165), ISBLANK(H165)), "", IFERROR(NETWORKDAYS(F165, H165), ""))
A166: 45715 | B166: 35791391000194 | C166: =VLOOKUP(B166,Fornecedores!A:B,2,0) -> QUALITY SOFTWARE SA | D166: JESSY | E166: 00025391 | F166: 45709 | G166: 1179.12 | H166: =VLOOKUP(E166&B166,'Conf Oracle'!A:F,6,0) -> #N/A | I166: OC_0007949 | J166: =IF(OR(ISBLANK(F166), ISBLANK(H166)), "", IFERROR(NETWORKDAYS(F166, H166), ""))
A167: 45715 | B167: 35791391000194 | C167: =VLOOKUP(B167,Fornecedores!A:B,2,0) -> QUALITY SOFTWARE SA | D167: JESSY | E167: 00025392 | F167: 45709 | G167: 1480.13 | H167: =VLOOKUP(E167&B167,'Conf Oracle'!A:F,6,0) -> #N/A | I167: OC_0007951 | J167: =IF(OR(ISBLANK(F167), ISBLANK(H167)), "", IFERROR(NETWORKDAYS(F167, H167), ""))
A168: 45715 | B168: 35791391000194 | C168: =VLOOKUP(B168,Fornecedores!A:B,2,0) -> QUALITY SOFTWARE SA | D168: JESSY | E168: 00025393 | F168: 45709 | G168: 1179.12 | H168: =VLOOKUP(E168&B168,'Conf Oracle'!A:F,6,0) -> #N/A | I168: OC_0007947 | J168: =IF(OR(ISBLANK(F168), ISBLANK(H168)), "", IFERROR(NETWORKDAYS(F168, H168), ""))
A169: 45715 | B169: 75092593001304 | C169: =VLOOKUP(B169,Fornecedores!A:B,2,0) -> ORSEGUPS SEGURANCA E VIGILANCIA LTDA | D169: JESSY | E169: 00036182 | F169: 45709 | G169: 63126.97 | H169: =VLOOKUP(E169&B169,'Conf Oracle'!A:F,6,0) -> 45715.359 | J169: =IF(OR(ISBLANK(F169), ISBLANK(H169)), "", IFERROR(NETWORKDAYS(F169, H169), "")) -> 5
A170: 45715 | B170: 75092593001304 | C170: =VLOOKUP(B170,Fornecedores!A:B,2,0) -> ORSEGUPS SEGURANCA E VIGILANCIA LTDA | D170: JESSY | E170: 00036183 | F170: 45709 | G170: 14347.67 | H170: =VLOOKUP(E170&B170,'Conf Oracle'!A:F,6,0) -> 45715.354 | J170: =IF(OR(ISBLANK(F170), ISBLANK(H170)), "", IFERROR(NETWORKDAYS(F170, H170), "")) -> 5
A171: 45715 | B171: 67393181000134 | C171: =VLOOKUP(B171,Fornecedores!A:B,2,0) -> IMAGEM GEOSISTEMAS E COMERCIO LTDA | D171: JESSY | E171: 00012296 | F171: 45709 | G171: 23914.48 | H171: =VLOOKUP(E171&B171,'Conf Oracle'!A:F,6,0) -> 45722.664 | J171: =IF(OR(ISBLANK(F171), ISBLANK(H171)), "", IFERROR(NETWORKDAYS(F171, H171), "")) -> 10
A172: 45715 | B172: 22806294000186 | C172: =VLOOKUP(B172,Fornecedores!A:B,2,0) -> BEYONDSOFT CONSULTING BRASIL LTDA | D172: JESSY | E172: 00001933 | F172: 45709 | G172: 26287 | H172: =VLOOKUP(E172&B172,'Conf Oracle'!A:F,6,0) -> 45714.315 | J172: =IF(OR(ISBLANK(F172), ISBLANK(H172)), "", IFERROR(NETWORKDAYS(F172, H172), "")) -> 4
A173: 45715 | B173: 02298314000148 | C173: =VLOOKUP(B173,Fornecedores!A:B,2,0) -> CELERIT SERVICOS DE INFORMATICA LTDA | D173: JESSY | E173: 00000079 | F173: 45712 | G173: 22970.31 | H173: =VLOOKUP(E173&B173,'Conf Oracle'!A:F,6,0) -> 45723.593 | J173: =IF(OR(ISBLANK(F173), ISBLANK(H173)), "", IFERROR(NETWORKDAYS(F173, H173), "")) -> 10
A174: 45715 | B174: 40548150000159 | C174: =VLOOKUP(B174,Fornecedores!A:B,2,0) -> DUNASTUR LTDA | D174: JESSY | E174: 00000951 | F174: 45713 | G174: 1020 | H174: =VLOOKUP(E174&B174,'Conf Oracle'!A:F,6,0) -> 45715.381 | J174: =IF(OR(ISBLANK(F174), ISBLANK(H174)), "", IFERROR(NETWORKDAYS(F174, H174), "")) -> 3
A175: 45715 | B175: 10817634000195 | C175: =VLOOKUP(B175,Fornecedores!A:B,2,0) -> THAG MIX DISTRIBUIDORA DE EMBALAGENS LTDA. | D175: JESSY | E175: 00093976 | F175: 45714 | G175: 3600 | H175: =VLOOKUP(E175&B175,'Conf Oracle'!A:F,6,0) -> 45722.464 | J175: =IF(OR(ISBLANK(F175), ISBLANK(H175)), "", IFERROR(NETWORKDAYS(F175, H175), "")) -> 7
A176: 45715 | B176: 11663706000150 | C176: =VLOOKUP(B176,Fornecedores!A:B,2,0) -> REVIGORAR CLINICA DE FISIOTERAPIA LTDA | D176: JESSY | E176: 00000674 | F176: 45714 | G176: 38803.87 | H176: =VLOOKUP(E176&B176,'Conf Oracle'!A:F,6,0) -> #N/A | I176: Substituída pela NF 675, a NF 674 Foi cancelada. | J176: =IF(OR(ISBLANK(F176), ISBLANK(H176)), "", IFERROR(NETWORKDAYS(F176, H176), ""))
A177: 45715 | B177: 10835932000108 | C177: =VLOOKUP(B177,Fornecedores!A:B,2,0) -> COMPANHIA ENERGETICA DE PERNANBUCO | D177: EVANDREA | E177: 47144253 | F177: 45705 | G177: 38227.11 | H177: =VLOOKUP(E177&B177,'Conf Oracle'!A:F,6,0) -> 45706.436 | J177: =IF(OR(ISBLANK(F177), ISBLANK(H177)), "", IFERROR(NETWORKDAYS(F177, H177), "")) -> 2
A178: 45715 | B178: 15667402000111 | C178: =VLOOKUP(B178,Fornecedores!A:B,2,0) -> SIMPLE ENERGY ASSESSORIA E GESTAO DE ENERGIA LTDA. | D178: EVANDREA | E178: 00019975 | F178: 45706 | G178: 733.38 | H178: =VLOOKUP(E178&B178,'Conf Oracle'!A:F,6,0) -> 45722.39 | J178: =IF(OR(ISBLANK(F178), ISBLANK(H178)), "", IFERROR(NETWORKDAYS(F178, H178), "")) -> 13
...

Sheet Controle de NF - Junho
A2: Mês | B2: CNPJ | C2: Fornecedor | D2: Gestor Adm | E2: NF | F2: Emissão da NF | G2: Valor da NF | H2: Conferência | I2: Observação | J2: SLA
A3: 45810 | B3: 03368287000103 | C3: =VLOOKUP(B3,Fornecedores!A:B,2,0) -> CTY INFORMATICA LTDA ME | D3: Ingrid | E3: 00012228 | F3: 45809 | G3: 14366.6 | H3: =VLOOKUP(E3&B3,'Conf Oracle'!A:F,6,0) -> 45820.576 | J3: =IF(OR(ISBLANK(F3), ISBLANK(H3)), "", IFERROR(NETWORKDAYS(F3, H3), "")) -> 9
A4: 45810 | B4: 58652678000139 | C4: =VLOOKUP(B4,Fornecedores!A:B,2,0) -> COLUMBIA STORAGE INTEGR DE SITEMAS LTDA | D4: Ingrid | E4: 00011156 | F4: 45810 | G4: 17116.41 | H4: =VLOOKUP(E4&B4,'Conf Oracle'!A:F,6,0) -> 45819.69 | J4: =IF(OR(ISBLANK(F4), ISBLANK(H4)), "", IFERROR(NETWORKDAYS(F4, H4), "")) -> 8
A5: 45810 | B5: 23412247000110 | C5: =VLOOKUP(B5,Fornecedores!A:B,2,0) -> AMAZON AWS SERVICOS BRASIL LTDA | D5: Ingrid | E5: 04406862 | F5: 45809 | G5: 63034.39 | H5: =VLOOKUP(E5&B5,'Conf Oracle'!A:F,6,0) -> 45833.708 | I5: OC_0009834 | J5: =IF(OR(ISBLANK(F5), ISBLANK(H5)), "", IFERROR(NETWORKDAYS(F5, H5), "")) -> 18
A6: 45810 | B6: 23412247000110 | C6: =VLOOKUP(B6,Fornecedores!A:B,2,0) -> AMAZON AWS SERVICOS BRASIL LTDA | D6: Ingrid | E6: 04406853 | F6: 45809 | G6: 71814.74 | H6: =VLOOKUP(E6&B6,'Conf Oracle'!A:F,6,0) -> #N/A | I6: OC_0009835 | J6: =IF(OR(ISBLANK(F6), ISBLANK(H6)), "", IFERROR(NETWORKDAYS(F6, H6), ""))
A7: 45810 | B7: 23412247000110 | C7: =VLOOKUP(B7,Fornecedores!A:B,2,0) -> AMAZON AWS SERVICOS BRASIL LTDA | D7: Ingrid | E7: 04403745 | F7: 45809 | G7: 617836.05 | H7: =VLOOKUP(E7&B7,'Conf Oracle'!A:F,6,0) -> 45833.713 | J7: =IF(OR(ISBLANK(F7), ISBLANK(H7)), "", IFERROR(NETWORKDAYS(F7, H7), "")) -> 18
A8: 45810 | B8: 07751071000175 | C8: =VLOOKUP(B8,Fornecedores!A:B,2,0) -> TELEGESTAO SISTEMAS DE ATEND LTDA | D8: Isabela | E8: 00001155 | F8: 45809 | G8: 700 | H8: =VLOOKUP(E8&B8,'Conf Oracle'!A:F,6,0) -> 45814.456 | J8: =IF(OR(ISBLANK(F8), ISBLANK(H8)), "", IFERROR(NETWORKDAYS(F8, H8), "")) -> 5
A9: 45810 | B9: 72157654000215 | C9: =VLOOKUP(B9,Fornecedores!A:B,2,0) -> VELA SOFTWARE E SERVICOS LTDA | D9: Isabela | E9: 20259372R | F9: 45810 | G9: 677.6 | H9: =VLOOKUP(E9&B9,'Conf Oracle'!A:F,6,0) -> 45819.645 | I9: Lançada | J9: =IF(OR(ISBLANK(F9), ISBLANK(H9)), "", IFERROR(NETWORKDAYS(F9, H9), "")) -> 8
A10: 45810 | B10: 72157654000215 | C10: =VLOOKUP(B10,Fornecedores!A:B,2,0) -> VELA SOFTWARE E SERVICOS LTDA | D10: Isabela | E10: 2029378R | F10: 45810 | G10: 677.6 | H10: =VLOOKUP(E10&B10,'Conf Oracle'!A:F,6,0) -> 45821.419 | I10: Lançada | J10: =IF(OR(ISBLANK(F10), ISBLANK(H10)), "", IFERROR(NETWORKDAYS(F10, H10), "")) -> 10
A11: 45810 | B11: 26409092000151 | C11: =VLOOKUP(B11,Fornecedores!A:B,2,0) -> SSAMRO SOLUCOES PARA MANUTENCAO INDUSTR | D11: Isabela | E11: 00025115 | F11: 45810 | G11: 648.76 | H11: =VLOOKUP(E11&B11,'Conf Oracle'!A:F,6,0) -> 45814.444 | J11: =IF(OR(ISBLANK(F11), ISBLANK(H11)), "", IFERROR(NETWORKDAYS(F11, H11), "")) -> 5
A12: 45810 | B12: 26409092000151 | C12: =VLOOKUP(B12,Fornecedores!A:B,2,0) -> SSAMRO SOLUCOES PARA MANUTENCAO INDUSTR | D12: Isabela | E12: 00025125 | F12: 45810 | G12: 648.76 | H12: =VLOOKUP(E12&B12,'Conf Oracle'!A:F,6,0) -> 45814.438 | J12: =IF(OR(ISBLANK(F12), ISBLANK(H12)), "", IFERROR(NETWORKDAYS(F12, H12), "")) -> 5
A13: 45810 | B13: 26409092000151 | C13: =VLOOKUP(B13,Fornecedores!A:B,2,0) -> SSAMRO SOLUCOES PARA MANUTENCAO INDUSTR | D13: Isabela | E13: 00025131 | F13: 45810 | G13: 648.76 | H13: =VLOOKUP(E13&B13,'Conf Oracle'!A:F,6,0) -> 45814.435 | J13: =IF(OR(ISBLANK(F13), ISBLANK(H13)), "", IFERROR(NETWORKDAYS(F13, H13), "")) -> 5
A14: 45810 | B14: 26409092000151 | C14: =VLOOKUP(B14,Fornecedores!A:B,2,0) -> SSAMRO SOLUCOES PARA MANUTENCAO INDUSTR | D14: Isabela | E14: 00025133 | F14: 45810 | G14: 648.76 | H14: =VLOOKUP(E14&B14,'Conf Oracle'!A:F,6,0) -> 45814.437 | J14: =IF(OR(ISBLANK(F14), ISBLANK(H14)), "", IFERROR(NETWORKDAYS(F14, H14), "")) -> 5
A15: 45813 | B15: 00191027000109 | C15: =VLOOKUP(B15,Fornecedores!A:B,2,0) -> FACILIT TECNOLOGIA LTDA EPP | D15: Sunara | E15: 00003719 | F15: 45810 | G15: 13496 | H15: =VLOOKUP(E15&B15,'Conf Oracle'!A:F,6,0) -> 45820.598 | J15: =IF(OR(ISBLANK(F15), ISBLANK(H15)), "", IFERROR(NETWORKDAYS(F15, H15), "")) -> 9
A16: 45810 | B16: 81785545000152 | C16: =VLOOKUP(B16,Fornecedores!A:B,2,0) -> DEL GRANDE INFO E TELEC IND E COM LTDA | D16: Pedro | E16: 00004150 | F16: 45810 | G16: 5077 | H16: =VLOOKUP(E16&B16,'Conf Oracle'!A:F,6,0) -> 45826.649 | J16: =IF(OR(ISBLANK(F16), ISBLANK(H16)), "", IFERROR(NETWORKDAYS(F16, H16), "")) -> 13
A17: 45810 | B17: 81785545000152 | C17: =VLOOKUP(B17,Fornecedores!A:B,2,0) -> DEL GRANDE INFO E TELEC IND E COM LTDA | D17: Pedro | E17: 00004151 | F17: 45810 | G17: 1618.7 | H17: =VLOOKUP(E17&B17,'Conf Oracle'!A:F,6,0) -> 45826.655 | J17: =IF(OR(ISBLANK(F17), ISBLANK(H17)), "", IFERROR(NETWORKDAYS(F17, H17), "")) -> 13
A18: 45810 | B18: 81785545000152 | C18: =VLOOKUP(B18,Fornecedores!A:B,2,0) -> DEL GRANDE INFO E TELEC IND E COM LTDA | D18: Pedro | E18: 00004153 | F18: 45810 | G18: 2825.73 | H18: =VLOOKUP(E18&B18,'Conf Oracle'!A:F,6,0) -> 45826.651 | J18: =IF(OR(ISBLANK(F18), ISBLANK(H18)), "", IFERROR(NETWORKDAYS(F18, H18), "")) -> 13
A19: 45810 | B19: 81785545000152 | C19: =VLOOKUP(B19,Fornecedores!A:B,2,0) -> DEL GRANDE INFO E TELEC IND E COM LTDA | D19: Pedro | E19: 00004152 | F19: 45810 | G19: 3151.24 | H19: =VLOOKUP(E19&B19,'Conf Oracle'!A:F,6,0) -> 45826.653 | J19: =IF(OR(ISBLANK(F19), ISBLANK(H19)), "", IFERROR(NETWORKDAYS(F19, H19), "")) -> 13
A20: 45813 | B20: 16554325000156 | C20: =VLOOKUP(B20,Fornecedores!A:B,2,0) -> AMBIENTE VERDE RESIDUOS LTDA | D20: Evandrea | E20: 00001035 | F20: 45810 | G20: 2690 | H20: =VLOOKUP(E20&B20,'Conf Oracle'!A:F,6,0) -> 45817.44 | J20: =IF(OR(ISBLANK(F20), ISBLANK(H20)), "", IFERROR(NETWORKDAYS(F20, H20), "")) -> 6
A21: 45813 | B21: 16554325000156 | C21: =VLOOKUP(B21,Fornecedores!A:B,2,0) -> AMBIENTE VERDE RESIDUOS LTDA | D21: Evandrea | E21: 00001034 | F21: 45810 | G21: 2690 | H21: =VLOOKUP(E21&B21,'Conf Oracle'!A:F,6,0) -> 45817.425 | J21: =IF(OR(ISBLANK(F21), ISBLANK(H21)), "", IFERROR(NETWORKDAYS(F21, H21), "")) -> 6
A22: 45813 | B22: 57623555000107 | C22: =VLOOKUP(B22,Fornecedores!A:B,2,0) -> MAGICCOMP ENG E SERV DE INFORMATICA LTDA | D22: Jessy | E22: 00055719 | F22: 45810 | G22: 27750 | H22: =VLOOKUP(E22&B22,'Conf Oracle'!A:F,6,0) -> 45824.604 | I22: Ok | J22: =IF(OR(ISBLANK(F22), ISBLANK(H22)), "", IFERROR(NETWORKDAYS(F22, H22), "")) -> 11
A23: 45813 | B23: 57623555000107 | C23: =VLOOKUP(B23,Fornecedores!A:B,2,0) -> MAGICCOMP ENG E SERV DE INFORMATICA LTDA | D23: Jessy | E23: 00055718 | F23: 45810 | G23: 27750 | H23: =VLOOKUP(E23&B23,'Conf Oracle'!A:F,6,0) -> 45824.596 | I23: Ok | J23: =IF(OR(ISBLANK(F23), ISBLANK(H23)), "", IFERROR(NETWORKDAYS(F23, H23), "")) -> 11
A24: 45813 | B24: 57623555000107 | C24: =VLOOKUP(B24,Fornecedores!A:B,2,0) -> MAGICCOMP ENG E SERV DE INFORMATICA LTDA | D24: Jessy | E24: 00055717 | F24: 45810 | G24: 27750 | H24: =VLOOKUP(E24&B24,'Conf Oracle'!A:F,6,0) -> 45824.59 | I24: Ok | J24: =IF(OR(ISBLANK(F24), ISBLANK(H24)), "", IFERROR(NETWORKDAYS(F24, H24), "")) -> 11
A25: 45813 | B25: 57623555000107 | C25: =VLOOKUP(B25,Fornecedores!A:B,2,0) -> MAGICCOMP ENG E SERV DE INFORMATICA LTDA | D25: Jessy | E25: 00055720 | F25: 45810 | G25: 27750 | H25: =VLOOKUP(E25&B25,'Conf Oracle'!A:F,6,0) -> 45824.708 | I25: Ok | J25: =IF(OR(ISBLANK(F25), ISBLANK(H25)), "", IFERROR(NETWORKDAYS(F25, H25), "")) -> 11
A26: 45813 | B26: 08689542000125 | C26: =VLOOKUP(B26,Fornecedores!A:B,2,0) -> VOCS MULTIMIDIA PROD AUDIO VID LTDA EPP | D26: Jessy | E26: 00003404 | F26: 45810 | G26: 6286.2 | H26: =VLOOKUP(E26&B26,'Conf Oracle'!A:F,6,0) -> 45839.39 | I26: OC_0010021 | J26: =IF(OR(ISBLANK(F26), ISBLANK(H26)), "", IFERROR(NETWORKDAYS(F26, H26), "")) -> 22
A27: 45813 | B27: 08689542000125 | C27: =VLOOKUP(B27,Fornecedores!A:B,2,0) -> VOCS MULTIMIDIA PROD AUDIO VID LTDA EPP | D27: Jessy | E27: 00003403 | F27: 45810 | G27: 21000 | H27: =VLOOKUP(E27&B27,'Conf Oracle'!A:F,6,0) -> 45818.618 | I27: OC_0009644 | J27: =IF(OR(ISBLANK(F27), ISBLANK(H27)), "", IFERROR(NETWORKDAYS(F27, H27), "")) -> 7
A28: 45813 | B28: 01933257000169 | C28: =VLOOKUP(B28,Fornecedores!A:B,2,0) -> FUTURE TECHNOLOGIES INFORMATICA LTDA | D28: Jessy | E28: 00004511 | F28: 45810 | G28: 6450 | H28: =VLOOKUP(E28&B28,'Conf Oracle'!A:F,6,0) -> 45818.606 | I28: lançada - OC_0009643 | J28: =IF(OR(ISBLANK(F28), ISBLANK(H28)), "", IFERROR(NETWORKDAYS(F28, H28), "")) -> 7
A29: 45813 | B29: 15667402000111 | C29: =VLOOKUP(B29,Fornecedores!A:B,2,0) -> SIMPLE ENERGY ASSESSORIA E GESTAO DE ENERGIA LTDA. | D29: Evandrea | E29: 00021347 | F29: 45810 | G29: 733.38 | H29: =VLOOKUP(E29&B29,'Conf Oracle'!A:F,6,0) -> 45818.415 | J29: =IF(OR(ISBLANK(F29), ISBLANK(H29)), "", IFERROR(NETWORKDAYS(F29, H29), "")) -> 7
A30: 45813 | B30: 15667402000111 | C30: =VLOOKUP(B30,Fornecedores!A:B,2,0) -> SIMPLE ENERGY ASSESSORIA E GESTAO DE ENERGIA LTDA. | D30: Evandrea | E30: 00021352 | F30: 45810 | G30: 733.38 | H30: =VLOOKUP(E30&B30,'Conf Oracle'!A:F,6,0) -> 45817.478 | J30: =IF(OR(ISBLANK(F30), ISBLANK(H30)), "", IFERROR(NETWORKDAYS(F30, H30), "")) -> 6
A31: 45813 | B31: 15667402000111 | C31: =VLOOKUP(B31,Fornecedores!A:B,2,0) -> SIMPLE ENERGY ASSESSORIA E GESTAO DE ENERGIA LTDA. | D31: Evandrea | E31: 00021349 | F31: 45810 | G31: 733.38 | H31: =VLOOKUP(E31&B31,'Conf Oracle'!A:F,6,0) -> 45818.385 | J31: =IF(OR(ISBLANK(F31), ISBLANK(H31)), "", IFERROR(NETWORKDAYS(F31, H31), "")) -> 7
A32: 45813 | B32: 15667402000111 | C32: =VLOOKUP(B32,Fornecedores!A:B,2,0) -> SIMPLE ENERGY ASSESSORIA E GESTAO DE ENERGIA LTDA. | D32: Evandrea | E32: 00021345 | F32: 45810 | G32: 733.38 | H32: =VLOOKUP(E32&B32,'Conf Oracle'!A:F,6,0) -> 45817.469 | J32: =IF(OR(ISBLANK(F32), ISBLANK(H32)), "", IFERROR(NETWORKDAYS(F32, H32), "")) -> 6
A33: 45813 | B33: 00001180000126 | C33: =VLOOKUP(B33,Fornecedores!A:B,2,0) -> Centrais Elétricas Brasileiras S/A - Eletrobras | D33: Evandrea | E33: 00046995 | F33: 45811 | G33: 20868.07 | H33: =VLOOKUP(E33&B33,'Conf Oracle'!A:F,6,0) -> 45817.454 | J33: =IF(OR(ISBLANK(F33), ISBLANK(H33)), "", IFERROR(NETWORKDAYS(F33, H33), "")) -> 5
A34: 45813 | B34: 00001180000126 | C34: =VLOOKUP(B34,Fornecedores!A:B,2,0) -> Centrais Elétricas Brasileiras S/A - Eletrobras | D34: Evandrea | E34: 00046994 | F34: 45811 | G34: 39255.84 | H34: =VLOOKUP(E34&B34,'Conf Oracle'!A:F,6,0) -> 45817.457 | J34: =IF(OR(ISBLANK(F34), ISBLANK(H34)), "", IFERROR(NETWORKDAYS(F34, H34), "")) -> 5
A35: 45813 | B35: 00001180000126 | C35: =VLOOKUP(B35,Fornecedores!A:B,2,0) -> Centrais Elétricas Brasileiras S/A - Eletrobras | D35: Evandrea | E35: 00046993 | F35: 45811 | G35: 87307.77 | H35: =VLOOKUP(E35&B35,'Conf Oracle'!A:F,6,0) -> 45817.471 | J35: =IF(OR(ISBLANK(F35), ISBLANK(H35)), "", IFERROR(NETWORKDAYS(F35, H35), "")) -> 5
A36: 45813 | B36: 00001180000126 | C36: =VLOOKUP(B36,Fornecedores!A:B,2,0) -> Centrais Elétricas Brasileiras S/A - Eletrobras | D36: Evandrea | E36: 00046992 | F36: 45811 | G36: 59812.8 | H36: =VLOOKUP(E36&B36,'Conf Oracle'!A:F,6,0) -> 45817.447 | J36: =IF(OR(ISBLANK(F36), ISBLANK(H36)), "", IFERROR(NETWORKDAYS(F36, H36), "")) -> 5
A37: 45810 | B37: 01609514000101 | C37: =VLOOKUP(B37,Fornecedores!A:B,2,0) -> E-HUNTER TECNOLOGIA DA INFORMAÇÃO LTDA | D37: Sunara | E37: 00005473 | F37: 45810 | G37: 2614 | H37: =VLOOKUP(E37&B37,'Conf Oracle'!A:F,6,0) -> 45824.713 | J37: =IF(OR(ISBLANK(F37), ISBLANK(H37)), "", IFERROR(NETWORKDAYS(F37, H37), "")) -> 11
A38: 45813 | B38: 09162855000517 | C38: =VLOOKUP(B38,Fornecedores!A:B,2,0) -> PTLS SERV TECNOLOGIA E ASSESS TECN LTDA | D38: Sunara | E38: 00217323 | F38: 45810 | G38: 30803.59 | H38: =VLOOKUP(E38&B38,'Conf Oracle'!A:F,6,0) -> 45825.377 | J38: =IF(OR(ISBLANK(F38), ISBLANK(H38)), "", IFERROR(NETWORKDAYS(F38, H38), "")) -> 12
A39: 45813 | B39: 09162855000517 | C39: =VLOOKUP(B39,Fornecedores!A:B,2,0) -> PTLS SERV TECNOLOGIA E ASSESS TECN LTDA | D39: Sunara | E39: 00217322 | F39: 45810 | G39: 6363.07 | H39: =VLOOKUP(E39&B39,'Conf Oracle'!A:F,6,0) -> 45824.73 | J39: =IF(OR(ISBLANK(F39), ISBLANK(H39)), "", IFERROR(NETWORKDAYS(F39, H39), "")) -> 11
A40: 45814 | B40: 40432544010290 | C40: =VLOOKUP(B40,Fornecedores!A:B,2,0) -> CLARO SA | D40: Evandrea | E40: 55993182 | F40: 45812 | G40: 2205.53 | H40: 45831 | I40: lançada dia 23/06 | J40: =IF(OR(ISBLANK(F40), ISBLANK(H40)), "", IFERROR(NETWORKDAYS(F40, H40), "")) -> 14
A41: 45814 | B41: 40432544044004 | C41: =VLOOKUP(B41,Fornecedores!A:B,2,0) -> CLARO SA | D41: Evandrea | E41: 31199182 | F41: 45812 | G41: 3370.45 | H41: 45831 | I41: lançada dia 23/06 | J41: =IF(OR(ISBLANK(F41), ISBLANK(H41)), "", IFERROR(NETWORKDAYS(F41, H41), "")) -> 14
A42: 45814 | B42: 40432544006269 | C42: =VLOOKUP(B42,Fornecedores!A:B,2,0) -> CLARO SA | D42: Evandrea | E42: 91614200 | F42: 45812 | G42: 1844.78 | H42: 45831 | I42: lançada dia 23/06 | J42: =IF(OR(ISBLANK(F42), ISBLANK(H42)), "", IFERROR(NETWORKDAYS(F42, H42), "")) -> 14
A43: 45814 | B43: 40432544019166 | C43: =VLOOKUP(B43,Fornecedores!A:B,2,0) -> CLARO SA | D43: Evandrea | E43: 05393224 | F43: 45812 | G43: 2599.51 | H43: 45831 | I43: lançada dia 23/06 | J43: =IF(OR(ISBLANK(F43), ISBLANK(H43)), "", IFERROR(NETWORKDAYS(F43, H43), "")) -> 14
A44: 45814 | B44: 40432544006269 | C44: =VLOOKUP(B44,Fornecedores!A:B,2,0) -> CLARO SA | D44: Evandrea | E44: 83906246 | F44: 45812 | G44: 18341.66 | H44: 45831 | I44: lançada dia 23/06 | J44: =IF(OR(ISBLANK(F44), ISBLANK(H44)), "", IFERROR(NETWORKDAYS(F44, H44), "")) -> 14
A45: 45814 | B45: 16554325000156 | C45: =VLOOKUP(B45,Fornecedores!A:B,2,0) -> AMBIENTE VERDE RESIDUOS LTDA | D45: Evandrea | E45: 00001056 | F45: 45812 | G45: 7844.35 | H45: =VLOOKUP(E45&B45,'Conf Oracle'!A:F,6,0) -> 45817.431 | J45: =IF(OR(ISBLANK(F45), ISBLANK(H45)), "", IFERROR(NETWORKDAYS(F45, H45), "")) -> 4
A46: 45814 | B46: 00028986001694 | C46: =VLOOKUP(B46,Fornecedores!A:B,2,0) -> ELEVADORES ATLAS SCHINDLER SA | D46: Evandrea | E46: 00470678 | F46: 45812 | G46: 1960.94 | H46: =VLOOKUP(E46&B46,'Conf Oracle'!A:F,6,0) -> 45817.724 | J46: =IF(OR(ISBLANK(F46), ISBLANK(H46)), "", IFERROR(NETWORKDAYS(F46, H46), "")) -> 4
A47: 45814 | B47: 16554325000156 | C47: =VLOOKUP(B47,Fornecedores!A:B,2,0) -> AMBIENTE VERDE RESIDUOS LTDA | D47: Evandrea | E47: 00001036 | F47: 45810 | G47: 2490 | H47: =VLOOKUP(E47&B47,'Conf Oracle'!A:F,6,0) -> 45817.436 | J47: =IF(OR(ISBLANK(F47), ISBLANK(H47)), "", IFERROR(NETWORKDAYS(F47, H47), "")) -> 6
A48: 45817 | B48: 08270682000164 | C48: =VLOOKUP(B48,Fornecedores!A:B,2,0) -> CONFIDERE IMOBILIARIA LTDA | D48: Evandrea | E48: 00202506 | F48: 45809 | G48: 2970031.4 | H48: =VLOOKUP(E48&B48,'Conf Oracle'!A:F,6,0) -> 45817.688 | I48: Lançada com o nome Confidere | J48: =IF(OR(ISBLANK(F48), ISBLANK(H48)), "", IFERROR(NETWORKDAYS(F48, H48), "")) -> 6
A49: 45817 | B49: 42356782000146 | C49: =VLOOKUP(B49,Fornecedores!A:B,2,0) -> EBSCO BRASIL LTDA | D49: Guilherme | E49: 00007829 | F49: 45810 | G49: 30731.4 | H49: =VLOOKUP(E49&B49,'Conf Oracle'!A:F,6,0) -> 45821.468 | J49: =IF(OR(ISBLANK(F49), ISBLANK(H49)), "", IFERROR(NETWORKDAYS(F49, H49), "")) -> 10
A50: 45817 | B50: 72381189000110 | C50: =VLOOKUP(B50,Fornecedores!A:B,2,0) -> DELL COMPUTADORES DO BRASIL LTDA | D50: Guilherme | E50: 02754153 | F50: 45813 | G50: 72117.53 | H50: 45834 | I50: REPROVADA PELO GT EM 26/06/2025 | J50: =IF(OR(ISBLANK(F50), ISBLANK(H50)), "", IFERROR(NETWORKDAYS(F50, H50), "")) -> 16
A51: 45817 | B51: 37103032000122 | C51: =VLOOKUP(B51,Fornecedores!A:B,2,0) -> DHAR COMERCIO E SERVICOS LTDA | D51: Guilherme | E51: 00004123 | F51: 45813 | G51: 1510.4 | H51: =VLOOKUP(E51&B51,'Conf Oracle'!A:F,6,0) -> 45834.722 | I51: LANÇADA | J51: =IF(OR(ISBLANK(F51), ISBLANK(H51)), "", IFERROR(NETWORKDAYS(F51, H51), "")) -> 16
A52: 45817 | B52: 72381189001354 | C52: =VLOOKUP(B52,Fornecedores!A:B,2,0) -> DELL COMPUTADORES DO BRASIL LTDA | D52: Guilherme | E52: 00016899 | F52: 45813 | G52: 122256.13 | H52: 45841 | I52: ERRO NA EMISSÃO DA NF 03/07/2025 | J52: =IF(OR(ISBLANK(F52), ISBLANK(H52)), "", IFERROR(NETWORKDAYS(F52, H52), "")) -> 21
A53: 45817 | B53: 72381189000110 | C53: =VLOOKUP(B53,Fornecedores!A:B,2,0) -> DELL COMPUTADORES DO BRASIL LTDA | D53: Guilherme | E53: 00016900 | F53: 45813 | G53: 132631.41 | H53: =VLOOKUP(E53&B53,'Conf Oracle'!A:F,6,0) -> 45838.597 | I53: LANÇADA | J53: =IF(OR(ISBLANK(F53), ISBLANK(H53)), "", IFERROR(NETWORKDAYS(F53, H53), "")) -> 18
A54: 45817 | B54: 29946276000149 | C54: =VLOOKUP(B54,Fornecedores!A:B,2,0) -> MANGE BUFFET LTDA | D54: Guilherme | E54: 00000205 | F54: 45814 | G54: 19800 | H54: =VLOOKUP(E54&B54,'Conf Oracle'!A:F,6,0) -> 45821.66 | I54: LANÇADA | J54: =IF(OR(ISBLANK(F54), ISBLANK(H54)), "", IFERROR(NETWORKDAYS(F54, H54), "")) -> 6
A55: 45817 | B55: 21515602000151 | C55: =VLOOKUP(B55,Fornecedores!A:B,2,0) -> CENARIO RJ TECNOLOGIA EM AUDIO E VIDEO LTDA | D55: Guilherme | E55: 00001240 | F55: 45814 | G55: 5000 | H55: =VLOOKUP(E55&B55,'Conf Oracle'!A:F,6,0) -> 45819.706 | I55: LANÇADA | J55: =IF(OR(ISBLANK(F55), ISBLANK(H55)), "", IFERROR(NETWORKDAYS(F55, H55), "")) -> 4
A56: 45817 | B56: 10350191000175 | C56: =VLOOKUP(B56,Fornecedores!A:B,2,0) -> AFIXCODE SOLUCOES GRAFICAS LTDA EPP | D56: Guilherme | E56: 00031350 | F56: 45812 | G56: 800 | H56: =VLOOKUP(E56&B56,'Conf Oracle'!A:F,6,0) -> 45826.395 | I56: LANÇADA | J56: =IF(OR(ISBLANK(F56), ISBLANK(H56)), "", IFERROR(NETWORKDAYS(F56, H56), "")) -> 11
A57: 45817 | B57: 21515602000151 | C57: =VLOOKUP(B57,Fornecedores!A:B,2,0) -> CENARIO RJ TECNOLOGIA EM AUDIO E VIDEO LTDA | D57: Guilherme | E57: 00001243 | F57: 45814 | G57: 1720 | H57: =VLOOKUP(E57&B57,'Conf Oracle'!A:F,6,0) -> 45826.398 | I57: LANÇADA | J57: =IF(OR(ISBLANK(F57), ISBLANK(H57)), "", IFERROR(NETWORKDAYS(F57, H57), "")) -> 9
A58: 45817 | B58: 21515602000151 | C58: =VLOOKUP(B58,Fornecedores!A:B,2,0) -> CENARIO RJ TECNOLOGIA EM AUDIO E VIDEO LTDA | D58: Guilherme | E58: 00001242 | F58: 45814 | G58: 940 | H58: =VLOOKUP(E58&B58,'Conf Oracle'!A:F,6,0) -> 45826.433 | I58: LANÇADA | J58: =IF(OR(ISBLANK(F58), ISBLANK(H58)), "", IFERROR(NETWORKDAYS(F58, H58), "")) -> 9
A59: 45817 | B59: 07850212000107 | C59: =VLOOKUP(B59,Fornecedores!A:B,2,0) -> REAL SEGURANCA INTEGRADA EIRELI | D59: Ingrid | E59: 00001252 | F59: 45812 | G59: 217.9 | H59: =VLOOKUP(E59&B59,'Conf Oracle'!A:F,6,0) -> 45819.651 | J59: =IF(OR(ISBLANK(F59), ISBLANK(H59)), "", IFERROR(NETWORKDAYS(F59, H59), "")) -> 6
A60: 45817 | B60: GRID PROTECTION | C60: =VLOOKUP(B60,Fornecedores!A:B,2,0) -> GRID PROTECTION ALLIANCE | D60: Ingrid | E60: 008 | F60: 45813 | G60: 60000 | H60: =VLOOKUP(E60&B60,'Conf Oracle'!A:F,6,0) -> 45826.437 | I60: OC_0009748 | J60: =IF(OR(ISBLANK(F60), ISBLANK(H60)), "", IFERROR(NETWORKDAYS(F60, H60), "")) -> 10
A61: 45817 | B61: 72157654000215 | C61: =VLOOKUP(B61,Fornecedores!A:B,2,0) -> VELA SOFTWARE E SERVICOS LTDA | D61: Isabela | E61: 20259531 | F61: 45811 | G61: 677.6 | H61: =VLOOKUP(E61&B61,'Conf Oracle'!A:F,6,0) -> 45819.626 | I61: Lançada | J61: =IF(OR(ISBLANK(F61), ISBLANK(H61)), "", IFERROR(NETWORKDAYS(F61, H61), "")) -> 7
A62: 45817 | B62: 72157654000215 | C62: =VLOOKUP(B62,Fornecedores!A:B,2,0) -> VELA SOFTWARE E SERVICOS LTDA | D62: Isabela | E62: 20259536 | F62: 45811 | G62: 677.6 | H62: =VLOOKUP(E62&B62,'Conf Oracle'!A:F,6,0) -> 45819.477 | I62: Lançada | J62: =IF(OR(ISBLANK(F62), ISBLANK(H62)), "", IFERROR(NETWORKDAYS(F62, H62), "")) -> 7
A63: 45817 | B63: 15491115000101 | C63: =VLOOKUP(B63,Fornecedores!A:B,2,0) -> CS INTEGRA SOLUCOES EM TECNOLOG LTDA ME | D63: Isabela | E63: 00006353 | F63: 45811 | G63: 3093 | H63: =VLOOKUP(E63&B63,'Conf Oracle'!A:F,6,0) -> 45814.446 | J63: =IF(OR(ISBLANK(F63), ISBLANK(H63)), "", IFERROR(NETWORKDAYS(F63, H63), "")) -> 4
A64: 45817 | B64: 04359325000116 | C64: =VLOOKUP(B64,Fornecedores!A:B,2,0) -> MORAES PITOMBO ADVOGADOS | D64: Isabela | E64: 00020606 | F64: 45811 | G64: 7500 | H64: =VLOOKUP(E64&B64,'Conf Oracle'!A:F,6,0) -> 45818.586 | I64: OC_0009638 | J64: =IF(OR(ISBLANK(F64), ISBLANK(H64)), "", IFERROR(NETWORKDAYS(F64, H64), "")) -> 6
A65: 45817 | B65: 19427033000140 | C65: =VLOOKUP(B65,Fornecedores!A:B,2,0) -> ARQUIVEI SERVICOS ON LINE LTDA | D65: Isabela | E65: 00482213 | F65: 45812 | G65: 2720 | H65: cancelada | I65: é a Qive que veio com o valor errado | J65: =IF(OR(ISBLANK(F65), ISBLANK(H65)), "", IFERROR(NETWORKDAYS(F65, H65), ""))
A66: 45817 | B66: 01708167000174 | C66: =VLOOKUP(B66,Fornecedores!A:B,2,0) -> KPMG CONSULTORIA LTDA | D66: Jessy | E66: 00004010 | F66: 45810 | G66: 40474.69 | H66: =VLOOKUP(E66&B66,'Conf Oracle'!A:F,6,0) -> 45825.327 | I66: ok | J66: =IF(OR(ISBLANK(F66), ISBLANK(H66)), "", IFERROR(NETWORKDAYS(F66, H66), "")) -> 12
A67: 45817 | B67: 25012398000107 | C67: =VLOOKUP(B67,Fornecedores!A:B,2,0) -> GOOGLE CLOUD BRASIL COMPUTAÇÃO E SERVICOS DE DADOS LTDA | D67: Jessy | E67: 13390242 | F67: 45810 | G67: 1271.73 | H67: =VLOOKUP(E67&B67,'Conf Oracle'!A:F,6,0) -> 45826.501 | I67: ok | J67: =IF(OR(ISBLANK(F67), ISBLANK(H67)), "", IFERROR(NETWORKDAYS(F67, H67), "")) -> 13
A68: 45817 | B68: 43965130000171 | C68: =VLOOKUP(B68,Fornecedores!A:B,2,0) -> AGUAS CLARAS GASTRONOMIA E EVENTOS LTDA | D68: Pedro | E68: 00001135 | F68: 45810 | G68: 3395 | H68: =VLOOKUP(E68&B68,'Conf Oracle'!A:F,6,0) -> 45811.665 | J68: =IF(OR(ISBLANK(F68), ISBLANK(H68)), "", IFERROR(NETWORKDAYS(F68, H68), "")) -> 2
A69: 45817 | B69: 23007579000110 | C69: =VLOOKUP(B69,Fornecedores!A:B,2,0) -> PERINITY - SOLUCOES E SERVICOS EM GOVERNANCA LTDA | D69: Pedro | E69: 00000142 | F69: 45811 | G69: 7230.05 | H69: 45833 | I69: NF CANCELADA | J69: =IF(OR(ISBLANK(F69), ISBLANK(H69)), "", IFERROR(NETWORKDAYS(F69, H69), "")) -> 17
A70: 45817 | B70: 23007579000110 | C70: =VLOOKUP(B70,Fornecedores!A:B,2,0) -> PERINITY - SOLUCOES E SERVICOS EM GOVERNANCA LTDA | D70: Pedro | E70: 00000143 | F70: 45811 | G70: 7230.05 | H70: =VLOOKUP(E70&B70,'Conf Oracle'!A:F,6,0) -> 45824.569 | J70: =IF(OR(ISBLANK(F70), ISBLANK(H70)), "", IFERROR(NETWORKDAYS(F70, H70), "")) -> 10
A71: 45817 | B71: 23007579000110 | C71: =VLOOKUP(B71,Fornecedores!A:B,2,0) -> PERINITY - SOLUCOES E SERVICOS EM GOVERNANCA LTDA | D71: Pedro | E71: 00000144 | F71: 45811 | G71: 7230.05 | H71: =VLOOKUP(E71&B71,'Conf Oracle'!A:F,6,0) -> 45841.484 | I71: ok | J71: =IF(OR(ISBLANK(F71), ISBLANK(H71)), "", IFERROR(NETWORKDAYS(F71, H71), "")) -> 23
A72: 45817 | B72: 82895327000133 | C72: =VLOOKUP(B72,Fornecedores!A:B,2,0) -> FUNDACAO DE ENSINO E ENGENHARIA DE SC | D72: Pedro | E72: 00009217 | F72: 45812 | G72: 53333.33 | H72: =VLOOKUP(E72&B72,'Conf Oracle'!A:F,6,0) -> 45820.691 | J72: =IF(OR(ISBLANK(F72), ISBLANK(H72)), "", IFERROR(NETWORKDAYS(F72, H72), "")) -> 7
A73: 45817 | B73: 30608514000195 | C73: =VLOOKUP(B73,Fornecedores!A:B,2,0) -> AGENCIA FR DE COMUNICACAO LTDA | D73: Pedro | E73: 00004185 | F73: 45815 | G73: 38034.8 | H73: =VLOOKUP(E73&B73,'Conf Oracle'!A:F,6,0) -> 45820.489 | J73: =IF(OR(ISBLANK(F73), ISBLANK(H73)), "", IFERROR(NETWORKDAYS(F73, H73), "")) -> 4
A74: 45817 | B74: 11136174000100 | C74: =VLOOKUP(B74,Fornecedores!A:B,2,0) -> AVVALE BRASIL LTDA | D74: Sunara | E74: 00005066 | F74: 45812 | G74: 8200 | H74: =VLOOKUP(E74&B74,'Conf Oracle'!A:F,6,0) -> 45825.379 | J74: =IF(OR(ISBLANK(F74), ISBLANK(H74)), "", IFERROR(NETWORKDAYS(F74, H74), "")) -> 10
A75: 45817 | B75: 08670505000175 | C75: =VLOOKUP(B75,Fornecedores!A:B,2,0) -> ELOGROUP DESENVOLVIMENTO E CONSULT LTDA | D75: Sunara | E75: 00011282 | F75: 45813 | G75: 210210 | H75: =VLOOKUP(E75&B75,'Conf Oracle'!A:F,6,0) -> 45826.514 | J75: =IF(OR(ISBLANK(F75), ISBLANK(H75)), "", IFERROR(NETWORKDAYS(F75, H75), "")) -> 10
A76: 45817 | B76: 08670505000175 | C76: =VLOOKUP(B76,Fornecedores!A:B,2,0) -> ELOGROUP DESENVOLVIMENTO E CONSULT LTDA | D76: Sunara | E76: 00011281 | F76: 45813 | G76: 226534 | H76: =VLOOKUP(E76&B76,'Conf Oracle'!A:F,6,0) -> 45826.467 | J76: =IF(OR(ISBLANK(F76), ISBLANK(H76)), "", IFERROR(NETWORKDAYS(F76, H76), "")) -> 10
A77: 45817 | B77: 08670505000175 | C77: =VLOOKUP(B77,Fornecedores!A:B,2,0) -> ELOGROUP DESENVOLVIMENTO E CONSULT LTDA | D77: Sunara | E77: 00011280 | F77: 45813 | G77: 186956 | H77: =VLOOKUP(E77&B77,'Conf Oracle'!A:F,6,0) -> 45831.633 | J77: =IF(OR(ISBLANK(F77), ISBLANK(H77)), "", IFERROR(NETWORKDAYS(F77, H77), "")) -> 13
A78: 45818 | B78: 52898194000198 | C78: =VLOOKUP(B78,Fornecedores!A:B,2,0) -> CM COMANDOS LINEARES LTDA | D78: Guilherme | E78: 00128333 | F78: 45817 | G78: 91330.6 | H78: =VLOOKUP(E78&B78,'Conf Oracle'!A:F,6,0) -> 45821.63 | I78: LANÇADA | J78: =IF(OR(ISBLANK(F78), ISBLANK(H78)), "", IFERROR(NETWORKDAYS(F78, H78), "")) -> 5
A79: 45819 | B79: 60444437000146 | C79: =VLOOKUP(B79,Fornecedores!A:B,2,0) -> LIGHT SERV. DE ELETRICIDADE SA | D79: Isabela | E79: 00266646 | F79: 45810 | G79: 133362.01 | H79: 45817 | I79: OC_0009624 | J79: =IF(OR(ISBLANK(F79), ISBLANK(H79)), "", IFERROR(NETWORKDAYS(F79, H79), "")) -> 6
A80: 45820 | B80: 90347840005691 | C80: =VLOOKUP(B80,Fornecedores!A:B,2,0) -> TK ELEVADORES BRASIL LTDA. | D80: Isabela | E80: 00111843 | F80: 45810 | G80: 13781.17 | H80: =VLOOKUP(E80&B80,'Conf Oracle'!A:F,6,0) -> 45818.599 | I80: OC_0009642 | J80: =IF(OR(ISBLANK(F80), ISBLANK(H80)), "", IFERROR(NETWORKDAYS(F80, H80), "")) -> 7
A81: 45821 | B81: 21515602000151 | C81: =VLOOKUP(B81,Fornecedores!A:B,2,0) -> CENARIO RJ TECNOLOGIA EM AUDIO E VIDEO LTDA | D81: Guilherme | E81: 00001245 | F81: 45819 | G81: 1280 | H81: =VLOOKUP(E81&B81,'Conf Oracle'!A:F,6,0) -> 45826.429 | I81: LANÇADA | J81: =IF(OR(ISBLANK(F81), ISBLANK(H81)), "", IFERROR(NETWORKDAYS(F81, H81), "")) -> 6
A82: 45821 | B82: 10836388000119 | C82: =VLOOKUP(B82,Fornecedores!A:B,2,0) -> STANDARD IT CONSULTORIA LTDA | D82: Guilherme | E82: 00001527 | F82: 45818 | G82: 32178.9 | H82: =VLOOKUP(E82&B82,'Conf Oracle'!A:F,6,0) -> 45825.375 | I82: LANÇADA | J82: =IF(OR(ISBLANK(F82), ISBLANK(H82)), "", IFERROR(NETWORKDAYS(F82, H82), "")) -> 6
A83: 45821 | B83: 02558157013574 | C83: =VLOOKUP(B83,Fornecedores!A:B,2,0) -> TELEFONICA BRASIL SA | D83: Ingrid | E83: 00466985 | F83: 45817 | G83: 915.86 | H83: =VLOOKUP(E83&B83,'Conf Oracle'!A:F,6,0) -> #N/A | I83: Em contestação | J83: =IF(OR(ISBLANK(F83), ISBLANK(H83)), "", IFERROR(NETWORKDAYS(F83, H83), ""))
A84: 45821 | B84: 02558157013574 | C84: =VLOOKUP(B84,Fornecedores!A:B,2,0) -> TELEFONICA BRASIL SA | D84: Ingrid | E84: 00469228 | F84: 45817 | G84: 1581.56 | H84: =VLOOKUP(E84&B84,'Conf Oracle'!A:F,6,0) -> #N/A | I84: Em contestação | J84: =IF(OR(ISBLANK(F84), ISBLANK(H84)), "", IFERROR(NETWORKDAYS(F84, H84), ""))
A85: 45821 | B85: 02558157013574 | C85: =VLOOKUP(B85,Fornecedores!A:B,2,0) -> TELEFONICA BRASIL SA | D85: Ingrid | E85: 00464393 | F85: 45817 | G85: 2522.64 | H85: =VLOOKUP(E85&B85,'Conf Oracle'!A:F,6,0) -> #N/A | I85: Em contestação | J85: =IF(OR(ISBLANK(F85), ISBLANK(H85)), "", IFERROR(NETWORKDAYS(F85, H85), ""))
A86: 45821 | B86: 02558157013574 | C86: =VLOOKUP(B86,Fornecedores!A:B,2,0) -> TELEFONICA BRASIL SA | D86: Ingrid | E86: 00464434 | F86: 45817 | G86: 3167.16 | H86: =VLOOKUP(E86&B86,'Conf Oracle'!A:F,6,0) -> #N/A | I86: Em contestação | J86: =IF(OR(ISBLANK(F86), ISBLANK(H86)), "", IFERROR(NETWORKDAYS(F86, H86), ""))
A87: 45821 | B87: 02558157013574 | C87: =VLOOKUP(B87,Fornecedores!A:B,2,0) -> TELEFONICA BRASIL SA | D87: Ingrid | E87: 00469213 | F87: 45817 | G87: 180 | H87: =VLOOKUP(E87&B87,'Conf Oracle'!A:F,6,0) -> #N/A | I87: Em contestação | J87: =IF(OR(ISBLANK(F87), ISBLANK(H87)), "", IFERROR(NETWORKDAYS(F87, H87), ""))
A88: 45821 | B88: 02558157013574 | C88: =VLOOKUP(B88,Fornecedores!A:B,2,0) -> TELEFONICA BRASIL SA | D88: Ingrid | E88: 00465282 | F88: 45817 | G88: 1110.62 | H88: =VLOOKUP(E88&B88,'Conf Oracle'!A:F,6,0) -> #N/A | I88: Em contestação | J88: =IF(OR(ISBLANK(F88), ISBLANK(H88)), "", IFERROR(NETWORKDAYS(F88, H88), ""))
A89: 45821 | B89: 02558157013574 | C89: =VLOOKUP(B89,Fornecedores!A:B,2,0) -> TELEFONICA BRASIL SA | D89: Ingrid | E89: 00465228 | F89: 45817 | G89: 1080 | H89: =VLOOKUP(E89&B89,'Conf Oracle'!A:F,6,0) -> 45840.459 | J89: =IF(OR(ISBLANK(F89), ISBLANK(H89)), "", IFERROR(NETWORKDAYS(F89, H89), "")) -> 18
A90: 45821 | B90: 02558157013574 | C90: =VLOOKUP(B90,Fornecedores!A:B,2,0) -> TELEFONICA BRASIL SA | D90: Ingrid | E90: 00465247 | F90: 45817 | G90: 882.79 | H90: =VLOOKUP(E90&B90,'Conf Oracle'!A:F,6,0) -> #N/A | I90: Em contestação | J90: =IF(OR(ISBLANK(F90), ISBLANK(H90)), "", IFERROR(NETWORKDAYS(F90, H90), ""))
A91: 45821 | B91: 02558157013574 | C91: =VLOOKUP(B91,Fornecedores!A:B,2,0) -> TELEFONICA BRASIL SA | D91: Ingrid | E91: 000465206 | F91: 45817 | G91: 360 | H91: =VLOOKUP(E91&B91,'Conf Oracle'!A:F,6,0) -> 45840.434 | J91: =IF(OR(ISBLANK(F91), ISBLANK(H91)), "", IFERROR(NETWORKDAYS(F91, H91), "")) -> 18
A92: 45821 | B92: 02558157013574 | C92: =VLOOKUP(B92,Fornecedores!A:B,2,0) -> TELEFONICA BRASIL SA | D92: Ingrid | E92: 00464408 | F92: 45817 | G92: 1657.98 | H92: =VLOOKUP(E92&B92,'Conf Oracle'!A:F,6,0) -> #N/A | I92: Em contestação | J92: =IF(OR(ISBLANK(F92), ISBLANK(H92)), "", IFERROR(NETWORKDAYS(F92, H92), ""))
A93: 45821 | B93: 02558157013574 | C93: =VLOOKUP(B93,Fornecedores!A:B,2,0) -> TELEFONICA BRASIL SA | D93: Ingrid | E93: 00469220 | F93: 45817 | G93: 180 | H93: =VLOOKUP(E93&B93,'Conf Oracle'!A:F,6,0) -> #N/A | I93: Em contestação | J93: =IF(OR(ISBLANK(F93), ISBLANK(H93)), "", IFERROR(NETWORKDAYS(F93, H93), ""))
A94: 45821 | B94: 485222719 | C94: =VLOOKUP(B94,Fornecedores!A:B,2,0) -> NETZOOM | D94: Ingrid | E94: 42537 | F94: 45820 | G94: 103500 | H94: =VLOOKUP(E94&B94,'Conf Oracle'!A:F,6,0) -> 45840.653 | I94: OC_0009952 | J94: =IF(OR(ISBLANK(F94), ISBLANK(H94)), "", IFERROR(NETWORKDAYS(F94, H94), "")) -> 15
A95: 45821 | B95: 64601925000502 | C95: =VLOOKUP(B95,Fornecedores!A:B,2,0) -> Tour House Viagens e Turismo LTDA-THV - Bragança | D95: Isabela | E95: 00636126 | F95: 45817 | G95: 225 | H95: 45820 | I95: Lançada | J95: =IF(OR(ISBLANK(F95), ISBLANK(H95)), "", IFERROR(NETWORKDAYS(F95, H95), "")) -> 4
A96: 45821 | B96: 08689801000118 | C96: =VLOOKUP(B96,Fornecedores!A:B,2,0) -> ALERTE AUTOM LEIT RECORT DIAR OFIC LTDA | D96: Isabela | E96: 00098681 | F96: 45819 | G96: 1470.18 | H96: =VLOOKUP(E96&B96,'Conf Oracle'!A:F,6,0) -> 45821.436 | J96: =IF(OR(ISBLANK(F96), ISBLANK(H96)), "", IFERROR(NETWORKDAYS(F96, H96), "")) -> 3
A97: 45821 | B97: 19427033000140 | C97: =VLOOKUP(B97,Fornecedores!A:B,2,0) -> ARQUIVEI SERVICOS ON LINE LTDA | D97: Evandrea | E97: 00485267 | F97: 45819 | G97: 2600 | H97: =VLOOKUP(E97&B97,'Conf Oracle'!A:F,6,0) -> 45819.685 | J97: =IF(OR(ISBLANK(F97), ISBLANK(H97)), "", IFERROR(NETWORKDAYS(F97, H97), "")) -> 1
A98: 45821 | B98: 69034668000156 | C98: =VLOOKUP(B98,Fornecedores!A:B,2,0) -> PLUXEE BENEFICIOS BRASIL SA | D98: Isabela | E98: 05303597 | F98: 45819 | G98: 2909.76 | H98: =VLOOKUP(E98&B98,'Conf Oracle'!A:F,6,0) -> 45820.667 | J98: =IF(OR(ISBLANK(F98), ISBLANK(H98)), "", IFERROR(NETWORKDAYS(F98, H98), "")) -> 2
A99: 45821 | B99: 69034668000156 | C99: =VLOOKUP(B99,Fornecedores!A:B,2,0) -> PLUXEE BENEFICIOS BRASIL SA | D99: Isabela | E99: 05303595 | F99: 45819 | G99: 1732 | H99: =VLOOKUP(E99&B99,'Conf Oracle'!A:F,6,0) -> 45820.685 | J99: =IF(OR(ISBLANK(F99), ISBLANK(H99)), "", IFERROR(NETWORKDAYS(F99, H99), "")) -> 2
A100: 45821 | B100: 20054467000121 | C100: =VLOOKUP(B100,Fornecedores!A:B,2,0) -> SOLARPLEX SERVICOS LTDA | D100: Jessy | E100: 00000149 | F100: 45818 | G100: 20400 | H100: =VLOOKUP(E100&B100,'Conf Oracle'!A:F,6,0) -> 45826.671 | I100: ok | J100: =IF(OR(ISBLANK(F100), ISBLANK(H100)), "", IFERROR(NETWORKDAYS(F100, H100), "")) -> 7
A101: 45821 | B101: 33434173000177 | C101: =VLOOKUP(B101,Fornecedores!A:B,2,0) -> INTERA TALENT HACKING RECRUTAMENTO LTDA | D101: Jessy | E101: 00003127 | F101: 45818 | G101: 11000 | H101: =VLOOKUP(E101&B101,'Conf Oracle'!A:F,6,0) -> 45832.609 | I101: ok | J101: =IF(OR(ISBLANK(F101), ISBLANK(H101)), "", IFERROR(NETWORKDAYS(F101, H101), "")) -> 11
...

Sheet Controle de NF - Maio
A2: Mês | B2: CNPJ | C2: Fornecedor | D2: Gestor Adm | E2: NF | F2: Emissão da NF | G2: Valor da NF | H2: Conferência | I2: Observação | J2: SLA
A3: 45782 | B3: 16554325000156 | C3: =VLOOKUP(B3,Fornecedores!A:B,2,0) -> AMBIENTE VERDE RESIDUOS LTDA | D3: Evandrea | E3: 00000955 | F3: 45779 | G3: 2690 | H3: =VLOOKUP(E3&B3,'Conf Oracle'!A:F,6,0) -> 45789.363 | J3: =IF(OR(ISBLANK(F3), ISBLANK(H3)), "", IFERROR(NETWORKDAYS(F3, H3), "")) -> 7
A4: 45782 | B4: 15667402000111 | C4: =VLOOKUP(B4,Fornecedores!A:B,2,0) -> SIMPLE ENERGY ASSESSORIA E GESTAO DE ENERGIA LTDA. | D4: Evandrea | E4: 00020983 | F4: 45779 | G4: 733.38 | H4: =VLOOKUP(E4&B4,'Conf Oracle'!A:F,6,0) -> 45786.469 | J4: =IF(OR(ISBLANK(F4), ISBLANK(H4)), "", IFERROR(NETWORKDAYS(F4, H4), "")) -> 6
A5: 45782 | B5: 15667402000111 | C5: =VLOOKUP(B5,Fornecedores!A:B,2,0) -> SIMPLE ENERGY ASSESSORIA E GESTAO DE ENERGIA LTDA. | D5: Evandrea | E5: 00020987 | F5: 45779 | G5: 733.38 | H5: =VLOOKUP(E5&B5,'Conf Oracle'!A:F,6,0) -> 45786.463 | J5: =IF(OR(ISBLANK(F5), ISBLANK(H5)), "", IFERROR(NETWORKDAYS(F5, H5), "")) -> 6
A6: 45782 | B6: 15667402000111 | C6: =VLOOKUP(B6,Fornecedores!A:B,2,0) -> SIMPLE ENERGY ASSESSORIA E GESTAO DE ENERGIA LTDA. | D6: Evandrea | E6: 00020976 | F6: 45779 | G6: 733.38 | H6: =VLOOKUP(E6&B6,'Conf Oracle'!A:F,6,0) -> 45786.461 | J6: =IF(OR(ISBLANK(F6), ISBLANK(H6)), "", IFERROR(NETWORKDAYS(F6, H6), "")) -> 6
A7: 45782 | B7: 15667402000111 | C7: =VLOOKUP(B7,Fornecedores!A:B,2,0) -> SIMPLE ENERGY ASSESSORIA E GESTAO DE ENERGIA LTDA. | D7: Evandrea | E7: 00020972 | F7: 45779 | G7: 733.38 | H7: =VLOOKUP(E7&B7,'Conf Oracle'!A:F,6,0) -> 45786.472 | J7: =IF(OR(ISBLANK(F7), ISBLANK(H7)), "", IFERROR(NETWORKDAYS(F7, H7), "")) -> 6
A8: 45783 | B8: 90347840005691 | C8: =VLOOKUP(B8,Fornecedores!A:B,2,0) -> TK ELEVADORES BRASIL LTDA. | D8: Evandrea | E8: 00111804 | F8: 45779 | G8: 13781.17 | H8: =VLOOKUP(E8&B8,'Conf Oracle'!A:F,6,0) -> 45786.465 | J8: =IF(OR(ISBLANK(F8), ISBLANK(H8)), "", IFERROR(NETWORKDAYS(F8, H8), "")) -> 6
A9: 45783 | B9: 00001180000126 | C9: =VLOOKUP(B9,Fornecedores!A:B,2,0) -> Centrais Elétricas Brasileiras S/A - Eletrobras | D9: Evandrea | E9: 00041021 | F9: 45782 | G9: 88432.31 | H9: =VLOOKUP(E9&B9,'Conf Oracle'!A:F,6,0) -> 45786.542 | J9: =IF(OR(ISBLANK(F9), ISBLANK(H9)), "", IFERROR(NETWORKDAYS(F9, H9), "")) -> 5
A10: 45783 | B10: 00001180000126 | C10: =VLOOKUP(B10,Fornecedores!A:B,2,0) -> Centrais Elétricas Brasileiras S/A - Eletrobras | D10: Evandrea | E10: 00041024 | F10: 45782 | G10: 41841.42 | H10: =VLOOKUP(E10&B10,'Conf Oracle'!A:F,6,0) -> 45786.537 | J10: =IF(OR(ISBLANK(F10), ISBLANK(H10)), "", IFERROR(NETWORKDAYS(F10, H10), "")) -> 5
A11: 45783 | B11: 00001180000126 | C11: =VLOOKUP(B11,Fornecedores!A:B,2,0) -> Centrais Elétricas Brasileiras S/A - Eletrobras | D11: Evandrea | E11: 00041020 | F11: 45782 | G11: 64408.65 | H11: =VLOOKUP(E11&B11,'Conf Oracle'!A:F,6,0) -> 45786.546 | J11: =IF(OR(ISBLANK(F11), ISBLANK(H11)), "", IFERROR(NETWORKDAYS(F11, H11), "")) -> 5
A12: 45783 | B12: 00001180000126 | C12: =VLOOKUP(B12,Fornecedores!A:B,2,0) -> Centrais Elétricas Brasileiras S/A - Eletrobras | D12: Evandrea | E12: 00041025 | F12: 45782 | G12: 21403.99 | H12: =VLOOKUP(E12&B12,'Conf Oracle'!A:F,6,0) -> 45786.534 | J12: =IF(OR(ISBLANK(F12), ISBLANK(H12)), "", IFERROR(NETWORKDAYS(F12, H12), "")) -> 5
A13: 45783 | B13: 00028986001694 | C13: =VLOOKUP(B13,Fornecedores!A:B,2,0) -> ELEVADORES ATLAS SCHINDLER SA | D13: Evandrea | E13: 00468657 | F13: 45782 | G13: 1960.94 | H13: =VLOOKUP(E13&B13,'Conf Oracle'!A:F,6,0) -> 45796.454 | I13: LANÇADA | J13: =IF(OR(ISBLANK(F13), ISBLANK(H13)), "", IFERROR(NETWORKDAYS(F13, H13), "")) -> 11
A14: 45783 | B14: 08270682000164 | C14: =VLOOKUP(B14,Fornecedores!A:B,2,0) -> CONFIDERE IMOBILIARIA LTDA | D14: Evandrea | E14: 00202505 | F14: 45784 | G14: 2970031.4 | H14: 45789 | J14: =IF(OR(ISBLANK(F14), ISBLANK(H14)), "", IFERROR(NETWORKDAYS(F14, H14), "")) -> 4
A15: 45783 | B15: 72381189000110 | C15: =VLOOKUP(B15,Fornecedores!A:B,2,0) -> DELL COMPUTADORES DO BRASIL LTDA | D15: Guilherme | E15: 02724579 | F15: 45779 | G15: 56100.02 | H15: =VLOOKUP(E15&B15,'Conf Oracle'!A:F,6,0) -> 45798.65 | I15: LANÇADA | J15: =IF(OR(ISBLANK(F15), ISBLANK(H15)), "", IFERROR(NETWORKDAYS(F15, H15), "")) -> 14
A16: 45783 | B16: 72381189000110 | C16: =VLOOKUP(B16,Fornecedores!A:B,2,0) -> DELL COMPUTADORES DO BRASIL LTDA | D16: Guilherme | E16: 02724573 | F16: 45779 | G16: 14999.99 | H16: =VLOOKUP(E16&B16,'Conf Oracle'!A:F,6,0) -> 45798.65 | J16: =IF(OR(ISBLANK(F16), ISBLANK(H16)), "", IFERROR(NETWORKDAYS(F16, H16), "")) -> 14
A17: 45783 | B17: 72381189000110 | C17: =VLOOKUP(B17,Fornecedores!A:B,2,0) -> DELL COMPUTADORES DO BRASIL LTDA | D17: Guilherme | E17: 02724575 | F17: 45779 | G17: 104399.97 | H17: =VLOOKUP(E17&B17,'Conf Oracle'!A:F,6,0) -> 45798.634 | J17: =IF(OR(ISBLANK(F17), ISBLANK(H17)), "", IFERROR(NETWORKDAYS(F17, H17), "")) -> 14
A18: 45783 | B18: 72381189000110 | C18: =VLOOKUP(B18,Fornecedores!A:B,2,0) -> DELL COMPUTADORES DO BRASIL LTDA | D18: Guilherme | E18: 02724579 | F18: 45779 | G18: 56100.02 | H18: =VLOOKUP(E18&B18,'Conf Oracle'!A:F,6,0) -> 45798.65 | J18: =IF(OR(ISBLANK(F18), ISBLANK(H18)), "", IFERROR(NETWORKDAYS(F18, H18), "")) -> 14
A19: 45785 | B19: 72381189001001 | C19: =VLOOKUP(B19,Fornecedores!A:B,2,0) -> DELL COMPUTADORES DO BRASIL LTDA | D19: Guilherme | E19: 07619304 | F19: 45783 | G19: 192271.61 | H19: =VLOOKUP(E19&B19,'Conf Oracle'!A:F,6,0) -> 45804.632 | J19: =IF(OR(ISBLANK(F19), ISBLANK(H19)), "", IFERROR(NETWORKDAYS(F19, H19), "")) -> 16
A20: 45785 | B20: 72381189001001 | C20: =VLOOKUP(B20,Fornecedores!A:B,2,0) -> DELL COMPUTADORES DO BRASIL LTDA | D20: Guilherme | E20: 02726713 | F20: 45783 | G20: 59347.4 | H20: =VLOOKUP(E20&B20,'Conf Oracle'!A:F,6,0) -> 45804.674 | J20: =IF(OR(ISBLANK(F20), ISBLANK(H20)), "", IFERROR(NETWORKDAYS(F20, H20), "")) -> 16
A21: 45785 | B21: 72381189001001 | C21: =VLOOKUP(B21,Fornecedores!A:B,2,0) -> DELL COMPUTADORES DO BRASIL LTDA | D21: Guilherme | E21: 07621804 | F21: 45784 | G21: 123667.75 | H21: =VLOOKUP(E21&B21,'Conf Oracle'!A:F,6,0) -> 45803.562 | J21: =IF(OR(ISBLANK(F21), ISBLANK(H21)), "", IFERROR(NETWORKDAYS(F21, H21), "")) -> 14
A22: 45785 | B22: 72381189001001 | C22: =VLOOKUP(B22,Fornecedores!A:B,2,0) -> DELL COMPUTADORES DO BRASIL LTDA | D22: Guilherme | E22: 07621796 | F22: 45784 | G22: 140004.35 | H22: =VLOOKUP(E22&B22,'Conf Oracle'!A:F,6,0) -> 45799.65 | J22: =IF(OR(ISBLANK(F22), ISBLANK(H22)), "", IFERROR(NETWORKDAYS(F22, H22), "")) -> 12
A23: 45785 | B23: 72381189001001 | C23: =VLOOKUP(B23,Fornecedores!A:B,2,0) -> DELL COMPUTADORES DO BRASIL LTDA | D23: Guilherme | E23: 02727291 | F23: 45784 | G23: 90866.9 | H23: =VLOOKUP(E23&B23,'Conf Oracle'!A:F,6,0) -> 45803.493 | J23: =IF(OR(ISBLANK(F23), ISBLANK(H23)), "", IFERROR(NETWORKDAYS(F23, H23), "")) -> 14
A24: 45785 | B24: 72381189001001 | C24: =VLOOKUP(B24,Fornecedores!A:B,2,0) -> DELL COMPUTADORES DO BRASIL LTDA | D24: Guilherme | E24: 02727290 | F24: 45784 | G24: 41258.43 | H24: =VLOOKUP(E24&B24,'Conf Oracle'!A:F,6,0) -> 45805.438 | J24: =IF(OR(ISBLANK(F24), ISBLANK(H24)), "", IFERROR(NETWORKDAYS(F24, H24), "")) -> 16
A25: 45785 | B25: 72381189001001 | C25: =VLOOKUP(B25,Fornecedores!A:B,2,0) -> DELL COMPUTADORES DO BRASIL LTDA | D25: Guilherme | E25: 02727292 | F25: 45784 | G25: 49112.05 | H25: =VLOOKUP(E25&B25,'Conf Oracle'!A:F,6,0) -> 45803.478 | J25: =IF(OR(ISBLANK(F25), ISBLANK(H25)), "", IFERROR(NETWORKDAYS(F25, H25), "")) -> 14
A26: 45785 | B26: 72381189001001 | C26: =VLOOKUP(B26,Fornecedores!A:B,2,0) -> DELL COMPUTADORES DO BRASIL LTDA | D26: Guilherme | E26: 07621797 | F26: 45784 | G26: 255168.33 | H26: =VLOOKUP(E26&B26,'Conf Oracle'!A:F,6,0) -> 45804.666 | J26: =IF(OR(ISBLANK(F26), ISBLANK(H26)), "", IFERROR(NETWORKDAYS(F26, H26), "")) -> 15
A27: 45785 | B27: 35808969000178 | C27: =VLOOKUP(B27,Fornecedores!A:B,2,0) -> DIGITAL 8 SOLUCOES DIGITAIS LTDA | D27: Guilherme | E27: 00000284 | F27: 45785 | G27: 26138.11 | H27: CANCELADA | I27: NF CANCELADA | J27: =IF(OR(ISBLANK(F27), ISBLANK(H27)), "", IFERROR(NETWORKDAYS(F27, H27), ""))
A28: 45782 | B28: 58652678000139 | C28: =VLOOKUP(B28,Fornecedores!A:B,2,0) -> COLUMBIA STORAGE INTEGR DE SITEMAS LTDA | D28: Ingrid | E28: 00011125 | F28: 45779 | G28: 17116.41 | H28: =VLOOKUP(E28&B28,'Conf Oracle'!A:F,6,0) -> 45799.428 | J28: =IF(OR(ISBLANK(F28), ISBLANK(H28)), "", IFERROR(NETWORKDAYS(F28, H28), "")) -> 15
A29: 45782 | B29: 23412247000110 | C29: =VLOOKUP(B29,Fornecedores!A:B,2,0) -> AMAZON AWS SERVICOS BRASIL LTDA | D29: Ingrid | E29: 04299709 | F29: 45779 | G29: 545976.71 | H29: =VLOOKUP(E29&B29,'Conf Oracle'!A:F,6,0) -> 45806.543 | J29: =IF(OR(ISBLANK(F29), ISBLANK(H29)), "", IFERROR(NETWORKDAYS(F29, H29), "")) -> 20
A30: 45782 | B30: 23412247000110 | C30: =VLOOKUP(B30,Fornecedores!A:B,2,0) -> AMAZON AWS SERVICOS BRASIL LTDA | D30: Ingrid | E30: 04299227 | F30: 45779 | G30: 59766.48 | H30: =VLOOKUP(E30&B30,'Conf Oracle'!A:F,6,0) -> 45806.54 | J30: =IF(OR(ISBLANK(F30), ISBLANK(H30)), "", IFERROR(NETWORKDAYS(F30, H30), "")) -> 20
A31: 45785 | B31: 07850212000107 | C31: =VLOOKUP(B31,Fornecedores!A:B,2,0) -> REAL SEGURANCA INTEGRADA EIRELI | D31: Ingrid | E31: 00001190 | F31: 45783 | G31: 217.9 | H31: =VLOOKUP(E31&B31,'Conf Oracle'!A:F,6,0) -> 45799.488 | J31: =IF(OR(ISBLANK(F31), ISBLANK(H31)), "", IFERROR(NETWORKDAYS(F31, H31), "")) -> 13
A32: 45782 | B32: 26409092000151 | C32: =VLOOKUP(B32,Fornecedores!A:B,2,0) -> SSAMRO SOLUCOES PARA MANUTENCAO INDUSTR | D32: Isabela | E32: 00024874 | F32: 45779 | G32: 648.76 | H32: =VLOOKUP(E32&B32,'Conf Oracle'!A:F,6,0) -> 45785.689 | J32: =IF(OR(ISBLANK(F32), ISBLANK(H32)), "", IFERROR(NETWORKDAYS(F32, H32), "")) -> 5
A33: 45782 | B33: 26409092000151 | C33: =VLOOKUP(B33,Fornecedores!A:B,2,0) -> SSAMRO SOLUCOES PARA MANUTENCAO INDUSTR | D33: Isabela | E33: 00024878 | F33: 45779 | G33: 648.76 | H33: =VLOOKUP(E33&B33,'Conf Oracle'!A:F,6,0) -> 45785.694 | J33: =IF(OR(ISBLANK(F33), ISBLANK(H33)), "", IFERROR(NETWORKDAYS(F33, H33), "")) -> 5
A34: 45782 | B34: 26409092000151 | C34: =VLOOKUP(B34,Fornecedores!A:B,2,0) -> SSAMRO SOLUCOES PARA MANUTENCAO INDUSTR | D34: Isabela | E34: 00024876 | F34: 45779 | G34: 648.76 | H34: =VLOOKUP(E34&B34,'Conf Oracle'!A:F,6,0) -> 45785.697 | J34: =IF(OR(ISBLANK(F34), ISBLANK(H34)), "", IFERROR(NETWORKDAYS(F34, H34), "")) -> 5
A35: 45782 | B35: 26409092000151 | C35: =VLOOKUP(B35,Fornecedores!A:B,2,0) -> SSAMRO SOLUCOES PARA MANUTENCAO INDUSTR | D35: Isabela | E35: 00024885 | F35: 45779 | G35: 648.76 | H35: =VLOOKUP(E35&B35,'Conf Oracle'!A:F,6,0) -> 45785.683 | J35: =IF(OR(ISBLANK(F35), ISBLANK(H35)), "", IFERROR(NETWORKDAYS(F35, H35), "")) -> 5
A36: 45783 | B36: 00497373000110 | C36: =VLOOKUP(B36,Fornecedores!A:B,2,0) -> SKY SERVICOS DE BANDA LARGA LTDA | D36: Evandrea | E36: 84551295 | F36: 45778 | G36: 185.24 | H36: =VLOOKUP(E36&B36,'Conf Oracle'!A:F,6,0) -> 45782.638 | J36: =IF(OR(ISBLANK(F36), ISBLANK(H36)), "", IFERROR(NETWORKDAYS(F36, H36), "")) -> 3
A37: 45782 | B37: 72157654000215 | C37: =VLOOKUP(B37,Fornecedores!A:B,2,0) -> VELA SOFTWARE E SERVICOS LTDA | D37: Isabela | E37: 20257901 | F37: 45780 | G37: 677.6 | H37: =VLOOKUP(E37&B37,'Conf Oracle'!A:F,6,0) -> 45785.712 | I37: lançada | J37: =IF(OR(ISBLANK(F37), ISBLANK(H37)), "", IFERROR(NETWORKDAYS(F37, H37), "")) -> 4
A38: 45782 | B38: 72157654000215 | C38: =VLOOKUP(B38,Fornecedores!A:B,2,0) -> VELA SOFTWARE E SERVICOS LTDA | D38: Isabela | E38: 20257900 | F38: 45780 | G38: 677.6 | H38: =VLOOKUP(E38&B38,'Conf Oracle'!A:F,6,0) -> 45785.716 | I38: lançada | J38: =IF(OR(ISBLANK(F38), ISBLANK(H38)), "", IFERROR(NETWORKDAYS(F38, H38), "")) -> 4
A39: 45782 | B39: 72157654000215 | C39: =VLOOKUP(B39,Fornecedores!A:B,2,0) -> VELA SOFTWARE E SERVICOS LTDA | D39: Isabela | E39: 20257898 | F39: 45780 | G39: 677.6 | H39: =VLOOKUP(E39&B39,'Conf Oracle'!A:F,6,0) -> 45785.719 | I39: lançada | J39: =IF(OR(ISBLANK(F39), ISBLANK(H39)), "", IFERROR(NETWORKDAYS(F39, H39), "")) -> 4
A40: 45782 | B40: 72157654000215 | C40: =VLOOKUP(B40,Fornecedores!A:B,2,0) -> VELA SOFTWARE E SERVICOS LTDA | D40: Isabela | E40: 20257902 | F40: 45781 | G40: 677.6 | H40: =VLOOKUP(E40&B40,'Conf Oracle'!A:F,6,0) -> 45785.724 | I40: lançada | J40: =IF(OR(ISBLANK(F40), ISBLANK(H40)), "", IFERROR(NETWORKDAYS(F40, H40), "")) -> 4
A41: 45783 | B41: 27532282000124 | C41: =VLOOKUP(B41,Fornecedores!A:B,2,0) -> TROPIFLORA PLANTAS E FLORES LTDA | D41: Isabela | E41: 00023264 | F41: 45782 | G41: 12247.12 | H41: =VLOOKUP(E41&B41,'Conf Oracle'!A:F,6,0) -> 45789.472 | J41: =IF(OR(ISBLANK(F41), ISBLANK(H41)), "", IFERROR(NETWORKDAYS(F41, H41), "")) -> 6
A42: 45785 | B42: 04359325000116 | C42: =VLOOKUP(B42,Fornecedores!A:B,2,0) -> MORAES PITOMBO ADVOGADOS | D42: Isabela | E42: 00020382 | F42: 45782 | G42: 7500 | H42: =VLOOKUP(E42&B42,'Conf Oracle'!A:F,6,0) -> 45786.321 | J42: =IF(OR(ISBLANK(F42), ISBLANK(H42)), "", IFERROR(NETWORKDAYS(F42, H42), "")) -> 5
A43: 45785 | B43: 15491115000101 | C43: =VLOOKUP(B43,Fornecedores!A:B,2,0) -> CS INTEGRA SOLUCOES EM TECNOLOG LTDA ME | D43: Isabela | E43: 00006305 | F43: 45783 | G43: 3093 | H43: =VLOOKUP(E43&B43,'Conf Oracle'!A:F,6,0) -> 45786.342 | J43: =IF(OR(ISBLANK(F43), ISBLANK(H43)), "", IFERROR(NETWORKDAYS(F43, H43), "")) -> 4
A44: 45782 | B44: 07619387000108 | C44: =VLOOKUP(B44,Fornecedores!A:B,2,0) -> INFRA EM INSTALACOES ELETRICAS LTDA | D44: Jessy | E44: 00002530 | F44: 45652 | G44: 18750 | H44: =VLOOKUP(E44&B44,'Conf Oracle'!A:F,6,0) -> 45660.726 | I44: Nota já lançada | J44: =IF(OR(ISBLANK(F44), ISBLANK(H44)), "", IFERROR(NETWORKDAYS(F44, H44), "")) -> 7
A45: 45782 | B45: 57623555000107 | C45: =VLOOKUP(B45,Fornecedores!A:B,2,0) -> MAGICCOMP ENG E SERV DE INFORMATICA LTDA | D45: Jessy | E45: 00055658 | F45: 45779 | G45: 27750 | H45: =VLOOKUP(E45&B45,'Conf Oracle'!A:F,6,0) -> 45789.618 | I45: ok | J45: =IF(OR(ISBLANK(F45), ISBLANK(H45)), "", IFERROR(NETWORKDAYS(F45, H45), "")) -> 7
A46: 45782 | B46: 57623555000107 | C46: =VLOOKUP(B46,Fornecedores!A:B,2,0) -> MAGICCOMP ENG E SERV DE INFORMATICA LTDA | D46: Jessy | E46: 00055659 | F46: 45779 | G46: 27750 | H46: =VLOOKUP(E46&B46,'Conf Oracle'!A:F,6,0) -> 45789.624 | I46: ok | J46: =IF(OR(ISBLANK(F46), ISBLANK(H46)), "", IFERROR(NETWORKDAYS(F46, H46), "")) -> 7
A47: 45782 | B47: 57623555000107 | C47: =VLOOKUP(B47,Fornecedores!A:B,2,0) -> MAGICCOMP ENG E SERV DE INFORMATICA LTDA | D47: Jessy | E47: 00055660 | F47: 45779 | G47: 27750 | H47: =VLOOKUP(E47&B47,'Conf Oracle'!A:F,6,0) -> 45789.627 | I47: ok | J47: =IF(OR(ISBLANK(F47), ISBLANK(H47)), "", IFERROR(NETWORKDAYS(F47, H47), "")) -> 7
A48: 45782 | B48: 57623555000107 | C48: =VLOOKUP(B48,Fornecedores!A:B,2,0) -> MAGICCOMP ENG E SERV DE INFORMATICA LTDA | D48: Jessy | E48: 00055661 | F48: 45779 | G48: 27750 | H48: =VLOOKUP(E48&B48,'Conf Oracle'!A:F,6,0) -> 45789.639 | I48: ok | J48: =IF(OR(ISBLANK(F48), ISBLANK(H48)), "", IFERROR(NETWORKDAYS(F48, H48), "")) -> 7
A49: 45782 | B49: 21356354000143 | C49: =VLOOKUP(B49,Fornecedores!A:B,2,0) -> POPULOS TECNOLOGIA LTDA | D49: Jessy | E49: 00002765 | F49: 45779 | G49: 3118.52 | H49: =VLOOKUP(E49&B49,'Conf Oracle'!A:F,6,0) -> 45790.374 | J49: =IF(OR(ISBLANK(F49), ISBLANK(H49)), "", IFERROR(NETWORKDAYS(F49, H49), "")) -> 8
A50: 45782 | B50: 01609514000101 | C50: =VLOOKUP(B50,Fornecedores!A:B,2,0) -> E-HUNTER TECNOLOGIA DA INFORMAÇÃO LTDA | D50: Jessy | E50: 00005461 | F50: 45779 | G50: 2614 | H50: =VLOOKUP(E50&B50,'Conf Oracle'!A:F,6,0) -> 45790.368 | J50: =IF(OR(ISBLANK(F50), ISBLANK(H50)), "", IFERROR(NETWORKDAYS(F50, H50), "")) -> 8
A51: 45782 | B51: 01708167000174 | C51: =VLOOKUP(B51,Fornecedores!A:B,2,0) -> KPMG CONSULTORIA LTDA | D51: Jessy | E51: 00003988 | F51: 45779 | G51: 40474.69 | H51: =VLOOKUP(E51&B51,'Conf Oracle'!A:F,6,0) -> 45790.588 | I51: ok | J51: =IF(OR(ISBLANK(F51), ISBLANK(H51)), "", IFERROR(NETWORKDAYS(F51, H51), "")) -> 8
A52: 45782 | B52: 09027044000180 | C52: =VLOOKUP(B52,Fornecedores!A:B,2,0) -> P4PRO PROJETOS DE TECNOLOGIA E GESTAO EMPRESARIAL LTDA. | D52: Sunára | E52: 00001397 | F52: 45782 | G52: 11686.67 | H52: =VLOOKUP(E52&B52,'Conf Oracle'!A:F,6,0) -> 45806.657 | J52: =IF(OR(ISBLANK(F52), ISBLANK(H52)), "", IFERROR(NETWORKDAYS(F52, H52), "")) -> 19
A53: 45782 | B53: 25012398000107 | C53: =VLOOKUP(B53,Fornecedores!A:B,2,0) -> GOOGLE CLOUD BRASIL COMPUTAÇÃO E SERVICOS DE DADOS LTDA | D53: Jessy | E53: 13101343 | F53: 45779 | G53: 0.03 | H53: =VLOOKUP(E53&B53,'Conf Oracle'!A:F,6,0) -> #N/A | I53: Checar com FN | J53: =IF(OR(ISBLANK(F53), ISBLANK(H53)), "", IFERROR(NETWORKDAYS(F53, H53), ""))
A54: 45785 | B54: 40432544000147 | C54: =VLOOKUP(B54,Fornecedores!A:B,2,0) -> CLARO SA | D54: Evandrea | E54: 53930425 | F54: 45777 | G54: 2603.14 | H54: =VLOOKUP(E54&B54,'Conf Oracle'!A:F,6,0) -> 45786.59 | I54: LANÇADA | J54: =IF(OR(ISBLANK(F54), ISBLANK(H54)), "", IFERROR(NETWORKDAYS(F54, H54), "")) -> 8
A55: 45785 | B55: 40432544000147 | C55: =VLOOKUP(B55,Fornecedores!A:B,2,0) -> CLARO SA | D55: Evandrea | E55: 39060425 | F55: 45777 | G55: 19949.16 | H55: =VLOOKUP(E55&B55,'Conf Oracle'!A:F,6,0) -> 45786.489 | I55: LANÇADA | J55: =IF(OR(ISBLANK(F55), ISBLANK(H55)), "", IFERROR(NETWORKDAYS(F55, H55), "")) -> 8
A56: 45785 | B56: 40432544000147 | C56: =VLOOKUP(B56,Fornecedores!A:B,2,0) -> CLARO SA | D56: Evandrea | E56: 59930425 | F56: 45777 | G56: 2198.47 | H56: =VLOOKUP(E56&B56,'Conf Oracle'!A:F,6,0) -> 45786.456 | I56: LANÇADA | J56: =IF(OR(ISBLANK(F56), ISBLANK(H56)), "", IFERROR(NETWORKDAYS(F56, H56), "")) -> 8
A57: 45785 | B57: 40432544000147 | C57: =VLOOKUP(B57,Fornecedores!A:B,2,0) -> CLARO SA | D57: Evandrea | E57: 11990425 | F57: 45777 | G57: 3370.45 | H57: =VLOOKUP(E57&B57,'Conf Oracle'!A:F,6,0) -> 45786.622 | I57: LANÇADA | J57: =IF(OR(ISBLANK(F57), ISBLANK(H57)), "", IFERROR(NETWORKDAYS(F57, H57), "")) -> 8
A58: 45785 | B58: 40432544000147 | C58: =VLOOKUP(B58,Fornecedores!A:B,2,0) -> CLARO SA | D58: Evandrea | E58: 16140425 | F58: 45777 | G58: 1844.18 | H58: =VLOOKUP(E58&B58,'Conf Oracle'!A:F,6,0) -> 45786.602 | I58: LANÇADA | J58: =IF(OR(ISBLANK(F58), ISBLANK(H58)), "", IFERROR(NETWORKDAYS(F58, H58), "")) -> 8
A59: 45782 | B59: 30154316000107 | C59: =VLOOKUP(B59,Fornecedores!A:B,2,0) -> SMARTFORCE TECNOLOGIA, CONSULTORIA E SERVICOS LTDA | D59: Jessy | E59: 00002366 | F59: 45782 | G59: 237864.56 | H59: =VLOOKUP(E59&B59,'Conf Oracle'!A:F,6,0) -> 45789.642 | J59: =IF(OR(ISBLANK(F59), ISBLANK(H59)), "", IFERROR(NETWORKDAYS(F59, H59), "")) -> 6
A60: 45783 | B60: 40548150000159 | C60: =VLOOKUP(B60,Fornecedores!A:B,2,0) -> DUNASTUR LTDA | D60: Jessy | E60: 00001077 | F60: 45782 | G60: 680 | H60: =VLOOKUP(E60&B60,'Conf Oracle'!A:F,6,0) -> 45789.708 | J60: =IF(OR(ISBLANK(F60), ISBLANK(H60)), "", IFERROR(NETWORKDAYS(F60, H60), "")) -> 6
A61: 45783 | B61: 00191027000109 | C61: =VLOOKUP(B61,Fornecedores!A:B,2,0) -> FACILIT TECNOLOGIA LTDA EPP | D61: Jessy | E61: 00003696 | F61: 45782 | G61: 13496 | H61: =VLOOKUP(E61&B61,'Conf Oracle'!A:F,6,0) -> 45790.372 | J61: =IF(OR(ISBLANK(F61), ISBLANK(H61)), "", IFERROR(NETWORKDAYS(F61, H61), "")) -> 7
A62: 45783 | B62: 01708167000174 | C62: =VLOOKUP(B62,Fornecedores!A:B,2,0) -> KPMG CONSULTORIA LTDA | D62: Jessy | E62: 00003994 | F62: 45782 | G62: 40474.71 | H62: =VLOOKUP(E62&B62,'Conf Oracle'!A:F,6,0) -> 45790.356 | I62: ok | J62: =IF(OR(ISBLANK(F62), ISBLANK(H62)), "", IFERROR(NETWORKDAYS(F62, H62), "")) -> 7
A63: 45783 | B63: 01708167000174 | C63: =VLOOKUP(B63,Fornecedores!A:B,2,0) -> KPMG CONSULTORIA LTDA | D63: Jessy | E63: 00003993 | F63: 45782 | G63: 40474.71 | H63: =VLOOKUP(E63&B63,'Conf Oracle'!A:F,6,0) -> 45790.594 | I63: ok | J63: =IF(OR(ISBLANK(F63), ISBLANK(H63)), "", IFERROR(NETWORKDAYS(F63, H63), "")) -> 7
A64: 45783 | B64: 01933257000169 | C64: =VLOOKUP(B64,Fornecedores!A:B,2,0) -> FUTURE TECHNOLOGIES INFORMATICA LTDA | D64: Jessy | E64: 00004451 | F64: 45782 | G64: 6053.32 | H64: =VLOOKUP(E64&B64,'Conf Oracle'!A:F,6,0) -> 45796.394 | J64: =IF(OR(ISBLANK(F64), ISBLANK(H64)), "", IFERROR(NETWORKDAYS(F64, H64), "")) -> 11
A65: 45785 | B65: 72381189001001 | C65: =VLOOKUP(B65,Fornecedores!A:B,2,0) -> DELL COMPUTADORES DO BRASIL LTDA | D65: Jessy | E65: 02726584 | F65: 45783 | G65: 7714.22 | H65: =VLOOKUP(E65&B65,'Conf Oracle'!A:F,6,0) -> #N/A | I65: Não entregue | J65: =IF(OR(ISBLANK(F65), ISBLANK(H65)), "", IFERROR(NETWORKDAYS(F65, H65), ""))
A66: 45785 | B66: 72381189001001 | C66: =VLOOKUP(B66,Fornecedores!A:B,2,0) -> DELL COMPUTADORES DO BRASIL LTDA | D66: Jessy | E66: 02726585 | F66: 45783 | G66: 6749.95 | H66: =VLOOKUP(E66&B66,'Conf Oracle'!A:F,6,0) -> #N/A | I66: Não entregue | J66: =IF(OR(ISBLANK(F66), ISBLANK(H66)), "", IFERROR(NETWORKDAYS(F66, H66), ""))
A67: 45785 | B67: 72381189001001 | C67: =VLOOKUP(B67,Fornecedores!A:B,2,0) -> DELL COMPUTADORES DO BRASIL LTDA | D67: Jessy | E67: 02726589 | F67: 45783 | G67: 7714.22 | H67: =VLOOKUP(E67&B67,'Conf Oracle'!A:F,6,0) -> #N/A | I67: Não entregue | J67: =IF(OR(ISBLANK(F67), ISBLANK(H67)), "", IFERROR(NETWORKDAYS(F67, H67), ""))
A68: 45785 | B68: 72381189001001 | C68: =VLOOKUP(B68,Fornecedores!A:B,2,0) -> DELL COMPUTADORES DO BRASIL LTDA | D68: Jessy | E68: 02726594 | F68: 45783 | G68: 7714.22 | H68: =VLOOKUP(E68&B68,'Conf Oracle'!A:F,6,0) -> #N/A | I68: Não entregue | J68: =IF(OR(ISBLANK(F68), ISBLANK(H68)), "", IFERROR(NETWORKDAYS(F68, H68), ""))
A69: 45785 | B69: 09162855000517 | C69: =VLOOKUP(B69,Fornecedores!A:B,2,0) -> PTLS SERV TECNOLOGIA E ASSESS TECN LTDA | D69: Jessy | E69: 00216843 | F69: 45784 | G69: 241980.15 | H69: =VLOOKUP(E69&B69,'Conf Oracle'!A:F,6,0) -> 45805.646 | I69: ok | J69: =IF(OR(ISBLANK(F69), ISBLANK(H69)), "", IFERROR(NETWORKDAYS(F69, H69), "")) -> 16
A70: 45782 | B70: 44455778000160 | C70: =VLOOKUP(B70,Fornecedores!A:B,2,0) -> RDM TECHNOLOGY LTDA | D70: Pedro | E70: 00002266 | F70: 45778 | G70: 24244.95 | H70: =VLOOKUP(E70&B70,'Conf Oracle'!A:F,6,0) -> 45805.429 | J70: =IF(OR(ISBLANK(F70), ISBLANK(H70)), "", IFERROR(NETWORKDAYS(F70, H70), "")) -> 20
A71: 45782 | B71: 81785545000152 | C71: =VLOOKUP(B71,Fornecedores!A:B,2,0) -> DEL GRANDE INFO E TELEC IND E COM LTDA | D71: Pedro | E71: 00004043 | F71: 45779 | G71: 5077 | H71: =VLOOKUP(E71&B71,'Conf Oracle'!A:F,6,0) -> 45806.523 | J71: =IF(OR(ISBLANK(F71), ISBLANK(H71)), "", IFERROR(NETWORKDAYS(F71, H71), "")) -> 20
A72: 45782 | B72: 81785545000152 | C72: =VLOOKUP(B72,Fornecedores!A:B,2,0) -> DEL GRANDE INFO E TELEC IND E COM LTDA | D72: Pedro | E72: 00004044 | F72: 45779 | G72: 1618.7 | H72: =VLOOKUP(E72&B72,'Conf Oracle'!A:F,6,0) -> 45806.516 | J72: =IF(OR(ISBLANK(F72), ISBLANK(H72)), "", IFERROR(NETWORKDAYS(F72, H72), "")) -> 20
A73: 45782 | B73: 81785545000152 | C73: =VLOOKUP(B73,Fornecedores!A:B,2,0) -> DEL GRANDE INFO E TELEC IND E COM LTDA | D73: Pedro | E73: 00004046 | F73: 45779 | G73: 2825.73 | H73: =VLOOKUP(E73&B73,'Conf Oracle'!A:F,6,0) -> 45806.521 | J73: =IF(OR(ISBLANK(F73), ISBLANK(H73)), "", IFERROR(NETWORKDAYS(F73, H73), "")) -> 20
A74: 45782 | B74: 81785545000152 | C74: =VLOOKUP(B74,Fornecedores!A:B,2,0) -> DEL GRANDE INFO E TELEC IND E COM LTDA | D74: Pedro | E74: 00004045 | F74: 45779 | G74: 3151.24 | H74: =VLOOKUP(E74&B74,'Conf Oracle'!A:F,6,0) -> 45806.519 | J74: =IF(OR(ISBLANK(F74), ISBLANK(H74)), "", IFERROR(NETWORKDAYS(F74, H74), "")) -> 20
A75: 45783 | B75: 82895327000133 | C75: =VLOOKUP(B75,Fornecedores!A:B,2,0) -> FUNDACAO DE ENSINO E ENGENHARIA DE SC | D75: Pedro | E75: 00009074 | F75: 45782 | G75: 53333.33 | H75: CANCELADA | J75: =IF(OR(ISBLANK(F75), ISBLANK(H75)), "", IFERROR(NETWORKDAYS(F75, H75), ""))
A76: 45783 | B76: 30608514000195 | C76: =VLOOKUP(B76,Fornecedores!A:B,2,0) -> AGENCIA FR DE COMUNICACAO LTDA | D76: Pedro | E76: 00004071 | F76: 45782 | G76: 38034.8 | H76: =VLOOKUP(E76&B76,'Conf Oracle'!A:F,6,0) -> 45805.474 | J76: =IF(OR(ISBLANK(F76), ISBLANK(H76)), "", IFERROR(NETWORKDAYS(F76, H76), "")) -> 18
A77: 45785 | B77: 08226125000146 | C77: =VLOOKUP(B77,Fornecedores!A:B,2,0) -> ICTS GLOBAL SERV D CONSUL GES RISCO LTDA | D77: Pedro | E77: 00005762 | F77: 45763 | G77: 70426.12 | H77: =VLOOKUP(E77&B77,'Conf Oracle'!A:F,6,0) -> 45804.609 | J77: =IF(OR(ISBLANK(F77), ISBLANK(H77)), "", IFERROR(NETWORKDAYS(F77, H77), "")) -> 30
A78: 45785 | B78: 10334263000190 | C78: =VLOOKUP(B78,Fornecedores!A:B,2,0) -> HYDROBYTE SOFTWARE EIRELI | D78: Pedro | E78: 00000458 | F78: 45785 | G78: 42840.24 | H78: =VLOOKUP(E78&B78,'Conf Oracle'!A:F,6,0) -> 45811.649 | I78: Lançada | J78: =IF(OR(ISBLANK(F78), ISBLANK(H78)), "", IFERROR(NETWORKDAYS(F78, H78), "")) -> 19
A79: 45790 | B79: 07384360000183 | C79: =VLOOKUP(B79,Fornecedores!A:B,2,0) -> MAXXIMA AURORA NEGOCIOS IMOB. LTDA | D79: Evandrea | E79: 00000046 | F79: 45786 | G79: 773126.72 | H79: =VLOOKUP(E79&B79,'Conf Oracle'!A:F,6,0) -> 45796.564 | I79: LANÇADA | J79: =IF(OR(ISBLANK(F79), ISBLANK(H79)), "", IFERROR(NETWORKDAYS(F79, H79), "")) -> 7
A80: 45790 | B80: 33597659001602 | C80: =VLOOKUP(B80,Fornecedores!A:B,2,0) -> RICOH BRASIL S A | D80: Evandrea | E80: 00051053 | F80: 45782 | G80: 639.19 | H80: =VLOOKUP(E80&B80,'Conf Oracle'!A:F,6,0) -> 45790.407 | J80: =IF(OR(ISBLANK(F80), ISBLANK(H80)), "", IFERROR(NETWORKDAYS(F80, H80), "")) -> 7
A81: 45790 | B81: 33597659001602 | C81: =VLOOKUP(B81,Fornecedores!A:B,2,0) -> RICOH BRASIL S A | D81: Evandrea | E81: 00051050 | F81: 45782 | G81: 19.86 | H81: =VLOOKUP(E81&B81,'Conf Oracle'!A:F,6,0) -> 45790.431 | J81: =IF(OR(ISBLANK(F81), ISBLANK(H81)), "", IFERROR(NETWORKDAYS(F81, H81), "")) -> 7
A82: 45790 | B82: 33597659001602 | C82: =VLOOKUP(B82,Fornecedores!A:B,2,0) -> RICOH BRASIL S A | D82: Evandrea | E82: 00051054 | F82: 45782 | G82: 738.23 | H82: =VLOOKUP(E82&B82,'Conf Oracle'!A:F,6,0) -> 45790.421 | J82: =IF(OR(ISBLANK(F82), ISBLANK(H82)), "", IFERROR(NETWORKDAYS(F82, H82), "")) -> 7
A83: 45790 | B83: 33597659001602 | C83: =VLOOKUP(B83,Fornecedores!A:B,2,0) -> RICOH BRASIL S A | D83: Evandrea | E83: 00051051 | F83: 45782 | G83: 18.65 | H83: =VLOOKUP(E83&B83,'Conf Oracle'!A:F,6,0) -> 45790.436 | J83: =IF(OR(ISBLANK(F83), ISBLANK(H83)), "", IFERROR(NETWORKDAYS(F83, H83), "")) -> 7
A84: 45790 | B84: 33597659001602 | C84: =VLOOKUP(B84,Fornecedores!A:B,2,0) -> RICOH BRASIL S A | D84: Evandrea | E84: 00051052 | F84: 45782 | G84: 2231.82 | H84: =VLOOKUP(E84&B84,'Conf Oracle'!A:F,6,0) -> 45790.427 | J84: =IF(OR(ISBLANK(F84), ISBLANK(H84)), "", IFERROR(NETWORKDAYS(F84, H84), "")) -> 7
A85: 45790 | B85: 33597659001602 | C85: =VLOOKUP(B85,Fornecedores!A:B,2,0) -> RICOH BRASIL S A | D85: Evandrea | E85: 00051049 | F85: 45782 | G85: 186.85 | H85: =VLOOKUP(E85&B85,'Conf Oracle'!A:F,6,0) -> 45790.404 | J85: =IF(OR(ISBLANK(F85), ISBLANK(H85)), "", IFERROR(NETWORKDAYS(F85, H85), "")) -> 7
A86: 45790 | B86: 33597659001602 | C86: =VLOOKUP(B86,Fornecedores!A:B,2,0) -> RICOH BRASIL S A | D86: Evandrea | E86: 00051055 | F86: 45782 | G86: 369.81 | H86: =VLOOKUP(E86&B86,'Conf Oracle'!A:F,6,0) -> 45790.555 | J86: =IF(OR(ISBLANK(F86), ISBLANK(H86)), "", IFERROR(NETWORKDAYS(F86, H86), "")) -> 7
A87: 45790 | B87: 72381189000110 | C87: =VLOOKUP(B87,Fornecedores!A:B,2,0) -> DELL COMPUTADORES DO BRASIL LTDA | D87: Guilherme | E87: 02718496 | F87: 45771 | G87: 1523.67 | H87: =VLOOKUP(E87&B87,'Conf Oracle'!A:F,6,0) -> 45807.68 | J87: =IF(OR(ISBLANK(F87), ISBLANK(H87)), "", IFERROR(NETWORKDAYS(F87, H87), "")) -> 27
A88: 45790 | B88: 72381189000110 | C88: =VLOOKUP(B88,Fornecedores!A:B,2,0) -> DELL COMPUTADORES DO BRASIL LTDA | D88: Guilherme | E88: 02718498 | F88: 45771 | G88: 1870.05 | H88: =VLOOKUP(E88&B88,'Conf Oracle'!A:F,6,0) -> 45810.413 | J88: =IF(OR(ISBLANK(F88), ISBLANK(H88)), "", IFERROR(NETWORKDAYS(F88, H88), "")) -> 28
A89: 45790 | B89: 72381189000110 | C89: =VLOOKUP(B89,Fornecedores!A:B,2,0) -> DELL COMPUTADORES DO BRASIL LTDA | D89: Guilherme | E89: 02718497 | F89: 45771 | G89: 1523.67 | H89: =VLOOKUP(E89&B89,'Conf Oracle'!A:F,6,0) -> 45810.436 | J89: =IF(OR(ISBLANK(F89), ISBLANK(H89)), "", IFERROR(NETWORKDAYS(F89, H89), "")) -> 28
A90: 45790 | B90: 72381189000110 | C90: =VLOOKUP(B90,Fornecedores!A:B,2,0) -> DELL COMPUTADORES DO BRASIL LTDA | D90: Guilherme | E90: 02718499 | F90: 45771 | G90: 1523.67 | H90: FOI PEDIDO PARA CANCELAR | J90: =IF(OR(ISBLANK(F90), ISBLANK(H90)), "", IFERROR(NETWORKDAYS(F90, H90), ""))
A91: 45790 | B91: 72381189000110 | C91: =VLOOKUP(B91,Fornecedores!A:B,2,0) -> DELL COMPUTADORES DO BRASIL LTDA | D91: Guilherme | E91: 02718500 | F91: 45771 | G91: 1523.67 | H91: =VLOOKUP(E91&B91,'Conf Oracle'!A:F,6,0) -> 45810.427 | J91: =IF(OR(ISBLANK(F91), ISBLANK(H91)), "", IFERROR(NETWORKDAYS(F91, H91), "")) -> 28
A92: 45790 | B92: 72381189000110 | C92: =VLOOKUP(B92,Fornecedores!A:B,2,0) -> DELL COMPUTADORES DO BRASIL LTDA | D92: Guilherme | E92: 02718501 | F92: 45771 | G92: 1944.73 | H92: =VLOOKUP(E92&B92,'Conf Oracle'!A:F,6,0) -> 45810.406 | J92: =IF(OR(ISBLANK(F92), ISBLANK(H92)), "", IFERROR(NETWORKDAYS(F92, H92), "")) -> 28
A93: 45790 | B93: 72381189000110 | C93: =VLOOKUP(B93,Fornecedores!A:B,2,0) -> DELL COMPUTADORES DO BRASIL LTDA | D93: Guilherme | E93: 02718502 | F93: 45771 | G93: 1523.67 | H93: FOI PEDIDO PARA CANCELAR | J93: =IF(OR(ISBLANK(F93), ISBLANK(H93)), "", IFERROR(NETWORKDAYS(F93, H93), ""))
A94: 45790 | B94: 21997241000127 | C94: =VLOOKUP(B94,Fornecedores!A:B,2,0) -> WL ATACADISTA LTDA | D94: Guilherme | E94: 00700746 | F94: 45785 | G94: 26631 | H94: =VLOOKUP(E94&B94,'Conf Oracle'!A:F,6,0) -> 45789.674 | J94: =IF(OR(ISBLANK(F94), ISBLANK(H94)), "", IFERROR(NETWORKDAYS(F94, H94), "")) -> 3
A95: 45790 | B95: 02558157013574 | C95: =VLOOKUP(B95,Fornecedores!A:B,2,0) -> TELEFONICA BRASIL SA | D95: Ingrid | E95: 00422631 | F95: 45786 | G95: 1581.56 | H95: =VLOOKUP(E95&B95,'Conf Oracle'!A:F,6,0) -> #N/A | I95: Em contestação | J95: =IF(OR(ISBLANK(F95), ISBLANK(H95)), "", IFERROR(NETWORKDAYS(F95, H95), ""))
A96: 45790 | B96: 02558157013574 | C96: =VLOOKUP(B96,Fornecedores!A:B,2,0) -> TELEFONICA BRASIL SA | D96: Ingrid | E96: 00424915 | F96: 45786 | G96: 3167.16 | H96: =VLOOKUP(E96&B96,'Conf Oracle'!A:F,6,0) -> #N/A | I96: Em contestação | J96: =IF(OR(ISBLANK(F96), ISBLANK(H96)), "", IFERROR(NETWORKDAYS(F96, H96), ""))
A97: 45790 | B97: 02558157013574 | C97: =VLOOKUP(B97,Fornecedores!A:B,2,0) -> TELEFONICA BRASIL SA | D97: Ingrid | E97: 00424187 | F97: 45786 | G97: 915.86 | H97: =VLOOKUP(E97&B97,'Conf Oracle'!A:F,6,0) -> #N/A | I97: Em contestação | J97: =IF(OR(ISBLANK(F97), ISBLANK(H97)), "", IFERROR(NETWORKDAYS(F97, H97), ""))
A98: 45790 | B98: 02558157013574 | C98: =VLOOKUP(B98,Fornecedores!A:B,2,0) -> TELEFONICA BRASIL SA | D98: Ingrid | E98: 00418025 | F98: 45786 | G98: 180 | H98: =VLOOKUP(E98&B98,'Conf Oracle'!A:F,6,0) -> #N/A | I98: Em contestação | J98: =IF(OR(ISBLANK(F98), ISBLANK(H98)), "", IFERROR(NETWORKDAYS(F98, H98), ""))
A99: 45790 | B99: 02558157013574 | C99: =VLOOKUP(B99,Fornecedores!A:B,2,0) -> TELEFONICA BRASIL SA | D99: Ingrid | E99: 00418640 | F99: 45786 | G99: 1657.98 | H99: =VLOOKUP(E99&B99,'Conf Oracle'!A:F,6,0) -> #N/A | I99: Em contestação | J99: =IF(OR(ISBLANK(F99), ISBLANK(H99)), "", IFERROR(NETWORKDAYS(F99, H99), ""))
A100: 45790 | B100: 02558157013574 | C100: =VLOOKUP(B100,Fornecedores!A:B,2,0) -> TELEFONICA BRASIL SA | D100: Ingrid | E100: 00417072 | F100: 45786 | G100: 180 | H100: =VLOOKUP(E100&B100,'Conf Oracle'!A:F,6,0) -> #N/A | I100: Em contestação | J100: =IF(OR(ISBLANK(F100), ISBLANK(H100)), "", IFERROR(NETWORKDAYS(F100, H100), ""))
A101: 45790 | B101: 02558157013574 | C101: =VLOOKUP(B101,Fornecedores!A:B,2,0) -> TELEFONICA BRASIL SA | D101: Ingrid | E101: 00422562 | F101: 45786 | G101: 2522.64 | H101: =VLOOKUP(E101&B101,'Conf Oracle'!A:F,6,0) -> #N/A | I101: Em contestação | J101: =IF(OR(ISBLANK(F101), ISBLANK(H101)), "", IFERROR(NETWORKDAYS(F101, H101), ""))
...

Sheet Controle de NF - Janeiro
A2: Mês | B2: CNPJ | C2: Fornecedor | D2: Gestor Adm | E2: NF | F2: Emissão da NF | G2: Valor da NF | H2: Conferência | I2: Observação | J2: SLA
A3: 45679 | B3: 00973749000115 | C3: =VLOOKUP(B3,Fornecedores!A:B,2,0) -> TOP SERVICE SERVICOS E SISTEMAS S/A | D3: EVANDREA | E3: 00203504 | F3: 45660 | G3: 87156.36 | H3: =VLOOKUP(E3&B3,'Conf Oracle'!A:F,6,0) -> 45680.752 | J3: =IF(OR(ISBLANK(F3), ISBLANK(H3)), "", IFERROR(NETWORKDAYS(F3, H3), "")) -> 15
A4: 45679 | B4: 00973749000115 | C4: =VLOOKUP(B4,Fornecedores!A:B,2,0) -> TOP SERVICE SERVICOS E SISTEMAS S/A | D4: EVANDREA | E4: 00203502 | F4: 45660 | G4: 18401.76 | H4: =VLOOKUP(E4&B4,'Conf Oracle'!A:F,6,0) -> 45680.722 | J4: =IF(OR(ISBLANK(F4), ISBLANK(H4)), "", IFERROR(NETWORKDAYS(F4, H4), "")) -> 15
A5: 45679 | B5: 00028986001694 | C5: =VLOOKUP(B5,Fornecedores!A:B,2,0) -> ELEVADORES ATLAS SCHINDLER SA | D5: EVANDREA | E5: 00461470 | F5: 45663 | G5: 1960.94 | H5: =VLOOKUP(E5&B5,'Conf Oracle'!A:F,6,0) -> 45685.453 | J5: =IF(OR(ISBLANK(F5), ISBLANK(H5)), "", IFERROR(NETWORKDAYS(F5, H5), "")) -> 17
A6: 45679 | B6: 08270682000164 | C6: =VLOOKUP(B6,Fornecedores!A:B,2,0) -> CONFIDERE IMOBILIARIA LTDA | D6: EVANDREA | E6: 00202501 | F6: 45664 | G6: 2737093.3 | H6: =VLOOKUP(E6&B6,'Conf Oracle'!A:F,6,0) -> 45688.515 | I6: OC_0007575 | J6: =IF(OR(ISBLANK(F6), ISBLANK(H6)), "", IFERROR(NETWORKDAYS(F6, H6), "")) -> 19
A7: 45679 | B7: 43965130000171 | C7: =VLOOKUP(B7,Fornecedores!A:B,2,0) -> AGUAS CLARAS GASTRONOMIA E EVENTOS LTDA | D7: EVANDREA | E7: 00000022 | F7: 45664 | G7: 2400 | H7: =VLOOKUP(E7&B7,'Conf Oracle'!A:F,6,0) -> 45686.53 | J7: =IF(OR(ISBLANK(F7), ISBLANK(H7)), "", IFERROR(NETWORKDAYS(F7, H7), "")) -> 17
A8: 45679 | B8: 60840055051631 | C8: =VLOOKUP(B8,Fornecedores!A:B,2,0) -> FLEURY SA | D8: EVANDREA | E8: 00207911 | F8: 45665 | G8: 433.45 | H8: =VLOOKUP(E8&B8,'Conf Oracle'!A:F,6,0) -> 45679.739 | J8: =IF(OR(ISBLANK(F8), ISBLANK(H8)), "", IFERROR(NETWORKDAYS(F8, H8), "")) -> 11
A9: 45679 | B9: 90347840005691 | C9: =VLOOKUP(B9,Fornecedores!A:B,2,0) -> TK ELEVADORES BRASIL LTDA. | D9: EVANDREA | E9: 00111649 | F9: 45659 | G9: 13781.17 | H9: =VLOOKUP(E9&B9,'Conf Oracle'!A:F,6,0) -> 45688.532 | I9: OC_0007574 | J9: =IF(OR(ISBLANK(F9), ISBLANK(H9)), "", IFERROR(NETWORKDAYS(F9, H9), "")) -> 22
A10: 45679 | B10: 69034668000156 | C10: =VLOOKUP(B10,Fornecedores!A:B,2,0) -> PLUXEE BENEFICIOS BRASIL SA | D10: EVANDREA | E10: 04153543 | F10: 45665 | G10: 4745.68 | H10: =VLOOKUP(E10&B10,'Conf Oracle'!A:F,6,0) -> 45687.509 | J10: =IF(OR(ISBLANK(F10), ISBLANK(H10)), "", IFERROR(NETWORKDAYS(F10, H10), "")) -> 17
A11: 45679 | B11: 69034668000156 | C11: =VLOOKUP(B11,Fornecedores!A:B,2,0) -> PLUXEE BENEFICIOS BRASIL SA | D11: EVANDREA | E11: 04153547 | F11: 45665 | G11: 1974.48 | H11: =VLOOKUP(E11&B11,'Conf Oracle'!A:F,6,0) -> 45687.53 | J11: =IF(OR(ISBLANK(F11), ISBLANK(H11)), "", IFERROR(NETWORKDAYS(F11, H11), "")) -> 17
A12: 45679 | B12: 40432544000147 | C12: =VLOOKUP(B12,Fornecedores!A:B,2,0) -> CLARO SA | D12: EVANDREA | E12: 39061224 | F12: 45661 | G12: 19352.38 | H12: =VLOOKUP(E12&B12,'Conf Oracle'!A:F,6,0) -> 45684.65 | I12: OC_0007417 | J12: =IF(OR(ISBLANK(F12), ISBLANK(H12)), "", IFERROR(NETWORKDAYS(F12, H12), "")) -> 16
A13: 45679 | B13: 40432544000147 | C13: =VLOOKUP(B13,Fornecedores!A:B,2,0) -> CLARO SA | D13: EVANDREA | E13: 53931224 | F13: 45661 | G13: 2606.34 | H13: =VLOOKUP(E13&B13,'Conf Oracle'!A:F,6,0) -> 45684.63 | I13: OC_0007418 | J13: =IF(OR(ISBLANK(F13), ISBLANK(H13)), "", IFERROR(NETWORKDAYS(F13, H13), "")) -> 16
A14: 45679 | B14: 40432544000147 | C14: =VLOOKUP(B14,Fornecedores!A:B,2,0) -> CLARO SA | D14: EVANDREA | E14: 16141224 | F14: 45661 | G14: 1842.68 | H14: =VLOOKUP(E14&B14,'Conf Oracle'!A:F,6,0) -> 45684.614 | I14: OC_0007419 | J14: =IF(OR(ISBLANK(F14), ISBLANK(H14)), "", IFERROR(NETWORKDAYS(F14, H14), "")) -> 16
A15: 45679 | B15: 40432544000147 | C15: =VLOOKUP(B15,Fornecedores!A:B,2,0) -> CLARO SA | D15: EVANDREA | E15: 11991224 | F15: 45661 | G15: 3542.9 | H15: =VLOOKUP(E15&B15,'Conf Oracle'!A:F,6,0) -> 45684.518 | I15: OC_0007420 | J15: =IF(OR(ISBLANK(F15), ISBLANK(H15)), "", IFERROR(NETWORKDAYS(F15, H15), "")) -> 16
A16: 45679 | B16: 40432544000147 | C16: =VLOOKUP(B16,Fornecedores!A:B,2,0) -> CLARO SA | D16: EVANDREA | E16: 59931224 | F16: 45661 | G16: 1948.57 | H16: =VLOOKUP(E16&B16,'Conf Oracle'!A:F,6,0) -> #N/A | I16: OC_0007421 | J16: =IF(OR(ISBLANK(F16), ISBLANK(H16)), "", IFERROR(NETWORKDAYS(F16, H16), ""))
A17: 45679 | B17: 00082024000137 | C17: =VLOOKUP(B17,Fornecedores!A:B,2,0) -> COMPANHIA DE SANEAMENTO AMBIENTAL DO DISTRITO FEDERAL | D17: EVANDREA | E17: 00012025 | F17: 45671 | G17: 27216.84 | H17: =VLOOKUP(E17&B17,'Conf Oracle'!A:F,6,0) -> 45686.471 | I17: OC_0007508 | J17: =IF(OR(ISBLANK(F17), ISBLANK(H17)), "", IFERROR(NETWORKDAYS(F17, H17), "")) -> 12
A18: 45679 | B18: 64601925000170 | C18: =VLOOKUP(B18,Fornecedores!A:B,2,0) -> TOUR HOUSE - VIAGENS E TURISMO LTDA. | D18: EVANDREA | E18: 00605596 | F18: 45670 | G18: 20265.73 | H18: =VLOOKUP(E18&B18,'Conf Oracle'!A:F,6,0) -> 45687.638 | I18: Lançado | J18: =IF(OR(ISBLANK(F18), ISBLANK(H18)), "", IFERROR(NETWORKDAYS(F18, H18), "")) -> 14
A19: 45679 | B19: 01092686002366 | C19: =VLOOKUP(B19,Fornecedores!A:B,2,0) -> JOHNSON CONTROLS BE DO BRASIL LTDA | D19: EVANDREA | E19: 00053932 | F19: 45671 | G19: 69907.39 | H19: =VLOOKUP(E19&B19,'Conf Oracle'!A:F,6,0) -> #N/A | I19: Lançado | J19: =IF(OR(ISBLANK(F19), ISBLANK(H19)), "", IFERROR(NETWORKDAYS(F19, H19), ""))
A20: 45679 | B20: 08689801000118 | C20: =VLOOKUP(B20,Fornecedores!A:B,2,0) -> ALERTE AUTOM LEIT RECORT DIAR OFIC LTDA | D20: EVANDREA | E20: 00096621 | F20: 45672 | G20: 1470.18 | H20: =VLOOKUP(E20&B20,'Conf Oracle'!A:F,6,0) -> 45679.738 | J20: =IF(OR(ISBLANK(F20), ISBLANK(H20)), "", IFERROR(NETWORKDAYS(F20, H20), "")) -> 6
A21: 45679 | B21: 59456277000176 | C21: =VLOOKUP(B21,Fornecedores!A:B,2,0) -> ORACLE DO BRASIL SISTEMAS LTDA | D21: EVANDREA | E21: 00063060 | F21: 45672 | G21: 440529.53 | H21: =VLOOKUP(E21&B21,'Conf Oracle'!A:F,6,0) -> 45679.743 | I21: Lançado | J21: =IF(OR(ISBLANK(F21), ISBLANK(H21)), "", IFERROR(NETWORKDAYS(F21, H21), "")) -> 6
A22: 45679 | B22: 21986074000119 | C22: =VLOOKUP(B22,Fornecedores!A:B,2,0) -> PRUDENTIAL DO BRASIL VIDA EM GRUPO S.A. | D22: EVANDREA | E22: 53944679 | F22: 45670 | G22: 972.18 | H22: =VLOOKUP(E22&B22,'Conf Oracle'!A:F,6,0) -> 45680.478 | I22: Lançado | J22: =IF(OR(ISBLANK(F22), ISBLANK(H22)), "", IFERROR(NETWORKDAYS(F22, H22), "")) -> 9
A23: 45679 | B23: 69034668000156 | C23: =VLOOKUP(B23,Fornecedores!A:B,2,0) -> PLUXEE BENEFICIOS BRASIL SA | D23: EVANDREA | E23: 04190916 | F23: 45673 | G23: 609656.86 | H23: =VLOOKUP(E23&B23,'Conf Oracle'!A:F,6,0) -> 45687.54 | J23: =IF(OR(ISBLANK(F23), ISBLANK(H23)), "", IFERROR(NETWORKDAYS(F23, H23), "")) -> 11
A24: 45679 | B24: 69034668000156 | C24: =VLOOKUP(B24,Fornecedores!A:B,2,0) -> PLUXEE BENEFICIOS BRASIL SA | D24: EVANDREA | E24: 04190913 | F24: 45673 | G24: 1054899.1 | H24: =VLOOKUP(E24&B24,'Conf Oracle'!A:F,6,0) -> 45687.537 | J24: =IF(OR(ISBLANK(F24), ISBLANK(H24)), "", IFERROR(NETWORKDAYS(F24, H24), "")) -> 11
A25: 45679 | B25: 34844263000107 | C25: =VLOOKUP(B25,Fornecedores!A:B,2,0) -> ELETROS SAUDE - ASSOCIACAO DE ASSISTENCIA A SAUDE | D25: ISABELA | E25: 00003576 | F25: 45672 | G25: 12831.09 | H25: =VLOOKUP(E25&B25,'Conf Oracle'!A:F,6,0) -> 45680.774 | I25: Lançado | J25: =IF(OR(ISBLANK(F25), ISBLANK(H25)), "", IFERROR(NETWORKDAYS(F25, H25), "")) -> 7
A26: 45679 | B26: 92693118000160 | C26: =VLOOKUP(B26,Fornecedores!A:B,2,0) -> BRADESCO SAUDE SA | D26: EVANDREA | E26: 48918032 | F26: 45665 | G26: 1976316.1 | H26: =VLOOKUP(E26&B26,'Conf Oracle'!A:F,6,0) -> 45681.585 | J26: =IF(OR(ISBLANK(F26), ISBLANK(H26)), "", IFERROR(NETWORKDAYS(F26, H26), "")) -> 13
A27: 45679 | B27: 40015579000180 | C27: =VLOOKUP(B27,Fornecedores!A:B,2,0) -> AVENTIS RENTAL S.A | D27: EVANDREA | E27: 00000004 | F27: 45311 | G27: 15116.88 | H27: =VLOOKUP(E27&B27,'Conf Oracle'!A:F,6,0) -> 45663.541 | I27: NÃO LANÇADA | J27: =IF(OR(ISBLANK(F27), ISBLANK(H27)), "", IFERROR(NETWORKDAYS(F27, H27), "")) -> 251
A28: 45679 | B28: 21948372000114 | C28: =VLOOKUP(B28,Fornecedores!A:B,2,0) -> DATA CENTRE DYNAMICS BRASIL TECNOLOGIAS LTDA | D28: EVANDREA | E28: 00000437 | F28: 45311 | G28: 172900 | H28: =VLOOKUP(E28&B28,'Conf Oracle'!A:F,6,0) -> #N/A | I28: NÃO LANÇADA | J28: =IF(OR(ISBLANK(F28), ISBLANK(H28)), "", IFERROR(NETWORKDAYS(F28, H28), ""))
A29: 45679 | B29: 07751071000175 | C29: =VLOOKUP(B29,Fornecedores!A:B,2,0) -> TELEGESTAO SISTEMAS DE ATEND LTDA | D29: ISABELA | E29: 00000813 | F29: 45658 | G29: 700 | H29: =VLOOKUP(E29&B29,'Conf Oracle'!A:F,6,0) -> 45679.733 | I29: Lançado | J29: =IF(OR(ISBLANK(F29), ISBLANK(H29)), "", IFERROR(NETWORKDAYS(F29, H29), "")) -> 16
A30: 45679 | B30: 26409092000151 | C30: =VLOOKUP(B30,Fornecedores!A:B,2,0) -> SSAMRO SOLUCOES PARA MANUTENCAO INDUSTR | D30: ISABELA | E30: 00023729 | F30: 45659 | G30: 648.76 | H30: =VLOOKUP(E30&B30,'Conf Oracle'!A:F,6,0) -> 45679.726 | I30: Lançado | J30: =IF(OR(ISBLANK(F30), ISBLANK(H30)), "", IFERROR(NETWORKDAYS(F30, H30), "")) -> 15
A31: 45679 | B31: 26409092000151 | C31: =VLOOKUP(B31,Fornecedores!A:B,2,0) -> SSAMRO SOLUCOES PARA MANUTENCAO INDUSTR | D31: ISABELA | E31: 00023742 | F31: 45659 | G31: 648.76 | H31: =VLOOKUP(E31&B31,'Conf Oracle'!A:F,6,0) -> 45679.73 | I31: Lançado | J31: =IF(OR(ISBLANK(F31), ISBLANK(H31)), "", IFERROR(NETWORKDAYS(F31, H31), "")) -> 15
A32: 45679 | B32: 26409092000151 | C32: =VLOOKUP(B32,Fornecedores!A:B,2,0) -> SSAMRO SOLUCOES PARA MANUTENCAO INDUSTR | D32: ISABELA | E32: 00023743 | F32: 45659 | G32: 648.76 | H32: =VLOOKUP(E32&B32,'Conf Oracle'!A:F,6,0) -> 45679.727 | I32: Lançado | J32: =IF(OR(ISBLANK(F32), ISBLANK(H32)), "", IFERROR(NETWORKDAYS(F32, H32), "")) -> 15
A33: 45679 | B33: 26409092000151 | C33: =VLOOKUP(B33,Fornecedores!A:B,2,0) -> SSAMRO SOLUCOES PARA MANUTENCAO INDUSTR | D33: ISABELA | E33: 00023751 | F33: 45659 | G33: 648.76 | H33: =VLOOKUP(E33&B33,'Conf Oracle'!A:F,6,0) -> 45679.729 | I33: Lançado | J33: =IF(OR(ISBLANK(F33), ISBLANK(H33)), "", IFERROR(NETWORKDAYS(F33, H33), "")) -> 15
A34: 45679 | B34: 64601925000502 | C34: =VLOOKUP(B34,Fornecedores!A:B,2,0) -> Tour House Viagens e Turismo LTDA-THV - Bragança | D34: ISABELA | E34: 00603212 | F34: 45663 | G34: 21748.7 | H34: =VLOOKUP(E34&B34,'Conf Oracle'!A:F,6,0) -> #N/A | I34: Lançado | J34: =IF(OR(ISBLANK(F34), ISBLANK(H34)), "", IFERROR(NETWORKDAYS(F34, H34), ""))
A35: 45679 | B35: 04359325000116 | C35: =VLOOKUP(B35,Fornecedores!A:B,2,0) -> MORAES PITOMBO ADVOGADOS | D35: ISABELA | E35: 00019572 | F35: 45659 | G35: 7500 | H35: =VLOOKUP(E35&B35,'Conf Oracle'!A:F,6,0) -> 45679.736 | I35: Lançado | J35: =IF(OR(ISBLANK(F35), ISBLANK(H35)), "", IFERROR(NETWORKDAYS(F35, H35), "")) -> 15
A36: 45679 | B36: 02593165000140 | C36: =VLOOKUP(B36,Fornecedores!A:B,2,0) -> GARTNER DO BRASIL SERV DE PESQUISAS LTDA | D36: ISABELA | E36: 00045139 | F36: 45659 | G36: 489649 | H36: =VLOOKUP(E36&B36,'Conf Oracle'!A:F,6,0) -> 45680.743 | I36: Lançado | J36: =IF(OR(ISBLANK(F36), ISBLANK(H36)), "", IFERROR(NETWORKDAYS(F36, H36), "")) -> 16
A37: 45679 | B37: 64601925000502 | C37: =VLOOKUP(B37,Fornecedores!A:B,2,0) -> Tour House Viagens e Turismo LTDA-THV - Bragança | D37: ISABELA | E37: 00002561 | F37: 45660 | G37: 3147.94 | H37: =VLOOKUP(E37&B37,'Conf Oracle'!A:F,6,0) -> #N/A | I37: Lançado | J37: =IF(OR(ISBLANK(F37), ISBLANK(H37)), "", IFERROR(NETWORKDAYS(F37, H37), ""))
A38: 45679 | B38: 02593165000140 | C38: =VLOOKUP(B38,Fornecedores!A:B,2,0) -> GARTNER DO BRASIL SERV DE PESQUISAS LTDA | D38: JESSY | E38: 00045138 | F38: 45659 | G38: 1507150 | H38: =VLOOKUP(E38&B38,'Conf Oracle'!A:F,6,0) -> 45681.678 | I38: OC_0007372 | J38: =IF(OR(ISBLANK(F38), ISBLANK(H38)), "", IFERROR(NETWORKDAYS(F38, H38), "")) -> 17
A39: 45679 | B39: 08736011000731 | C39: =VLOOKUP(B39,Fornecedores!A:B,2,0) -> GRAN COFFEE COMERCIO LOCACAO SERVICOS SA | D39: EVANDREA | E39: 00001776 | F39: 45677 | G39: 1958 | H39: =VLOOKUP(E39&B39,'Conf Oracle'!A:F,6,0) -> 45680.739 | J39: =IF(OR(ISBLANK(F39), ISBLANK(H39)), "", IFERROR(NETWORKDAYS(F39, H39), "")) -> 4
A40: 45679 | B40: 35272126000108 | C40: =VLOOKUP(B40,Fornecedores!A:B,2,0) -> RECOLD REFRIGERACAO S/C EIRELI | D40: EVANDREA | E40: 00001432 | F40: 45677 | G40: 4600 | H40: =VLOOKUP(E40&B40,'Conf Oracle'!A:F,6,0) -> 45679.741 | J40: =IF(OR(ISBLANK(F40), ISBLANK(H40)), "", IFERROR(NETWORKDAYS(F40, H40), "")) -> 3
A41: 45679 | B41: 58119199000151 | C41: =VLOOKUP(B41,Fornecedores!A:B,2,0) -> ODONTOPREV SA | D41: ISABELA | E41: 49111714 | F41: 45689 | G41: 132714.48 | H41: =VLOOKUP(E41&B41,'Conf Oracle'!A:F,6,0) -> 45681.574 | I41: Lançado | J41: =IF(OR(ISBLANK(F41), ISBLANK(H41)), "", IFERROR(NETWORKDAYS(F41, H41), "")) -> -6
A42: 45679 | B42: 69034668000156 | C42: =VLOOKUP(B42,Fornecedores!A:B,2,0) -> PLUXEE BENEFICIOS BRASIL SA | D42: ISABELA | E42: 04196643 | F42: 45674 | G42: 3000.6 | H42: =VLOOKUP(E42&B42,'Conf Oracle'!A:F,6,0) -> 45688.75 | J42: =IF(OR(ISBLANK(F42), ISBLANK(H42)), "", IFERROR(NETWORKDAYS(F42, H42), "")) -> 11
A43: 45679 | B43: 69034668000156 | C43: =VLOOKUP(B43,Fornecedores!A:B,2,0) -> PLUXEE BENEFICIOS BRASIL SA | D43: ISABELA | E43: 04196644 | F43: 45674 | G43: 3000.6 | H43: =VLOOKUP(E43&B43,'Conf Oracle'!A:F,6,0) -> 45688.717 | J43: =IF(OR(ISBLANK(F43), ISBLANK(H43)), "", IFERROR(NETWORKDAYS(F43, H43), "")) -> 11
A44: 45679 | B44: 69034668000156 | C44: =VLOOKUP(B44,Fornecedores!A:B,2,0) -> PLUXEE BENEFICIOS BRASIL SA | D44: ISABELA | E44: 04196645 | F44: 45674 | G44: 1382.43 | H44: =VLOOKUP(E44&B44,'Conf Oracle'!A:F,6,0) -> 45688.699 | J44: =IF(OR(ISBLANK(F44), ISBLANK(H44)), "", IFERROR(NETWORKDAYS(F44, H44), "")) -> 11
A45: 45679 | B45: 69034668000156 | C45: =VLOOKUP(B45,Fornecedores!A:B,2,0) -> PLUXEE BENEFICIOS BRASIL SA | D45: ISABELA | E45: 04196646 | F45: 45674 | G45: 1382.43 | H45: =VLOOKUP(E45&B45,'Conf Oracle'!A:F,6,0) -> 45688.673 | J45: =IF(OR(ISBLANK(F45), ISBLANK(H45)), "", IFERROR(NETWORKDAYS(F45, H45), "")) -> 11
A46: 45679 | B46: 64601925000502 | C46: =VLOOKUP(B46,Fornecedores!A:B,2,0) -> Tour House Viagens e Turismo LTDA-THV - Bragança | D46: ISABELA | E46: 00606655 | F46: 45677 | G46: 31660.7 | H46: =VLOOKUP(E46&B46,'Conf Oracle'!A:F,6,0) -> #N/A | I46: Lançado | J46: =IF(OR(ISBLANK(F46), ISBLANK(H46)), "", IFERROR(NETWORKDAYS(F46, H46), ""))
A47: 45679 | B47: 05666393000190 | C47: =VLOOKUP(B47,Fornecedores!A:B,2,0) -> SUPREMA LOCADORA E TURISMO LTDA EPP | D47: ISABELA | E47: 00000585 | F47: 45679 | G47: 1762.52 | H47: =VLOOKUP(E47&B47,'Conf Oracle'!A:F,6,0) -> 45680.787 | J47: =IF(OR(ISBLANK(F47), ISBLANK(H47)), "", IFERROR(NETWORKDAYS(F47, H47), "")) -> 2
A48: 45679 | B48: 01933257000169 | C48: =VLOOKUP(B48,Fornecedores!A:B,2,0) -> FUTURE TECHNOLOGIES INFORMATICA LTDA | D48: JESSY | E48: 00004248 | F48: 45659 | G48: 6450 | H48: =VLOOKUP(E48&B48,'Conf Oracle'!A:F,6,0) -> 45688.763 | I48: OC_0007607 | J48: =IF(OR(ISBLANK(F48), ISBLANK(H48)), "", IFERROR(NETWORKDAYS(F48, H48), "")) -> 22
A49: 45679 | B49: 57623555000107 | C49: =VLOOKUP(B49,Fornecedores!A:B,2,0) -> MAGICCOMP ENG E SERV DE INFORMATICA LTDA | D49: JESSY | E49: 00055370 | F49: 45659 | G49: 23587.74 | H49: =VLOOKUP(E49&B49,'Conf Oracle'!A:F,6,0) -> 45688.746 | I49: OC_0007600 | J49: =IF(OR(ISBLANK(F49), ISBLANK(H49)), "", IFERROR(NETWORKDAYS(F49, H49), "")) -> 22
A50: 45679 | B50: 57623555000107 | C50: =VLOOKUP(B50,Fornecedores!A:B,2,0) -> MAGICCOMP ENG E SERV DE INFORMATICA LTDA | D50: JESSY | E50: 00055367 | F50: 45659 | G50: 26357.42 | H50: =VLOOKUP(E50&B50,'Conf Oracle'!A:F,6,0) -> #N/A | I50: OC_0007604 | J50: =IF(OR(ISBLANK(F50), ISBLANK(H50)), "", IFERROR(NETWORKDAYS(F50, H50), ""))
A51: 45679 | B51: 57623555000107 | C51: =VLOOKUP(B51,Fornecedores!A:B,2,0) -> MAGICCOMP ENG E SERV DE INFORMATICA LTDA | D51: JESSY | E51: 00055368 | F51: 45659 | G51: 26357.42 | H51: =VLOOKUP(E51&B51,'Conf Oracle'!A:F,6,0) -> #N/A | I51: OC_0007605 | J51: =IF(OR(ISBLANK(F51), ISBLANK(H51)), "", IFERROR(NETWORKDAYS(F51, H51), ""))
A52: 45679 | B52: 57623555000107 | C52: =VLOOKUP(B52,Fornecedores!A:B,2,0) -> MAGICCOMP ENG E SERV DE INFORMATICA LTDA | D52: JESSY | E52: 00055369 | F52: 45659 | G52: 23587.74 | H52: =VLOOKUP(E52&B52,'Conf Oracle'!A:F,6,0) -> 45688.749 | I52: OC_0007602 | J52: =IF(OR(ISBLANK(F52), ISBLANK(H52)), "", IFERROR(NETWORKDAYS(F52, H52), "")) -> 22
A53: 45679 | B53: 21356354000143 | C53: =VLOOKUP(B53,Fornecedores!A:B,2,0) -> POPULOS TECNOLOGIA LTDA | D53: JESSY | E53: 00002457 | F53: 45659 | G53: 3118.52 | H53: =VLOOKUP(E53&B53,'Conf Oracle'!A:F,6,0) -> #N/A | I53: OC_0007611 | J53: =IF(OR(ISBLANK(F53), ISBLANK(H53)), "", IFERROR(NETWORKDAYS(F53, H53), ""))
A54: 45679 | B54: 28268233000350 | C54: =VLOOKUP(B54,Fornecedores!A:B,2,0) -> TD SYNNEX BRASIL LTDA | D54: JESSY | E54: 00005336 | F54: 45659 | G54: 121028.4 | H54: =VLOOKUP(E54&B54,'Conf Oracle'!A:F,6,0) -> 45684.469 | I54: OC_0007547 | J54: =IF(OR(ISBLANK(F54), ISBLANK(H54)), "", IFERROR(NETWORKDAYS(F54, H54), "")) -> 18
A55: 45679 | B55: 25012398000107 | C55: =VLOOKUP(B55,Fornecedores!A:B,2,0) -> GOOGLE CLOUD BRASIL COMPUTAÇÃO E SERVICOS DE DADOS LTDA | D55: JESSY | E55: 11849070 | F55: 45659 | G55: 793.35 | H55: =VLOOKUP(E55&B55,'Conf Oracle'!A:F,6,0) -> 45680.621 | I55: OC_0007377 | J55: =IF(OR(ISBLANK(F55), ISBLANK(H55)), "", IFERROR(NETWORKDAYS(F55, H55), "")) -> 16
A56: 45679 | B56: 28268233000784 | C56: =VLOOKUP(B56,Fornecedores!A:B,2,0) -> TD SYNNEX BRASIL LTDA | D56: JESSY | E56: 00583694 | F56: 45659 | G56: 3303913.7 | H56: =VLOOKUP(E56&B56,'Conf Oracle'!A:F,6,0) -> 45684.449 | I56: OC_0007408 | J56: =IF(OR(ISBLANK(F56), ISBLANK(H56)), "", IFERROR(NETWORKDAYS(F56, H56), "")) -> 18
A57: 45679 | B57: 21515602000151 | C57: =VLOOKUP(B57,Fornecedores!A:B,2,0) -> CENARIO RJ TECNOLOGIA EM AUDIO E VIDEO LTDA | D57: JESSY | E57: 00001181 | F57: 45660 | G57: 7200 | H57: =VLOOKUP(E57&B57,'Conf Oracle'!A:F,6,0) -> 45688.589 | I57: OC_0007427 | J57: =IF(OR(ISBLANK(F57), ISBLANK(H57)), "", IFERROR(NETWORKDAYS(F57, H57), "")) -> 21
A58: 45679 | B58: 89237911028908 | C58: =VLOOKUP(B58,Fornecedores!A:B,2,0) -> GLOBAL DISTRIBUICAO DE BENS DE CONSUMO L | D58: JESSY | E58: 00000058 | F58: 45663 | G58: 2398 | H58: =VLOOKUP(E58&B58,'Conf Oracle'!A:F,6,0) -> #N/A | I58: Entega indevida- o fornecedor vai coletar o material | J58: =IF(OR(ISBLANK(F58), ISBLANK(H58)), "", IFERROR(NETWORKDAYS(F58, H58), ""))
A59: 45679 | B59: 09554428000150 | C59: =VLOOKUP(B59,Fornecedores!A:B,2,0) -> STAEFA SERVICOS DE MANUTENCAO PREDIAL LTDA | D59: JESSY | E59: 00001421 | F59: 45663 | G59: 41603.74 | H59: =VLOOKUP(E59&B59,'Conf Oracle'!A:F,6,0) -> 45681.602 | I59: OC_0007401 | J59: =IF(OR(ISBLANK(F59), ISBLANK(H59)), "", IFERROR(NETWORKDAYS(F59, H59), "")) -> 15
... A95: 45681 | B95: 07668845000107 | C95: =VLOOKUP(B95,Fornecedores!A:B,2,0) -> FERNANDO ANTONIO ZILIOTTO GOMES RES EPP | D95: GUILHERME | E95: 00000632 | F95: 45671 | G95: 6000 | H95: =VLOOKUP(E95&B95,'Conf Oracle'!A:F,6,0) -> 45685.438 | I95: lançar | J95: =IF(OR(ISBLANK(F95), ISBLANK(H95)), "", IFERROR(NETWORKDAYS(F95, H95), "")) -> 11
A96: 45684 | B96: 00497373000110 | C96: =VLOOKUP(B96,Fornecedores!A:B,2,0) -> SKY SERVICOS DE BANDA LARGA LTDA | D96: EVANDREA | E96: 80332411 | F96: 45669 | G96: 315.88 | H96: =VLOOKUP(E96&B96,'Conf Oracle'!A:F,6,0) -> 45686.734 | J96: =IF(OR(ISBLANK(F96), ISBLANK(H96)), "", IFERROR(NETWORKDAYS(F96, H96), "")) -> 13
A97: 45684 | B97: 43965130000171 | C97: =VLOOKUP(B97,Fornecedores!A:B,2,0) -> AGUAS CLARAS GASTRONOMIA E EVENTOS LTDA | D97: EVANDREA | E97: 00001054 | F97: 45680 | G97: 2400 | H97: =VLOOKUP(E97&B97,'Conf Oracle'!A:F,6,0) -> #N/A | I97: NÃO LANÇADA | J97: =IF(OR(ISBLANK(F97), ISBLANK(H97)), "", IFERROR(NETWORKDAYS(F97, H97), ""))
A98: 45684 | B98: 04365103000106 | C98: =VLOOKUP(B98,Fornecedores!A:B,2,0) -> UP CHEF2 COMERCIO E SERVICOS LTDA ME | D98: EVANDREA | E98: 00000364 | F98: 45681 | G98: 7778.94 | H98: =VLOOKUP(E98&B98,'Conf Oracle'!A:F,6,0) -> #N/A | I98: NÃO LANÇADA | J98: =IF(OR(ISBLANK(F98), ISBLANK(H98)), "", IFERROR(NETWORKDAYS(F98, H98), ""))
A99: 45684 | B99: 01731177000120 | C99: =VLOOKUP(B99,Fornecedores!A:B,2,0) -> RUSSEL REYNOLDS ASSOCIATES LTDA | D99: EVANDREA | E99: 00007339 | F99: 45681 | G99: 100000 | H99: =VLOOKUP(E99&B99,'Conf Oracle'!A:F,6,0) -> #N/A | I99: NÃO LANÇADA | J99: =IF(OR(ISBLANK(F99), ISBLANK(H99)), "", IFERROR(NETWORKDAYS(F99, H99), ""))
A100: 45684 | B100: 23412247000110 | C100: =VLOOKUP(B100,Fornecedores!A:B,2,0) -> AMAZON AWS SERVICOS BRASIL LTDA | D100: INGRID | E100: 88689225 | F100: 45658 | G100: 612910.07 | H100: =VLOOKUP(E100&B100,'Conf Oracle'!A:F,6,0) -> #N/A | J100: =IF(OR(ISBLANK(F100), ISBLANK(H100)), "", IFERROR(NETWORKDAYS(F100, H100), ""))
A101: 45684 | B101: 23412247000110 | C101: =VLOOKUP(B101,Fornecedores!A:B,2,0) -> AMAZON AWS SERVICOS BRASIL LTDA | D101: INGRID | E101: 03886866 | F101: 45658 | G101: 612910.41 | H101: =VLOOKUP(E101&B101,'Conf Oracle'!A:F,6,0) -> 45681.753 | J101: =IF(OR(ISBLANK(F101), ISBLANK(H101)), "", IFERROR(NETWORKDAYS(F101, H101), "")) -> 18
A102: 45684 | B102: 23412247000110 | C102: =VLOOKUP(B102,Fornecedores!A:B,2,0) -> AMAZON AWS SERVICOS BRASIL LTDA | D102: INGRID | E102: 88828241 | F102: 45658 | G102: 0.08 | H102: =VLOOKUP(E102&B102,'Conf Oracle'!A:F,6,0) -> #N/A | J102: =IF(OR(ISBLANK(F102), ISBLANK(H102)), "", IFERROR(NETWORKDAYS(F102, H102), ""))
A103: 45684 | B103: 23412247000110 | C103: =VLOOKUP(B103,Fornecedores!A:B,2,0) -> AMAZON AWS SERVICOS BRASIL LTDA | D103: INGRID | E103: 88934817 | F103: 45658 | G103: 59766.53 | H103: =VLOOKUP(E103&B103,'Conf Oracle'!A:F,6,0) -> #N/A | J103: =IF(OR(ISBLANK(F103), ISBLANK(H103)), "", IFERROR(NETWORKDAYS(F103, H103), ""))
A104: 45684 | B104: 23412247000110 | C104: =VLOOKUP(B104,Fornecedores!A:B,2,0) -> AMAZON AWS SERVICOS BRASIL LTDA | D104: INGRID | E104: 03889689 | F104: 45658 | G104: 59766.61 | H104: =VLOOKUP(E104&B104,'Conf Oracle'!A:F,6,0) -> 45681.725 | J104: =IF(OR(ISBLANK(F104), ISBLANK(H104)), "", IFERROR(NETWORKDAYS(F104, H104), "")) -> 18
A105: 45684 | B105: 00000463921926 | C105: =VLOOKUP(B105,Fornecedores!A:B,2,0) -> Realtimeboard Inc dba Miro | D105: INGRID | E105: 02797949 | F105: 45667 | G105: 8000 | H105: =VLOOKUP(E105&B105,'Conf Oracle'!A:F,6,0) -> #N/A | I105: LANÇADA | J105: =IF(OR(ISBLANK(F105), ISBLANK(H105)), "", IFERROR(NETWORKDAYS(F105, H105), ""))
A106: 45684 | B106: 02558157013574 | C106: =VLOOKUP(B106,Fornecedores!A:B,2,0) -> TELEFONICA BRASIL SA | D106: INGRID | E106: 00255470 | F106: 45664 | G106: 2522.64 | H106: =VLOOKUP(E106&B106,'Conf Oracle'!A:F,6,0) -> #N/A | J106: =IF(OR(ISBLANK(F106), ISBLANK(H106)), "", IFERROR(NETWORKDAYS(F106, H106), ""))
A107: 45684 | B107: 02558157013574 | C107: =VLOOKUP(B107,Fornecedores!A:B,2,0) -> TELEFONICA BRASIL SA | D107: INGRID | E107: 00258087 | F107: 45664 | G107: 1657.98 | H107: =VLOOKUP(E107&B107,'Conf Oracle'!A:F,6,0) -> #N/A | J107: =IF(OR(ISBLANK(F107), ISBLANK(H107)), "", IFERROR(NETWORKDAYS(F107, H107), ""))
A108: 45684 | B108: 02558157013574 | C108: =VLOOKUP(B108,Fornecedores!A:B,2,0) -> TELEFONICA BRASIL SA | D108: INGRID | E108: 00258932 | F108: 45664 | G108: 3167.16 | H108: =VLOOKUP(E108&B108,'Conf Oracle'!A:F,6,0) -> #N/A | J108: =IF(OR(ISBLANK(F108), ISBLANK(H108)), "", IFERROR(NETWORKDAYS(F108, H108), ""))
A109: 45684 | B109: 02558157013574 | C109: =VLOOKUP(B109,Fornecedores!A:B,2,0) -> TELEFONICA BRASIL SA | D109: INGRID | E109: 00256792 | F109: 45664 | G109: 1581.56 | H109: =VLOOKUP(E109&B109,'Conf Oracle'!A:F,6,0) -> #N/A | J109: =IF(OR(ISBLANK(F109), ISBLANK(H109)), "", IFERROR(NETWORKDAYS(F109, H109), ""))
A110: 45684 | B110: 02558157013574 | C110: =VLOOKUP(B110,Fornecedores!A:B,2,0) -> TELEFONICA BRASIL SA | D110: INGRID | E110: 00257683 | F110: 45664 | G110: 180 | H110: =VLOOKUP(E110&B110,'Conf Oracle'!A:F,6,0) -> #N/A | J110: =IF(OR(ISBLANK(F110), ISBLANK(H110)), "", IFERROR(NETWORKDAYS(F110, H110), ""))
A111: 45684 | B111: 02558157013574 | C111: =VLOOKUP(B111,Fornecedores!A:B,2,0) -> TELEFONICA BRASIL SA | D111: INGRID | E111: 00253933 | F111: 45664 | G111: 915.86 | H111: =VLOOKUP(E111&B111,'Conf Oracle'!A:F,6,0) -> #N/A | J111: =IF(OR(ISBLANK(F111), ISBLANK(H111)), "", IFERROR(NETWORKDAYS(F111, H111), ""))
A112: 45684 | B112: 02558157013574 | C112: =VLOOKUP(B112,Fornecedores!A:B,2,0) -> TELEFONICA BRASIL SA | D112: INGRID | E112: 00254553 | F112: 45664 | G112: 180 | H112: =VLOOKUP(E112&B112,'Conf Oracle'!A:F,6,0) -> #N/A | J112: =IF(OR(ISBLANK(F112), ISBLANK(H112)), "", IFERROR(NETWORKDAYS(F112, H112), ""))
A113: 45684 | B113: 02558157013574 | C113: =VLOOKUP(B113,Fornecedores!A:B,2,0) -> TELEFONICA BRASIL SA | D113: INGRID | E113: 00258562 | F113: 45664 | G113: 1080 | H113: =VLOOKUP(E113&B113,'Conf Oracle'!A:F,6,0) -> #N/A | J113: =IF(OR(ISBLANK(F113), ISBLANK(H113)), "", IFERROR(NETWORKDAYS(F113, H113), ""))
A114: 45684 | B114: 02558157013574 | C114: =VLOOKUP(B114,Fornecedores!A:B,2,0) -> TELEFONICA BRASIL SA | D114: INGRID | E114: 00261052 | F114: 45664 | G114: 882.79 | H114: =VLOOKUP(E114&B114,'Conf Oracle'!A:F,6,0) -> #N/A | J114: =IF(OR(ISBLANK(F114), ISBLANK(H114)), "", IFERROR(NETWORKDAYS(F114, H114), ""))
A115: 45684 | B115: 02558157013574 | C115: =VLOOKUP(B115,Fornecedores!A:B,2,0) -> TELEFONICA BRASIL SA | D115: INGRID | E115: 00253984 | F115: 45664 | G115: 360 | H115: =VLOOKUP(E115&B115,'Conf Oracle'!A:F,6,0) -> #N/A | J115: =IF(OR(ISBLANK(F115), ISBLANK(H115)), "", IFERROR(NETWORKDAYS(F115, H115), ""))
A116: 45684 | B116: 02558157013574 | C116: =VLOOKUP(B116,Fornecedores!A:B,2,0) -> TELEFONICA BRASIL SA | D116: INGRID | E116: 00255067 | F116: 45664 | G116: 1110.62 | H116: =VLOOKUP(E116&B116,'Conf Oracle'!A:F,6,0) -> #N/A | J116: =IF(OR(ISBLANK(F116), ISBLANK(H116)), "", IFERROR(NETWORKDAYS(F116, H116), ""))
A117: 45684 | B117: 4950715139 | C117: =VLOOKUP(B117,Fornecedores!A:B,2,0) -> BIZAGI LATAM SAS | D117: INGRID | E117: 00000476 | F117: 45667 | G117: 100406 | H117: =VLOOKUP(E117&B117,'Conf Oracle'!A:F,6,0) -> #N/A | I117: LANÇADA | J117: =IF(OR(ISBLANK(F117), ISBLANK(H117)), "", IFERROR(NETWORKDAYS(F117, H117), ""))
A118: 45684 | B118: 02558157000162 | C118: =VLOOKUP(B118,Fornecedores!A:B,2,0) -> TELEFONICA BRASIL SA | D118: INGRID | F118: 45663 | G118: 1870.82 | H118: =VLOOKUP(E118&B118,'Conf Oracle'!A:F,6,0) -> #N/A | J118: =IF(OR(ISBLANK(F118), ISBLANK(H118)), "", IFERROR(NETWORKDAYS(F118, H118), ""))
A119: 45684 | B119: 02558157000162 | C119: =VLOOKUP(B119,Fornecedores!A:B,2,0) -> TELEFONICA BRASIL SA | D119: INGRID | F119: 45663 | G119: 13264 | H119: =VLOOKUP(E119&B119,'Conf Oracle'!A:F,6,0) -> #N/A | J119: =IF(OR(ISBLANK(F119), ISBLANK(H119)), "", IFERROR(NETWORKDAYS(F119, H119), ""))
A120: 45684 | B120: 02558157000162 | C120: =VLOOKUP(B120,Fornecedores!A:B,2,0) -> TELEFONICA BRASIL SA | D120: INGRID | F120: 45663 | G120: 19118.88 | H120: =VLOOKUP(E120&B120,'Conf Oracle'!A:F,6,0) -> #N/A | J120: =IF(OR(ISBLANK(F120), ISBLANK(H120)), "", IFERROR(NETWORKDAYS(F120, H120), ""))
A121: 45684 | B121: 02558157000162 | C121: =VLOOKUP(B121,Fornecedores!A:B,2,0) -> TELEFONICA BRASIL SA | D121: INGRID | F121: 45663 | G121: 337.86 | H121: =VLOOKUP(E121&B121,'Conf Oracle'!A:F,6,0) -> #N/A | J121: =IF(OR(ISBLANK(F121), ISBLANK(H121)), "", IFERROR(NETWORKDAYS(F121, H121), ""))
A122: 45684 | B122: 02421421000111 | C122: =VLOOKUP(B122,Fornecedores!A:B,2,0) -> TIM SA | D122: INGRID | E122: 57916934 | F122: 45633 | G122: 32.45 | H122: =VLOOKUP(E122&B122,'Conf Oracle'!A:F,6,0) -> #N/A | J122: =IF(OR(ISBLANK(F122), ISBLANK(H122)), "", IFERROR(NETWORKDAYS(F122, H122), ""))
A123: 45684 | B123: 02421421000111 | C123: =VLOOKUP(B123,Fornecedores!A:B,2,0) -> TIM SA | D123: INGRID | E123: 57916933 | F123: 45633 | G123: 32.45 | H123: =VLOOKUP(E123&B123,'Conf Oracle'!A:F,6,0) -> #N/A | J123: =IF(OR(ISBLANK(F123), ISBLANK(H123)), "", IFERROR(NETWORKDAYS(F123, H123), ""))
A124: 45684 | B124: 02408485000182 | C124: =VLOOKUP(B124,Fornecedores!A:B,2,0) -> MULTIVIS BRASIL LTDA | D124: INGRID | E124: 00002475 | F124: 45677 | G124: 76829.38 | H124: =VLOOKUP(E124&B124,'Conf Oracle'!A:F,6,0) -> #N/A | J124: =IF(OR(ISBLANK(F124), ISBLANK(H124)), "", IFERROR(NETWORKDAYS(F124, H124), ""))
A125: 45684 | B125: 00593850000221 | C125: =VLOOKUP(B125,Fornecedores!A:B,2,0) -> RERUM ENGENHARIA DE SISTEMAS LTDA | D125: INGRID | E125: 00000641 | F125: 45678 | G125: 41287.84 | H125: =VLOOKUP(E125&B125,'Conf Oracle'!A:F,6,0) -> #N/A | J125: =IF(OR(ISBLANK(F125), ISBLANK(H125)), "", IFERROR(NETWORKDAYS(F125, H125), ""))
A126: 45684 | B126: 00593850000221 | C126: =VLOOKUP(B126,Fornecedores!A:B,2,0) -> RERUM ENGENHARIA DE SISTEMAS LTDA | D126: INGRID | E126: 00000642 | F126: 45678 | G126: 41287.84 | H126: =VLOOKUP(E126&B126,'Conf Oracle'!A:F,6,0) -> #N/A | J126: =IF(OR(ISBLANK(F126), ISBLANK(H126)), "", IFERROR(NETWORKDAYS(F126, H126), ""))
A127: 45684 | B127: 00593850000221 | C127: =VLOOKUP(B127,Fornecedores!A:B,2,0) -> RERUM ENGENHARIA DE SISTEMAS LTDA | D127: INGRID | E127: 00000643 | F127: 45678 | G127: 91040.78 | H127: =VLOOKUP(E127&B127,'Conf Oracle'!A:F,6,0) -> #N/A | J127: =IF(OR(ISBLANK(F127), ISBLANK(H127)), "", IFERROR(NETWORKDAYS(F127, H127), ""))
A128: 45684 | B128: 01768873000101 | C128: =VLOOKUP(B128,Fornecedores!A:B,2,0) -> AMCOM SISTEMAS DE INFORMACAO SA | D128: INGRID | E128: 00018928 | F128: 45680 | G128: 52360 | H128: =VLOOKUP(E128&B128,'Conf Oracle'!A:F,6,0) -> #N/A | J128: =IF(OR(ISBLANK(F128), ISBLANK(H128)), "", IFERROR(NETWORKDAYS(F128, H128), ""))
A129: 45684 | B129: 01768873000101 | C129: =VLOOKUP(B129,Fornecedores!A:B,2,0) -> AMCOM SISTEMAS DE INFORMACAO SA | D129: INGRID | E129: 00018929 | F129: 45680 | G129: 157250 | H129: =VLOOKUP(E129&B129,'Conf Oracle'!A:F,6,0) -> #N/A | J129: =IF(OR(ISBLANK(F129), ISBLANK(H129)), "", IFERROR(NETWORKDAYS(F129, H129), ""))
A130: 45684 | B130: 01768873000101 | C130: =VLOOKUP(B130,Fornecedores!A:B,2,0) -> AMCOM SISTEMAS DE INFORMACAO SA | D130: INGRID | E130: 00018930 | F130: 45680 | G130: 186150 | H130: =VLOOKUP(E130&B130,'Conf Oracle'!A:F,6,0) -> #N/A | J130: =IF(OR(ISBLANK(F130), ISBLANK(H130)), "", IFERROR(NETWORKDAYS(F130, H130), ""))
A131: 45684 | B131: 01768873000101 | C131: =VLOOKUP(B131,Fornecedores!A:B,2,0) -> AMCOM SISTEMAS DE INFORMACAO SA | D131: INGRID | E131: 00018931 | F131: 45680 | G131: 58480 | H131: =VLOOKUP(E131&B131,'Conf Oracle'!A:F,6,0) -> #N/A | J131: =IF(OR(ISBLANK(F131), ISBLANK(H131)), "", IFERROR(NETWORKDAYS(F131, H131), ""))
A132: 45684 | B132: 01768873000101 | C132: =VLOOKUP(B132,Fornecedores!A:B,2,0) -> AMCOM SISTEMAS DE INFORMACAO SA | D132: INGRID | E132: 00018932 | F132: 45680 | G132: 134300 | H132: =VLOOKUP(E132&B132,'Conf Oracle'!A:F,6,0) -> #N/A | J132: =IF(OR(ISBLANK(F132), ISBLANK(H132)), "", IFERROR(NETWORKDAYS(F132, H132), ""))
A133: 45684 | B133: 01768873000101 | C133: =VLOOKUP(B133,Fornecedores!A:B,2,0) -> AMCOM SISTEMAS DE INFORMACAO SA | D133: INGRID | E133: 00018933 | F133: 45680 | G133: 52700 | H133: =VLOOKUP(E133&B133,'Conf Oracle'!A:F,6,0) -> #N/A | J133: =IF(OR(ISBLANK(F133), ISBLANK(H133)), "", IFERROR(NETWORKDAYS(F133, H133), ""))
... A138: 45684 | B138: 87169900001389 | C138: =VLOOKUP(B138,Fornecedores!A:B,2,0) -> GRABER SISTEMAS DE SEGURANCA LTDA | D138: ISABELA | E138: 00001309 | F138: 45681 | G138: 111691.37 | H138: =VLOOKUP(E138&B138,'Conf Oracle'!A:F,6,0) -> 45681.706 | J138: =IF(OR(ISBLANK(F138), ISBLANK(H138)), "", IFERROR(NETWORKDAYS(F138, H138), "")) -> 1
A139: 45684 | B139: 01092686002366 | C139: =VLOOKUP(B139,Fornecedores!A:B,2,0) -> JOHNSON CONTROLS BE DO BRASIL LTDA | D139: ISABELA | E139: 00054124 | F139: 45681 | G139: 35889.87 | H139: =VLOOKUP(E139&B139,'Conf Oracle'!A:F,6,0) -> #N/A | I139: CANCELADA | J139: =IF(OR(ISBLANK(F139), ISBLANK(H139)), "", IFERROR(NETWORKDAYS(F139, H139), ""))
A140: 45684 | B140: 44591001000123 | C140: =VLOOKUP(B140,Fornecedores!A:B,2,0) -> EMERSON TANIGAWA TUBONI | D140: ISABELA | E140: 02025771 | F140: 45681 | G140: 3274.68 | H140: =VLOOKUP(E140&B140,'Conf Oracle'!A:F,6,0) -> #N/A | I140: Lançado | J140: =IF(OR(ISBLANK(F140), ISBLANK(H140)), "", IFERROR(NETWORKDAYS(F140, H140), ""))
...

Sheet Controle de NF - Julho 
A2: Mês | B2: CNPJ | C2: Fornecedor | D2: Gestor Adm | E2: NF | F2: Emissão da NF | G2: Valor da NF | H2: Conferência | I2: Observação | J2: SLA
A3: 45846 | B3: 19427033000140 | C3: =VLOOKUP(B3,Fornecedores!A:B,2,0) -> ARQUIVEI SERVICOS ON LINE LTDA | D3: Evandrea | E3: 00492094 | F3: 45839 | G3: 2600 | H3: =VLOOKUP(E3&B3,'Conf Oracle'!A:F,6,0) -> 45849.549 | I3: LANÇADO | J3: =IF(OR(ISBLANK(F3), ISBLANK(H3)), "", IFERROR(NETWORKDAYS(F3, H3), "")) -> 9
A4: 45846 | B4: 16554325000156 | C4: =VLOOKUP(B4,Fornecedores!A:B,2,0) -> AMBIENTE VERDE RESIDUOS LTDA | D4: Evandrea | E4: 00001098 | F4: 45839 | G4: 2490 | H4: =VLOOKUP(E4&B4,'Conf Oracle'!A:F,6,0) -> 45849.665 | I4: LANÇADO | J4: =IF(OR(ISBLANK(F4), ISBLANK(H4)), "", IFERROR(NETWORKDAYS(F4, H4), "")) -> 9
A5: 45846 | B5: 16554325000156 | C5: =VLOOKUP(B5,Fornecedores!A:B,2,0) -> AMBIENTE VERDE RESIDUOS LTDA | D5: Evandrea | E5: 00001097 | F5: 45839 | G5: 2690 | H5: =VLOOKUP(E5&B5,'Conf Oracle'!A:F,6,0) -> 45853.654 | I5: LANÇADO | J5: =IF(OR(ISBLANK(F5), ISBLANK(H5)), "", IFERROR(NETWORKDAYS(F5, H5), "")) -> 11
A6: 45846 | B6: 16554325000156 | C6: =VLOOKUP(B6,Fornecedores!A:B,2,0) -> AMBIENTE VERDE RESIDUOS LTDA | D6: Evandrea | E6: 00001096 | F6: 45839 | G6: 2690 | H6: =VLOOKUP(E6&B6,'Conf Oracle'!A:F,6,0) -> 45853.475 | I6: LANÇADO | J6: =IF(OR(ISBLANK(F6), ISBLANK(H6)), "", IFERROR(NETWORKDAYS(F6, H6), "")) -> 11
A7: 45846 | B7: 94001641000104 | C7: =VLOOKUP(B7,Fornecedores!A:B,2,0) -> BRINGER DO BRASIL AG CARGAS NAC INT LTDA | D7: Evandrea | E7: 00578467 | F7: 45841 | G7: 763.96 | H7: =VLOOKUP(E7&B7,'Conf Oracle'!A:F,6,0) -> 45852.473 | I7: LANÇADO | J7: =IF(OR(ISBLANK(F7), ISBLANK(H7)), "", IFERROR(NETWORKDAYS(F7, H7), "")) -> 8
A8: 45846 | B8: 16554325000156 | C8: =VLOOKUP(B8,Fornecedores!A:B,2,0) -> AMBIENTE VERDE RESIDUOS LTDA | D8: Evandrea | E8: 00001120 | F8: 45842 | G8: 4884.5 | H8: 45849 | I8: NOTA CANCELADA EMITIDA UMA NOVA Nº1138, VALOR DE R$8.934,50 | J8: =IF(OR(ISBLANK(F8), ISBLANK(H8)), "", IFERROR(NETWORKDAYS(F8, H8), "")) -> 6
A9: 45846 | B9: 01092686002366 | C9: =VLOOKUP(B9,Fornecedores!A:B,2,0) -> JOHNSON CONTROLS BE DO BRASIL LTDA | D9: Guilherme | E9: 00129763 | F9: 45839 | G9: 29368.98 | H9: =VLOOKUP(E9&B9,'Conf Oracle'!A:F,6,0) -> 45848.46 | I9: LANÇADA | J9: =IF(OR(ISBLANK(F9), ISBLANK(H9)), "", IFERROR(NETWORKDAYS(F9, H9), "")) -> 8
A10: 45846 | B10: 01092686002366 | C10: =VLOOKUP(B10,Fornecedores!A:B,2,0) -> JOHNSON CONTROLS BE DO BRASIL LTDA | D10: Guilherme | E10: 00129767 | F10: 45839 | G10: 30505.73 | H10: 45839 | I10: NF DE SAÍDA DE MERCADORIA, NÃO SERÁ LANÇADA | J10: =IF(OR(ISBLANK(F10), ISBLANK(H10)), "", IFERROR(NETWORKDAYS(F10, H10), "")) -> 1
A11: 45846 | B11: 52852468000108 | C11: =VLOOKUP(B11,Fornecedores!A:B,2,0) -> Grupo BWX | D11: Guilherme | E11: 00202539 | F11: 45839 | G11: 22000 | H11: =VLOOKUP(E11&B11,'Conf Oracle'!A:F,6,0) -> 45841.383 | J11: =IF(OR(ISBLANK(F11), ISBLANK(H11)), "", IFERROR(NETWORKDAYS(F11, H11), "")) -> 3
A12: 45846 | B12: 58652678000139 | C12: =VLOOKUP(B12,Fornecedores!A:B,2,0) -> COLUMBIA STORAGE INTEGR DE SITEMAS LTDA | D12: Ingrid | E12: 00011187 | F12: 45839 | G12: 17116.41 | H12: =VLOOKUP(E12&B12,'Conf Oracle'!A:F,6,0) -> 45861.692 | J12: =IF(OR(ISBLANK(F12), ISBLANK(H12)), "", IFERROR(NETWORKDAYS(F12, H12), "")) -> 17
A13: 45846 | B13: 17234781000181 | C13: =VLOOKUP(B13,Fornecedores!A:B,2,0) -> CONSESPE ENGENHEIROS ASSOCIADOS SS LTDA | D13: Ingrid | E13: 00003320 | F13: 45839 | G13: 57000 | H13: =VLOOKUP(E13&B13,'Conf Oracle'!A:F,6,0) -> 45861.356 | I13: Lançada | J13: =IF(OR(ISBLANK(F13), ISBLANK(H13)), "", IFERROR(NETWORKDAYS(F13, H13), "")) -> 17
A14: 45846 | B14: 07850212000107 | C14: =VLOOKUP(B14,Fornecedores!A:B,2,0) -> REAL SEGURANCA INTEGRADA EIRELI | D14: Ingrid | E14: 00001324 | F14: 45839 | G14: 217.9 | H14: =VLOOKUP(E14&B14,'Conf Oracle'!A:F,6,0) -> 45862.405 | J14: =IF(OR(ISBLANK(F14), ISBLANK(H14)), "", IFERROR(NETWORKDAYS(F14, H14), "")) -> 18
A15: 45846 | B15: 23412247000110 | C15: =VLOOKUP(B15,Fornecedores!A:B,2,0) -> AMAZON AWS SERVICOS BRASIL LTDA | D15: Ingrid | E15: 04522682 | F15: 45839 | G15: 571110.83 | H15: =VLOOKUP(E15&B15,'Conf Oracle'!A:F,6,0) -> 45860.624 | J15: =IF(OR(ISBLANK(F15), ISBLANK(H15)), "", IFERROR(NETWORKDAYS(F15, H15), "")) -> 16
A16: 45846 | B16: 23412247000110 | C16: =VLOOKUP(B16,Fornecedores!A:B,2,0) -> AMAZON AWS SERVICOS BRASIL LTDA | D16: Ingrid | E16: 04524267 | F16: 45839 | G16: 71814.74 | H16: =VLOOKUP(E16&B16,'Conf Oracle'!A:F,6,0) -> 45860.408 | J16: =IF(OR(ISBLANK(F16), ISBLANK(H16)), "", IFERROR(NETWORKDAYS(F16, H16), "")) -> 16
A17: 45846 | B17: 23412247000110 | C17: =VLOOKUP(B17,Fornecedores!A:B,2,0) -> AMAZON AWS SERVICOS BRASIL LTDA | D17: Ingrid | E17: 04524151 | F17: 45839 | G17: 114085.1 | H17: =VLOOKUP(E17&B17,'Conf Oracle'!A:F,6,0) -> 45860.619 | J17: =IF(OR(ISBLANK(F17), ISBLANK(H17)), "", IFERROR(NETWORKDAYS(F17, H17), "")) -> 16
A18: 45846 | B18: 15491115000101 | C18: =VLOOKUP(B18,Fornecedores!A:B,2,0) -> CS INTEGRA SOLUCOES EM TECNOLOG LTDA ME | D18: Isabela | E18: 00006399 | F18: 45839 | G18: 3093 | H18: =VLOOKUP(E18&B18,'Conf Oracle'!A:F,6,0) -> 45846.374 | J18: =IF(OR(ISBLANK(F18), ISBLANK(H18)), "", IFERROR(NETWORKDAYS(F18, H18), "")) -> 6
A19: 45846 | B19: 26409092000151 | C19: =VLOOKUP(B19,Fornecedores!A:B,2,0) -> SSAMRO SOLUCOES PARA MANUTENCAO INDUSTR | D19: Isabela | E19: 00025446 | F19: 45839 | G19: 648.76 | H19: =VLOOKUP(E19&B19,'Conf Oracle'!A:F,6,0) -> 45845.496 | J19: =IF(OR(ISBLANK(F19), ISBLANK(H19)), "", IFERROR(NETWORKDAYS(F19, H19), "")) -> 5
A20: 45846 | B20: 26409092000151 | C20: =VLOOKUP(B20,Fornecedores!A:B,2,0) -> SSAMRO SOLUCOES PARA MANUTENCAO INDUSTR | D20: Isabela | E20: 00025447 | F20: 45839 | G20: 648.76 | H20: =VLOOKUP(E20&B20,'Conf Oracle'!A:F,6,0) -> 45845.628 | J20: =IF(OR(ISBLANK(F20), ISBLANK(H20)), "", IFERROR(NETWORKDAYS(F20, H20), "")) -> 5
A21: 45846 | B21: 26409092000151 | C21: =VLOOKUP(B21,Fornecedores!A:B,2,0) -> SSAMRO SOLUCOES PARA MANUTENCAO INDUSTR | D21: Isabela | E21: 00025453 | F21: 45839 | G21: 648.76 | H21: =VLOOKUP(E21&B21,'Conf Oracle'!A:F,6,0) -> 45845.624 | J21: =IF(OR(ISBLANK(F21), ISBLANK(H21)), "", IFERROR(NETWORKDAYS(F21, H21), "")) -> 5
A22: 45846 | B22: 26409092000151 | C22: =VLOOKUP(B22,Fornecedores!A:B,2,0) -> SSAMRO SOLUCOES PARA MANUTENCAO INDUSTR | D22: Isabela | E22: 00025461 | F22: 45839 | G22: 648.76 | H22: =VLOOKUP(E22&B22,'Conf Oracle'!A:F,6,0) -> 45845.494 | J22: =IF(OR(ISBLANK(F22), ISBLANK(H22)), "", IFERROR(NETWORKDAYS(F22, H22), "")) -> 5
A23: 45846 | B23: 87169900001389 | C23: =VLOOKUP(B23,Fornecedores!A:B,2,0) -> GRABER SISTEMAS DE SEGURANCA LTDA | D23: Isabela | E23: 00001561 | F23: 45840 | G23: 111691.36 | H23: =VLOOKUP(E23&B23,'Conf Oracle'!A:F,6,0) -> 45845.706 | J23: =IF(OR(ISBLANK(F23), ISBLANK(H23)), "", IFERROR(NETWORKDAYS(F23, H23), "")) -> 4
A24: 45846 | B24: 72157654000215 | C24: =VLOOKUP(B24,Fornecedores!A:B,2,0) -> VELA SOFTWARE E SERVICOS LTDA | D24: Isabela | E24: 00011985 | F24: 45841 | G24: 677.6 | H24: =VLOOKUP(E24&B24,'Conf Oracle'!A:F,6,0) -> 45846.626 | J24: =IF(OR(ISBLANK(F24), ISBLANK(H24)), "", IFERROR(NETWORKDAYS(F24, H24), "")) -> 4
